Workbook

Sheet Details local delivery
A1: WEEK | B1: N° Voyage | C1: Date PICK UP | D1: MOIS | E1: Matricule | F1: Chauffeur | G1: N° Voyage | H1: Delivery address | I1: Matricule | J1: Max weight truck | K1: weight | L1: Max Nbr of position truck | M1: POSITION | N1: Matricule | O1: Chauffeur | P1: ETD COF TN | Q1: Real ETD COF TN | R1: objectif ETA CLINET | S1: REAL ETA Customer | T1: Real ETD Customer | U1: ETA COFICAB | V1: real ETA COFICAB | W1: OTD | X1: kM | Y1: Stationnement | Z1: trajet allé | AA1: trajet Retour | AB1: cause | AC1: NEW OTD
B2: VOY2026COFTN01 | C2: 46024 | D2: Janvier | E2: 5735tu217 | F2: Bilel | G2: VOY2026COFTN01 | H2: ADC Sousse | I2: 5735tu217 | J2: 10200 | K2: 7100 | L2: 14 | M2: 10 | N2: 5735tu217 | O2: Bilel | P2: 0.29166667 | W2: =IFERROR(IF(S2<R2,100%,"100"%-(S2-R2)*1.2),"-") -> 1 | AC2: =IFERROR(IF(Y2<X2,100%,"100"%-(Y2-X2)*1.2),"-") -> 1
B3: VOY2026COFTN02 | C3: 46024 | D3: Janvier | E3: 4331tu175 | F3: Mehrez | G3: VOY2026COFTN02 | H3: ADC Sousse | I3: 4331tu175 | J3: 9200 | K3: 7000 | L3: 14 | M3: 10 | N3: 4331tu175 | O3: Mehrez | P3: 0.375 | W3: =IFERROR(IF(S3<R3,100%,"100"%-(S3-R3)*1.2),"-") -> 1 | AC3: =IFERROR(IF(Y3<X3,100%,"100"%-(Y3-X3)*1.2),"-") -> 1
B4: VOY2026COFTN03 | C4: 46024 | D4: Janvier | E4: 4331tu175 | F4: mehrez | G4: VOY2026COFTN03 | H4: COFAT TUNIS | I4: 4331tu175 | J4: 9200 | K4: 7000 | L4: 14 | M4: 10 | N4: 4331tu175 | O4: mehrez | P4: 0.29166667 | W4: =IFERROR(IF(S4<R4,100%,"100"%-(S4-R4)*1.2),"-") -> 1 | AC4: =IFERROR(IF(Y4<X4,100%,"100"%-(Y4-X4)*1.2),"-") -> 1
B5: VOY2026COFTN04 | C5: 46025 | D5: Janvier | E5: 4331tu175 | F5: mehrez | G5: VOY2026COFTN04 | H5: LEONI Wiring Systems Tunisia SUD | I5: 4331tu175 | J5: 9200 | K5: 7000 | L5: 14 | M5: 10 | N5: 4331tu175 | O5: mehrez | P5: 0.29166667 | W5: =IFERROR(IF(S5<R5,100%,"100"%-(S5-R5)*1.2),"-") -> 1 | AC5: =IFERROR(IF(Y5<X5,100%,"100"%-(Y5-X5)*1.2),"-") -> 1
B6: VOY2026COFTN05 | C6: 46027 | D6: Janvier | E6: REM107627 | F6: karim | G6: VOY2026COFTN05 | H6: WeWire Hammamet Tunisia SARL | I6: REM107627 | J6: 24950 | K6: 23000 | L6: 27 | M6: 10 | N6: REM107627 | O6: karim | P6: 0.41666667 | Q6: 0.31597222 | R6: 0.5 | S6: 0.375 | T6: 0.43055556 | U6: 0.47916667 | V6: 0.47916667 | W6: =IFERROR(IF(S6<R6,100%,"100"%-(S6-R6)*1.2),"-") -> 1 | AC6: =IFERROR(IF(Y6<X6,100%,"100"%-(Y6-X6)*1.2),"-") -> 1
B7: VOY2026COFTN06 | C7: 46027 | D7: Janvier | E7: REM107627 | F7: karim | G7: VOY2026COFTN06 | H7: ELECTROCONTACT TUNISIE | I7: REM107627 | J7: 24950 | K7: 22303 | L7: 27 | M7: 10 | N7: REM107627 | O7: karim | P7: 0.29166667 | Q7: 0.56597222 | R7: 0.75 | S7: 0.73958333 | T7: 0.79166667 | U7: 0.98958333 | V7: 0.98958333 | W7: =IFERROR(IF(S7<R7,100%,"100"%-(S7-R7)*1.2),"-") -> 1 | AC7: =IFERROR(IF(Y7<X7,100%,"100"%-(Y7-X7)*1.2),"-") -> 1
B8: VOY2026COFTN07 | C8: 46027 | D8: Janvier | E8: 7797tu218 | F8: Houssem | G8: VOY2026COFTN07 | H8: COFAT TUNIS | I8: 7797tu218 | J8: 927 | K8: 500 | L8: 3 | M8: 1 | N8: 7797tu218 | O8: Houssem | P8: 0.5 | W8: =IFERROR(IF(S8<R8,100%,"100"%-(S8-R8)*1.2),"-") -> 1 | AC8: =IFERROR(IF(Y8<X8,100%,"100"%-(Y8-X8)*1.2),"-") -> 1
B9: VOY2026COFTN07 | C9: 46027 | D9: Janvier | E9: Location | F9: Location | G9: VOY2026COFTN07 | H9: LEONI Wiring Systems Tunisia NORD | I9: Location | N9: SEMI REMORQUE | O9: SEMI REMORQUE | P9: 0.5 | Q9: 0.73958333 | R9: 0.5 | S9: 0.79861111 | T9: 0.86458333 | U9: 0.92708333 | V9: 0.92708333 | W9: =IFERROR(IF(S9<R9,100%,"100"%-(S9-R9)*1.2),"-") -> 0.64166667 | AB9: retard production | AC9: =IFERROR(IF(Y9<X9,100%,"100"%-(Y9-X9)*1.2),"-") -> 1
B10: VOY2026COFTN07 | C10: 46027 | D10: Janvier | E10: Location | F10: Location | G10: VOY2026COFTN07 | H10: TTE International | I10: Location | N10: SEMI REMORQUE | O10: SEMI REMORQUE | P10: 0.5 | W10: =IFERROR(IF(S10<R10,100%,"100"%-(S10-R10)*1.2),"-") -> 1 | AC10: =IFERROR(IF(Y10<X10,100%,"100"%-(Y10-X10)*1.2),"-") -> 1
B11: VOY2026COFTN08 | C11: 46027 | D11: Janvier | E11: Location | F11: Location | G11: VOY2026COFTN08 | H11: KAB-LEM Tunisia SARL | I11: Location | K11: 936 | L11: 4 | N11: SEMI REMORQUE | O11: SEMI REMORQUE | P11: 0.29166667 | W11: =IFERROR(IF(S11<R11,100%,"100"%-(S11-R11)*1.2),"-") -> 1 | AC11: =IFERROR(IF(Y11<X11,100%,"100"%-(Y11-X11)*1.2),"-") -> 1
B12: VOY2026COFTN09 | C12: 46027 | D12: Janvier | E12: 4331tu175 | F12: mehrez | G12: VOY2026COFTN09 | H12: COFAT MATEUR | I12: 4331tu175 | J12: 9200 | K12: 2100 | L12: 14 | M12: 10 | N12: 4331tu175 | O12: mehrez | P12: 0.41666667 | Q12: 0.73958333 | R12: 0.5 | S12: 0.79861111 | T12: 0.86458333 | U12: 0.92708333 | V12: 0.92708333 | W12: =IFERROR(IF(S12<R12,100%,"100"%-(S12-R12)*1.2),"-") -> 0.64166667 | AB12: retard production | AC12: =IFERROR(IF(Y12<X12,100%,"100"%-(Y12-X12)*1.2),"-") -> 1
B13: VOY2026COFTN10 | C13: 46027 | D13: Janvier | E13: 7797tu218 | F13: Houssem | G13: VOY2026COFTN10 | H13: SE BORDNETZE EL FEJJA S.A.R.L | I13: 7797tu218 | J13: 927 | K13: 500 | L13: 3 | M13: 1 | N13: 7797tu218 | O13: Houssem | P13: 0.25 | Q13: 0.46875 | R13: 0.75 | S13: 0.48958333 | T13: 0.51041667 | U13: 0.54166667 | V13: 0.54166667 | W13: =IFERROR(IF(S13<R13,100%,"100"%-(S13-R13)*1.2),"-") -> 1 | AC13: =IFERROR(IF(Y13<X13,100%,"100"%-(Y13-X13)*1.2),"-") -> 1
B14: VOY2026COFTN11 | C14: 46027 | D14: Janvier | E14: 5735tu217 | F14: Bilel | G14: VOY2026COFTN11 | H14: LEONI Wiring Systems Tunisia SUD | I14: 5735tu217 | J14: 10200 | K14: 7100 | L14: 14 | M14: 10 | N14: 5735tu217 | O14: Bilel | P14: 0.29166667 | W14: =IFERROR(IF(S14<R14,100%,"100"%-(S14-R14)*1.2),"-") -> 1 | AC14: =IFERROR(IF(Y14<X14,100%,"100"%-(Y14-X14)*1.2),"-") -> 1
B15: VOY2026COFTN12 | C15: 46027 | D15: Janvier | E15: 2282tu131 | F15: Hbib | G15: VOY2026COFTN12 | H15: YURA CORPORATION TUNISIA | I15: 2282tu131 | J15: 10200 | K15: 2810.6 | L15: 14 | M15: 10 | N15: 2282tu131 | O15: Hbib | P15: 0.5 | Q15: 0.41666667 | R15: 0.5 | S15: 0.57638889 | T15: 0.66666667 | U15: 0.82638889 | V15: 0.82638889 | W15: =IFERROR(IF(S15<R15,100%,"100"%-(S15-R15)*1.2),"-") -> 0.90833333 | AB15: retard production | AC15: =IFERROR(IF(Y15<X15,100%,"100"%-(Y15-X15)*1.2),"-") -> 1
B16: VOY2026COFTN13 | C16: 46027 | D16: Janvier | E16: 5735tu217 | F16: Bilel | G16: VOY2026COFTN13 | H16: Aptiv Services Tunisia SARL | I16: 5735tu217 | J16: 10200 | K16: 6500 | L16: 14 | M16: 10 | N16: 5735tu217 | O16: Bilel | P16: 0.41666667 | W16: =IFERROR(IF(S16<R16,100%,"100"%-(S16-R16)*1.2),"-") -> 1 | AC16: =IFERROR(IF(Y16<X16,100%,"100"%-(Y16-X16)*1.2),"-") -> 1
B17: VOY2026COFTN14 | C17: 46027 | D17: Janvier | E17: 5735tu217 | F17: Bilel | G17: VOY2026COFTN14 | H17: METS MANUFAC ELECTRO.DE SOUSSE | I17: 5735tu217 | J17: 10200 | K17: 7100 | L17: 14 | M17: 10 | N17: 5735tu217 | O17: Bilel | P17: 0.5 | W17: =IFERROR(IF(S17<R17,100%,"100"%-(S17-R17)*1.2),"-") -> 1 | AC17: =IFERROR(IF(Y17<X17,100%,"100"%-(Y17-X17)*1.2),"-") -> 1
B18: VOY2026COFTN15 | C18: 46027 | D18: Janvier | E18: 7797tu218 | F18: ala | G18: VOY2026COFTN15 | H18: Yazaki Automotive Products Tunisia | I18: 7797tu218 | J18: 927 | K18: 500 | L18: 3 | M18: 1 | N18: 7797tu218 | O18: ala | P18: 0.25 | W18: =IFERROR(IF(S18<R18,100%,"100"%-(S18-R18)*1.2),"-") -> 1 | AC18: =IFERROR(IF(Y18<X18,100%,"100"%-(Y18-X18)*1.2),"-") -> 1
B19: VOY2026COFTN16 | C19: 46027 | D19: Janvier | E19: 9524TU238 | F19: Ridha | G19: VOY2026COFTN16 | H19: SCHULTE AUTOMOTIVE TUNISIA srl | I19: 9524TU238 | J19: 10230 | K19: 10000 | L19: 14 | M19: 10 | N19: 9524TU238 | O19: Ridha | P19: 0.70833333 | Q19: 0.70833333 | R19: 0.625 | S19: 0.75 | T19: 0.70833333 | U19: 0.83333333 | V19: 0.83333333 | W19: =IFERROR(IF(S19<R19,100%,"100"%-(S19-R19)*1.2),"-") -> 0.85 | AB19: retard production | AC19: =IFERROR(IF(Y19<X19,100%,"100"%-(Y19-X19)*1.2),"-") -> 1
B20: VOY2026COFTN17 | C20: 46027 | D20: Janvier | E20: 5735tu217 | F20: bilel | G20: VOY2026COFTN17 | H20: LEONI Wiring Systems Tunisia SUD | I20: 5735tu217 | J20: 10200 | K20: 7100 | L20: 14 | M20: 10 | N20: 5735tu217 | O20: bilel | P20: 0.29166667 | Q20: 0.29166667 | R20: 0.5 | S20: 0.35416667 | T20: 0.41666667 | U20: 0.47916667 | V20: 0.47916667 | W20: =IFERROR(IF(S20<R20,100%,"100"%-(S20-R20)*1.2),"-") -> 1 | AC20: =IFERROR(IF(Y20<X20,100%,"100"%-(Y20-X20)*1.2),"-") -> 1
B21: VOY2026COFTN18 | C21: 46027 | D21: Janvier | E21: 5735tu217 | F21: bilel | G21: VOY2026COFTN18 | H21: METS MANUFAC ELECTRO.DE SOUSSE | I21: 5735tu217 | J21: 10200 | K21: 7100 | L21: 14 | M21: 10 | N21: 5735tu217 | O21: bilel | P21: 0.5 | Q21: 0.5625 | R21: 0.75 | S21: 0.63888889 | T21: 0.70833333 | U21: 0.83333333 | V21: 0.83333333 | W21: =IFERROR(IF(S21<R21,100%,"100"%-(S21-R21)*1.2),"-") -> 1 | AC21: =IFERROR(IF(Y21<X21,100%,"100"%-(Y21-X21)*1.2),"-") -> 1
B22: VOY2026COFTN19 | C22: 46028 | D22: Janvier | E22: REM107627 | F22: karim | G22: VOY2026COFTN19 | H22: LEONI Wiring Systems Tunisia NORD | I22: REM107627 | J22: 24950 | K22: 10200 | L22: 27 | M22: 14 | N22: REM107627 | O22: karim | P22: 0.29166667 | Q22: 0.46527778 | R22: 0.5 | S22: 0.55208333 | T22: 0.77083333 | U22: 0.83333333 | V22: 0.83333333 | W22: =IFERROR(IF(S22<R22,100%,"100"%-(S22-R22)*1.2),"-") -> 0.9375 | AB22: retard production | AC22: =IFERROR(IF(Y22<X22,100%,"100"%-(Y22-X22)*1.2),"-") -> 1
B23: VOY2026COFTN19 | C23: 46028 | D23: Janvier | E23: REM107627 | F23: karim | G23: VOY2026COFTN19 | H23: LEONI Wiring Systems Tunisia SUD | I23: REM107627 | J23: 24950 | K23: 10200 | L23: 27 | M23: 10 | N23: REM107627 | O23: karim | P23: 0.29166667 | Q23: 0.46527778 | R23: 0.5 | S23: 0.55208333 | T23: 0.77083333 | U23: 0.83333333 | V23: 0.83333333 | W23: =IFERROR(IF(S23<R23,100%,"100"%-(S23-R23)*1.2),"-") -> 0.9375 | AB23: retard production | AC23: =IFERROR(IF(Y23<X23,100%,"100"%-(Y23-X23)*1.2),"-") -> 1
B24: VOY2026COFTN20 | C24: 46028 | D24: Janvier | E24: 4331tu175 | F24: mehrez | G24: VOY2026COFTN20 | H24: COFAT MATEUR | I24: 4331tu175 | J24: 9200 | K24: 5500 | L24: 14 | M24: 14 | N24: 4331tu175 | O24: mehrez | P24: 0.58333333 | W24: =IFERROR(IF(S24<R24,100%,"100"%-(S24-R24)*1.2),"-") -> 1 | AC24: =IFERROR(IF(Y24<X24,100%,"100"%-(Y24-X24)*1.2),"-") -> 1
B25: VOY2026COFTN21 | C25: 46028 | D25: Janvier | E25: Location | F25: Location | G25: VOY2026COFTN21 | H25: SEBN (SUMITOMO) | I25: Location | M25: 16 | N25: SEMI REMORQUE | O25: SEMI REMORQUE | P25: 0.375 | W25: =IFERROR(IF(S25<R25,100%,"100"%-(S25-R25)*1.2),"-") -> 1 | AC25: =IFERROR(IF(Y25<X25,100%,"100"%-(Y25-X25)*1.2),"-") -> 1
B26: VOY2026COFTN21 | C26: 46028 | D26: Janvier | E26: Location | F26: Location | G26: VOY2026COFTN21 | H26: Kromberg & Schubert Tunisie SARL | I26: Location | M26: 17 | N26: SEMI REMORQUE | O26: SEMI REMORQUE | P26: 0.375 | W26: =IFERROR(IF(S26<R26,100%,"100"%-(S26-R26)*1.2),"-") -> 1 | AC26: =IFERROR(IF(Y26<X26,100%,"100"%-(Y26-X26)*1.2),"-") -> 1
B27: VOY2026COFTN22 | C27: 46028 | D27: Janvier | E27: 2282tu131 | F27: Hbib | G27: VOY2026COFTN22 | H27: Aptiv Services Tunisia SARL | I27: 2282tu131 | J27: 10200 | K27: 10200 | L27: 14 | M27: 11 | N27: 2282tu131 | O27: Hbib | P27: 0.3125 | Q27: 0.39930556 | R27: 0.75 | S27: 0.44791667 | T27: 0.49305556 | U27: 0.57291667 | V27: 0.57291667 | W27: =IFERROR(IF(S27<R27,100%,"100"%-(S27-R27)*1.2),"-") -> 1 | AC27: =IFERROR(IF(Y27<X27,100%,"100"%-(Y27-X27)*1.2),"-") -> 1
B28: VOY2026COFTN23 | C28: 46028 | D28: Janvier | E28: 2282tu131 | F28: Hbib | G28: VOY2026COFTN23 | H28: WeWire Hammamet Tunisia SARL | I28: 2282tu131 | J28: 10200 | K28: 10000 | L28: 14 | M28: 10 | N28: 2282tu131 | O28: Hbib | P28: 0.5 | Q28: 0.65972222 | R28: 0.75 | S28: 0.72916667 | T28: 0.77083333 | U28: 0.82638889 | V28: 0.82638889 | W28: =IFERROR(IF(S28<R28,100%,"100"%-(S28-R28)*1.2),"-") -> 1 | AC28: =IFERROR(IF(Y28<X28,100%,"100"%-(Y28-X28)*1.2),"-") -> 1
B29: VOY2026COFTN24 | C29: 46028 | D29: Janvier | E29: 7797tu218 | F29: Houssem | G29: VOY2026COFTN24 | H29: COFAT TUNIS | I29: 7797tu218 | J29: 927 | K29: 500 | L29: 3 | M29: 3 | N29: 7797tu218 | O29: Houssem | P29: 0.29166667 | W29: =IFERROR(IF(S29<R29,100%,"100"%-(S29-R29)*1.2),"-") -> 1 | AC29: =IFERROR(IF(Y29<X29,100%,"100"%-(Y29-X29)*1.2),"-") -> 1
B30: VOY2026COFTN25 | C30: 46028 | D30: Janvier | E30: 9524TU238 | F30: Ridha | G30: VOY2026COFTN25 | H30: perplastic | I30: 9524TU238 | J30: 10230 | K30: 10200 | L30: 14 | M30: 10 | N30: 9524TU238 | O30: Ridha | P30: 0.5 | Q30: 0.29166667 | R30: 0.5 | S30: 0.3125 | T30: 0.35416667 | U30: 0.41666667 | V30: 0.41666667 | W30: =IFERROR(IF(S30<R30,100%,"100"%-(S30-R30)*1.2),"-") -> 1 | AC30: =IFERROR(IF(Y30<X30,100%,"100"%-(Y30-X30)*1.2),"-") -> 1
B31: VOY2026COFTN26 | C31: 46028 | D31: Janvier | E31: 9524TU238 | F31: Ridha | G31: VOY2026COFTN26 | H31: SCHULTE AUTOMOTIVE TUNISIA srl | I31: 9524TU238 | J31: 10230 | K31: 10200 | L31: 14 | M31: 14 | N31: 9524TU238 | O31: Ridha | P31: 0.625 | Q31: 0.625 | W31: =IFERROR(IF(S31<R31,100%,"100"%-(S31-R31)*1.2),"-") -> 1 | AC31: =IFERROR(IF(Y31<X31,100%,"100"%-(Y31-X31)*1.2),"-") -> 1
B32: VOY2026COFTN27 | C32: 46028 | D32: Janvier | E32: 4331tu175 | F32: mehrez | G32: VOY2026COFTN27 | H32: A C T Assemblage Cable Tunisie | I32: 4331tu175 | J32: 9200 | K32: 5000 | L32: 14 | M32: 7 | N32: 4331tu175 | O32: mehrez | P32: 0.20833333 | Q32: 0.29166667 | R32: 0.5 | S32: 0.33333333 | T32: 0.41666667 | U32: 0.45833333 | V32: 0.45833333 | W32: =IFERROR(IF(S32<R32,100%,"100"%-(S32-R32)*1.2),"-") -> 1 | AC32: =IFERROR(IF(Y32<X32,100%,"100"%-(Y32-X32)*1.2),"-") -> 1
B33: VOY2026COFTN28 | C33: 46028 | D33: Janvier | E33: 4331tu175 | F33: mehrez | G33: VOY2026COFTN28 | H33: COFAT MATEUR | I33: 4331tu175 | J33: 9200 | K33: 6000 | L33: 14 | M33: 14 | N33: 4331tu175 | O33: mehrez | P33: 0.75 | Q33: 0.6875 | R33: 0.75 | S33: 0.76388889 | T33: 0.79166667 | U33: 0.875 | V33: 0.875 | W33: =IFERROR(IF(S33<R33,100%,"100"%-(S33-R33)*1.2),"-") -> 0.98333333 | AB33: retard production | AC33: =IFERROR(IF(Y33<X33,100%,"100"%-(Y33-X33)*1.2),"-") -> 1
B34: VOY2026COFTN29 | C34: 46028 | D34: Janvier | E34: Location | F34: Location | G34: VOY2026COFTN29 | H34: MEDITERRANEAN ELECTRIC WIRING | I34: Location | M34: 7 | N34: SEMI REMORQUE | O34: SEMI REMORQUE | P34: 0.29166667 | W34: =IFERROR(IF(S34<R34,100%,"100"%-(S34-R34)*1.2),"-") -> 1 | AC34: =IFERROR(IF(Y34<X34,100%,"100"%-(Y34-X34)*1.2),"-") -> 1
B35: VOY2026COFTN29 | C35: 46028 | D35: Janvier | E35: Location | F35: Location | G35: VOY2026COFTN29 | H35: YURA CORPORATION TUNISIA | I35: Location | M35: 20 | N35: SEMI REMORQUE | O35: SEMI REMORQUE | P35: 0.29166667 | W35: =IFERROR(IF(S35<R35,100%,"100"%-(S35-R35)*1.2),"-") -> 1 | AC35: =IFERROR(IF(Y35<X35,100%,"100"%-(Y35-X35)*1.2),"-") -> 1
B36: VOY2026COFTN30 | C36: 46028 | D36: Janvier | E36: 2282tu131 | F36: ala | G36: VOY2026COFTN30 | H36: COFAT MATEUR | I36: 2282tu131 | J36: 10200 | K36: 10000 | L36: 14 | M36: 10 | N36: 2282tu131 | O36: ala | P36: 0.33333333 | Q36: 0.91666667 | R36: 0.91666667 | S36: 0.5 | T36: 0.083333333 | U36: 0.19444444 | V36: 0.19444444 | W36: =IFERROR(IF(S36<R36,100%,"100"%-(S36-R36)*1.2),"-") -> 1 | AC36: =IFERROR(IF(Y36<X36,100%,"100"%-(Y36-X36)*1.2),"-") -> 1
B37: VOY2026COFTN31 | C37: 46029 | D37: Janvier | E37: 9524TU238 | F37: Ridha | G37: VOY2026COFTN31 | H37: LEONI Wiring Systems Tunisia SUD | I37: 9524TU238 | J37: 10230 | K37: 8000 | L37: 14 | M37: 11 | N37: 9524TU238 | O37: Ridha | P37: 0.29166667 | Q37: 0.38888889 | R37: 0.5 | S37: 0.45833333 | T37: 0.5 | U37: 0.58333333 | V37: 0.58333333 | W37: =IFERROR(IF(S37<R37,100%,"100"%-(S37-R37)*1.2),"-") -> 1 | AC37: =IFERROR(IF(Y37<X37,100%,"100"%-(Y37-X37)*1.2),"-") -> 1
B38: VOY2026COFTN32 | C38: 46029 | D38: Janvier | E38: 9524TU238 | F38: Ridha | G38: VOY2026COFTN32 | H38: perplastic | I38: 9524TU238 | J38: 10230 | K38: 10000 | L38: 14 | M38: 9 | N38: 9524TU238 | O38: Ridha | P38: 0.5 | Q38: 0.58333333 | R38: 0.75 | S38: 0.60416667 | T38: 0.64583333 | U38: 0.70833333 | V38: 0.70833333 | W38: =IFERROR(IF(S38<R38,100%,"100"%-(S38-R38)*1.2),"-") -> 1 | AC38: =IFERROR(IF(Y38<X38,100%,"100"%-(Y38-X38)*1.2),"-") -> 1
B39: VOY2026COFTN33 | C39: 46029 | D39: Janvier | E39: Location | F39: Location | G39: VOY2026COFTN33 | H39: SEWS TN SARL | I39: Location | M39: 7 | N39: SEMI REMORQUE | O39: SEMI REMORQUE | P39: 0.375 | W39: =IFERROR(IF(S39<R39,100%,"100"%-(S39-R39)*1.2),"-") -> 1 | AC39: =IFERROR(IF(Y39<X39,100%,"100"%-(Y39-X39)*1.2),"-") -> 1
B40: VOY2026COFTN33 | C40: 46029 | D40: Janvier | E40: Location | F40: Location | G40: VOY2026COFTN33 | H40: ELECTROCONTACT TUNISIE | I40: Location | M40: 15 | N40: SEMI REMORQUE | O40: SEMI REMORQUE | P40: 0.375 | W40: =IFERROR(IF(S40<R40,100%,"100"%-(S40-R40)*1.2),"-") -> 1 | AC40: =IFERROR(IF(Y40<X40,100%,"100"%-(Y40-X40)*1.2),"-") -> 1
B41: VOY2026COFTN34 | C41: 46029 | D41: Janvier | E41: 4331tu175 | F41: mehrez | G41: VOY2026COFTN34 | H41: COFAT MATEUR | I41: 4331tu175 | J41: 9200 | K41: 6000 | L41: 14 | M41: 11 | N41: 4331tu175 | O41: mehrez | P41: 0.29166667 | Q41: 0.29166667 | R41: 0.5 | S41: 0.375 | T41: 0.45833333 | U41: 0.54166667 | V41: 0.54166667 | W41: =IFERROR(IF(S41<R41,100%,"100"%-(S41-R41)*1.2),"-") -> 1 | AC41: =IFERROR(IF(Y41<X41,100%,"100"%-(Y41-X41)*1.2),"-") -> 1
B42: VOY2026COFTN35 | C42: 46029 | D42: Janvier | E42: 2282tu131 | F42: Hbib | G42: VOY2026COFTN35 | H42: COFAT TUNIS | I42: 2282tu131 | J42: 10200 | K42: 10000 | L42: 14 | M42: 10 | N42: 2282tu131 | O42: Hbib | P42: 0.33333333 | Q42: 0.33333333 | R42: 0.5 | S42: 0.33680556 | T42: 0.35416667 | U42: 0.35763889 | V42: 0.35763889 | W42: =IFERROR(IF(S42<R42,100%,"100"%-(S42-R42)*1.2),"-") -> 1 | AC42: =IFERROR(IF(Y42<X42,100%,"100"%-(Y42-X42)*1.2),"-") -> 1
B43: VOY2026COFTN36 | C43: 46029 | D43: Janvier | E43: 2282tu131 | F43: Hbib | G43: VOY2026COFTN36 | H43: DIS Draxlmaier Indust Solution Gmbh | I43: 2282tu131 | J43: 10200 | K43: 5000 | L43: 14 | M43: 5 | N43: 2282tu131 | O43: Hbib | P43: 0.41666667 | W43: =IFERROR(IF(S43<R43,100%,"100"%-(S43-R43)*1.2),"-") -> 1 | AC43: =IFERROR(IF(Y43<X43,100%,"100"%-(Y43-X43)*1.2),"-") -> 1
B44: VOY2026COFTN36 | C44: 46029 | D44: Janvier | E44: 2282tu131 | F44: Hbib | G44: VOY2026COFTN36 | H44: Aptiv Services Tunisia SARL | I44: 2282tu131 | J44: 10200 | K44: 2300 | L44: 14 | M44: 3 | N44: 2282tu131 | O44: Hbib | P44: 0.41666667 | Q44: 0.64930556 | R44: 0.5 | S44: 0.70833333 | T44: 0.75 | U44: 0.81597222 | V44: 0.81597222 | W44: =IFERROR(IF(S44<R44,100%,"100"%-(S44-R44)*1.2),"-") -> 0.75 | AB44: retard production | AC44: =IFERROR(IF(Y44<X44,100%,"100"%-(Y44-X44)*1.2),"-") -> 1
B45: VOY2026COFTN37 | C45: 46029 | D45: Janvier | E45: 5735tu217 | F45: Bilel | G45: VOY2026COFTN37 | H45: SCHULTE AUTOMOTIVE TUNISIA srl | I45: 5735tu217 | J45: 10200 | K45: 7100 | L45: 14 | M45: 10 | N45: 5735tu217 | O45: Bilel | P45: 0.41666667 | Q45: 0.58333333 | R45: 0.75 | S45: 0.625 | T45: 0.66666667 | U45: 0.75 | V45: 0.75 | W45: =IFERROR(IF(S45<R45,100%,"100"%-(S45-R45)*1.2),"-") -> 1 | AC45: =IFERROR(IF(Y45<X45,100%,"100"%-(Y45-X45)*1.2),"-") -> 1
B46: VOY2026COFTN38 | C46: 46029 | D46: Janvier | E46: REM107627 | F46: karim | G46: VOY2026COFTN38 | H46: ADC Sousse | I46: REM107627 | J46: 24950 | K46: 14000 | L46: 27 | M46: 27 | N46: REM107627 | O46: karim | P46: 0.25 | Q46: 0.3125 | R46: 0.625 | S46: 0.43055556 | T46: 0.53125 | U46: 0.71875 | V46: 0.71875 | W46: =IFERROR(IF(S46<R46,100%,"100"%-(S46-R46)*1.2),"-") -> 1 | AC46: =IFERROR(IF(Y46<X46,100%,"100"%-(Y46-X46)*1.2),"-") -> 1
B47: VOY2026COFTN39 | C47: 46029 | D47: Janvier | E47: 7797tu218 | F47: Houssem | G47: VOY2026COFTN39 | H47: COELEC TUNISIA | I47: 7797tu218 | J47: 927 | K47: 500 | L47: 3 | M47: 3 | N47: 7797tu218 | O47: Houssem | P47: 0.33333333 | Q47: 0.41666667 | R47: 0.5 | S47: 0.4375 | T47: 0.46180556 | U47: 0.48263889 | V47: 0.48263889 | W47: =IFERROR(IF(S47<R47,100%,"100"%-(S47-R47)*1.2),"-") -> 1 | AC47: =IFERROR(IF(Y47<X47,100%,"100"%-(Y47-X47)*1.2),"-") -> 1
B48: VOY2026COFTN40 | C48: 46029 | D48: Janvier | E48: 7797tu218 | F48: Houssem | G48: VOY2026COFTN40 | H48: COELEC TUNISIA | I48: 7797tu218 | J48: 927 | K48: 500 | L48: 3 | M48: 2 | N48: 7797tu218 | O48: Houssem | P48: 0.41666667 | Q48: 0.33333333 | R48: 0.5 | S48: 0.35416667 | T48: 0.375 | U48: 0.39583333 | V48: 0.39583333 | W48: =IFERROR(IF(S48<R48,100%,"100"%-(S48-R48)*1.2),"-") -> 1 | AC48: =IFERROR(IF(Y48<X48,100%,"100"%-(Y48-X48)*1.2),"-") -> 1
B49: VOY2026COFTN41 | C49: 46029 | D49: Janvier | E49: 7797tu218 | F49: Houssem | G49: VOY2026COFTN41 | H49: LEONI Wiring Systems Tunisia NORD | I49: 7797tu218 | J49: 927 | K49: 500 | L49: 3 | M49: 1 | N49: 7797tu218 | O49: Houssem | P49: 0.5 | Q49: 0.5 | R49: 0.5 | S49: 0.56597222 | T49: 0.67361111 | U49: 0.75 | V49: 0.75 | W49: =IFERROR(IF(S49<R49,100%,"100"%-(S49-R49)*1.2),"-") -> 0.92083333 | AB49: retard production | AC49: =IFERROR(IF(Y49<X49,100%,"100"%-(Y49-X49)*1.2),"-") -> 1
B50: VOY2026COFTN42 | C50: 46029 | D50: Janvier | E50: 7797tu218 | F50: Houssem | G50: VOY2026COFTN42 | H50: WeWire Hammamet Tunisia SARL | I50: 7797tu218 | J50: 927 | K50: 500 | L50: 3 | M50: 1 | N50: 7797tu218 | O50: Houssem | P50: 0.54166667 | W50: =IFERROR(IF(S50<R50,100%,"100"%-(S50-R50)*1.2),"-") -> 1 | AC50: =IFERROR(IF(Y50<X50,100%,"100"%-(Y50-X50)*1.2),"-") -> 1
B51: VOY2026COFTN43 | C51: 46029 | D51: Janvier | E51: Location | F51: Location | G51: VOY2026COFTN43 | H51: YAZAKI TUNISIA s.a.r.l | I51: Location | M51: 5 | N51: POIDS LOURD | O51: MR | P51: 0.125 | W51: =IFERROR(IF(S51<R51,100%,"100"%-(S51-R51)*1.2),"-") -> 1 | AC51: =IFERROR(IF(Y51<X51,100%,"100"%-(Y51-X51)*1.2),"-") -> 1
B52: VOY2026COFTN44 | C52: 46029 | D52: Janvier | E52: 5735tu217 | F52: bilel | G52: VOY2026COFTN44 | H52: navette mateur | I52: 5735tu217 | J52: 10200 | K52: 7100 | L52: 14 | M52: 5 | N52: 5735tu217 | O52: bilel | P52: 0.125 | Q52: 0.069444444 | R52: 0.5 | S52: 002:25 | T52: 03:000 | U52: 0.16666667 | V52: 0.16666667 | W52: =IFERROR(IF(S52<R52,100%,"100"%-(S52-R52)*1.2),"-") -> - | AC52: =IFERROR(IF(Y52<X52,100%,"100"%-(Y52-X52)*1.2),"-") -> 1
B53: VOY2026COFTN45 | C53: 46029 | D53: Janvier | E53: 2282tu131 | F53: ala | G53: VOY2026COFTN45 | H53: LEONI Wiring Systems Tunisia NORD | I53: 2282tu131 | J53: 10200 | K53: 2300 | L53: 14 | M53: 5 | N53: 2282tu131 | O53: ala | P53: 0.875 | Q53: 0.90972222 | R53: 0.9375 | S53: 0.97569444 | T53: 0 | U53: 0.11111111 | V53: 0.11111111 | W53: =IFERROR(IF(S53<R53,100%,"100"%-(S53-R53)*1.2),"-") -> 0.95416667 | AB53: retard production | AC53: =IFERROR(IF(Y53<X53,100%,"100"%-(Y53-X53)*1.2),"-") -> 1
B54: VOY2026COFTN45 | C54: 46029 | D54: Janvier | E54: 2282tu131 | F54: ala | G54: VOY2026COFTN45 | H54: LEONI Wiring Systems Tunisia SUD | I54: 2282tu131 | J54: 10200 | K54: 2300 | L54: 14 | M54: 5 | N54: 2282tu131 | O54: ala | P54: 0.875 | Q54: 0.90972222 | R54: 0.9375 | S54: 0.97569444 | T54: 0 | U54: 0.11111111 | V54: 0.11111111 | W54: =IFERROR(IF(S54<R54,100%,"100"%-(S54-R54)*1.2),"-") -> 0.95416667 | AB54: retard production | AC54: =IFERROR(IF(Y54<X54,100%,"100"%-(Y54-X54)*1.2),"-") -> 1
B55: VOY2026COFTN45 | C55: 46029 | D55: Janvier | E55: 2282tu131 | F55: ala | G55: VOY2026COFTN45 | H55: COFAT MATEUR | I55: 2282tu131 | J55: 10200 | K55: 2300 | L55: 14 | M55: 5 | N55: 2282tu131 | O55: ala | P55: 0.875 | Q55: 0.90972222 | R55: 0.9375 | S55: 0.97569444 | T55: 0 | U55: 0.11111111 | V55: 0.11111111 | W55: =IFERROR(IF(S55<R55,100%,"100"%-(S55-R55)*1.2),"-") -> 0.95416667 | AB55: retard production | AC55: =IFERROR(IF(Y55<X55,100%,"100"%-(Y55-X55)*1.2),"-") -> 1
B56: VOY2026COFTN46 | C56: 46030 | D56: Janvier | E56: 7797tu218 | F56: Houssem | G56: VOY2026COFTN46 | H56: COELEC TUNISIA | I56: 7797tu218 | J56: 927 | K56: 1000 | L56: 3 | M56: 1 | N56: 7797tu218 | O56: Houssem | P56: 0.375 | Q56: 0.5 | R56: 0.75 | S56: 0.52430556 | T56: 0.54166667 | U56: 0.56597222 | V56: 0.56597222 | W56: =IFERROR(IF(S56<R56,100%,"100"%-(S56-R56)*1.2),"-") -> 1 | AC56: =IFERROR(IF(Y56<X56,100%,"100"%-(Y56-X56)*1.2),"-") -> 1
B57: VOY2026COFTN47 | C57: 46030 | D57: Janvier | E57: 7797tu218 | F57: Houssem | G57: VOY2026COFTN47 | H57: CMR | I57: 7797tu218 | J57: 927 | K57: 1000 | L57: 3 | M57: 3 | N57: 7797tu218 | O57: Houssem | P57: 0.41666667 | Q57: 0.39930556 | R57: 0.5 | S57: 0.42361111 | T57: 0.45833333 | U57: 0.47916667 | V57: 0.47916667 | W57: =IFERROR(IF(S57<R57,100%,"100"%-(S57-R57)*1.2),"-") -> 1 | AC57: =IFERROR(IF(Y57<X57,100%,"100"%-(Y57-X57)*1.2),"-") -> 1
B58: VOY2026COFTN48 | C58: 46030 | D58: Janvier | E58: 7797tu218 | F58: Houssem | G58: VOY2026COFTN48 | H58: WeWire Hammamet Tunisia SARL | I58: 7797tu218 | J58: 927 | K58: 1000 | L58: 3 | M58: 2 | N58: 7797tu218 | O58: Houssem | P58: 0.5 | Q58: 0.60416667 | R58: 0.75 | S58: 0.64930556 | T58: 0.73263889 | U58: 0.83333333 | V58: 0.83333333 | W58: =IFERROR(IF(S58<R58,100%,"100"%-(S58-R58)*1.2),"-") -> 1 | AC58: =IFERROR(IF(Y58<X58,100%,"100"%-(Y58-X58)*1.2),"-") -> 1
B59: VOY2026COFTN49 | C59: 46030 | D59: Janvier | E59: 5735tu217 | F59: Bilel | G59: VOY2026COFTN49 | H59: COFAT MATEUR | I59: 5735tu217 | J59: 10200 | K59: 3000 | L59: 14 | M59: 5 | N59: 5735tu217 | O59: Bilel | P59: 0.33333333 | Q59: 0.33333333 | R59: 0.5 | S59: 0.46875 | T59: 0.5 | U59: 0.58333333 | V59: 0.58333333 | W59: =IFERROR(IF(S59<R59,100%,"100"%-(S59-R59)*1.2),"-") -> 1 | AC59: =IFERROR(IF(Y59<X59,100%,"100"%-(Y59-X59)*1.2),"-") -> 1
B60: VOY2026COFTN49 | C60: 46030 | D60: Janvier | E60: 5735tu217 | F60: Bilel | G60: VOY2026COFTN49 | H60: LEONI Wiring Systems Tunisia SUD | I60: 5735tu217 | J60: 10200 | K60: 7000 | L60: 14 | M60: 8 | N60: 5735tu217 | O60: Bilel | P60: 0.33333333 | Q60: 0.33333333 | R60: 0.5 | S60: 0.41666667 | T60: 0.45833333 | U60: 0.58333333 | V60: 0.58333333 | W60: =IFERROR(IF(S60<R60,100%,"100"%-(S60-R60)*1.2),"-") -> 1 | AC60: =IFERROR(IF(Y60<X60,100%,"100"%-(Y60-X60)*1.2),"-") -> 1
B61: VOY2026COFTN50 | C61: 46030 | D61: Janvier | E61: 5735tu217 | F61: Bilel | G61: VOY2026COFTN50 | H61: SCHULTE AUTOMOTIVE TUNISIA srl | I61: 5735tu217 | J61: 10200 | K61: 11000 | L61: 14 | M61: 14 | N61: 5735tu217 | O61: Bilel | P61: 0.625 | Q61: 0.6875 | R61: 0.83333333 | S61: 0.79166667 | T61: 0.81597222 | U61: 0.85416667 | V61: 0.85416667 | W61: =IFERROR(IF(S61<R61,100%,"100"%-(S61-R61)*1.2),"-") -> 1 | AC61: =IFERROR(IF(Y61<X61,100%,"100"%-(Y61-X61)*1.2),"-") -> 1
B62: VOY2026COFTN51 | C62: 46030 | D62: Janvier | E62: 9524TU238 | F62: Ridha | G62: VOY2026COFTN51 | H62: COFAT TUNIS | I62: 9524TU238 | J62: 10230 | K62: 11100 | L62: 14 | M62: 4 | N62: 9524TU238 | O62: Ridha | P62: 0.29166667 | Q62: 0.32986111 | R62: 0.5 | S62: 0.33333333 | T62: 0.33680556 | U62: 0.34027778 | V62: 0.34027778 | W62: =IFERROR(IF(S62<R62,100%,"100"%-(S62-R62)*1.2),"-") -> 1 | AC62: =IFERROR(IF(Y62<X62,100%,"100"%-(Y62-X62)*1.2),"-") -> 1
B63: VOY2026COFTN52 | C63: 46030 | D63: Janvier | E63: 9524TU238 | F63: Ridha | G63: VOY2026COFTN52 | H63: COFAT KAIROUAN | I63: 9524TU238 | J63: 10230 | K63: 300 | L63: 14 | M63: 1 | N63: 9524TU238 | O63: Ridha | P63: 0.375 | Q63: 0.42708333 | R63: 0.625 | S63: 0.54166667 | T63: 0.55208333 | U63: 0.83333333 | V63: 0.83333333 | W63: =IFERROR(IF(S63<R63,100%,"100"%-(S63-R63)*1.2),"-") -> 1 | AC63: =IFERROR(IF(Y63<X63,100%,"100"%-(Y63-X63)*1.2),"-") -> 1
B64: VOY2026COFTN52 | C64: 46030 | D64: Janvier | E64: 9524TU238 | F64: Ridha | G64: VOY2026COFTN52 | H64: YURA CORPORATION TUNISIA | I64: 9524TU238 | J64: 10230 | K64: 11000 | L64: 14 | M64: 17 | N64: 9524TU238 | O64: Ridha | P64: 0.375 | Q64: 0.42708333 | R64: 0.625 | S64: 0.5 | T64: 0.66666667 | U64: 0.83333333 | V64: 0.83333333 | W64: =IFERROR(IF(S64<R64,100%,"100"%-(S64-R64)*1.2),"-") -> 1 | AC64: =IFERROR(IF(Y64<X64,100%,"100"%-(Y64-X64)*1.2),"-") -> 1
B65: VOY2026COFTN52 | C65: 46030 | D65: Janvier | E65: 2282tu131 | F65: ala | G65: VOY2026COFTN52 | H65: TTE International | I65: 2282tu131 | J65: 10200 | K65: 350 | L65: 14 | M65: 2 | N65: 2282tu131 | O65: ala | P65: 0.45833333 | Q65: 0.69097222 | R65: 0.83333333 | S65: 0.80208333 | T65: 0.81597222 | U65: 0.89583333 | V65: 0.89583333 | W65: =IFERROR(IF(S65<R65,100%,"100"%-(S65-R65)*1.2),"-") -> 1 | AC65: =IFERROR(IF(Y65<X65,100%,"100"%-(Y65-X65)*1.2),"-") -> 1
B66: VOY2026COFTN52 | C66: 46030 | D66: Janvier | E66: 2282tu131 | F66: ala | G66: VOY2026COFTN52 | H66: Yazaki Automotive Products Tunisia | I66: 2282tu131 | J66: 10200 | K66: 1253 | L66: 14 | M66: 4 | N66: 2282tu131 | O66: ala | P66: 0.45833333 | Q66: 0.69097222 | R66: 0.83333333 | S66: 0.75694444 | T66: 0.78819444 | U66: 0.89583333 | V66: 0.89583333 | W66: =IFERROR(IF(S66<R66,100%,"100"%-(S66-R66)*1.2),"-") -> 1 | AC66: =IFERROR(IF(Y66<X66,100%,"100"%-(Y66-X66)*1.2),"-") -> 1
B67: VOY2026COFTN52 | C67: 46030 | D67: Janvier | E67: 2282tu131 | F67: ala | G67: VOY2026COFTN52 | H67: ERA CONTACTS TUNISIA | I67: 2282tu131 | J67: 10200 | K67: 2235 | L67: 14 | M67: 1 | N67: 2282tu131 | O67: ala | P67: 0.45833333 | Q67: 0.69097222 | R67: 0.83333333 | S67: 0.75694444 | T67: 0.78819444 | U67: 0.89583333 | V67: 0.89583333 | W67: =IFERROR(IF(S67<R67,100%,"100"%-(S67-R67)*1.2),"-") -> 1 | AC67: =IFERROR(IF(Y67<X67,100%,"100"%-(Y67-X67)*1.2),"-") -> 1
... B80: VOY2026COFTN61 | C80: 46031 | D80: Janvier | E80: REM107627 | F80: ala | G80: VOY2026COFTN61 | H80: perplastic | I80: REM107627 | J80: 24950 | K80: 8500 | L80: 27 | M80: 10 | N80: REM107627 | O80: ala | P80: 0.29166667 | Q80: 0.33333333 | R80: 0.70833333 | S80: 0.35069444 | T80: 0.47916667 | U80: 0.5 | V80: 0.5 | W80: =IFERROR(IF(S80<R80,100%,"100"%-(S80-R80)*1.2),"-") -> 1 | AC80: =IFERROR(IF(Y80<X80,100%,"100"%-(Y80-X80)*1.2),"-") -> 1
B81: VOY2026COFTN62 | C81: 46031 | D81: Janvier | E81: REM107627 | F81: ala | G81: VOY2026COFTN62 | H81: ADC Sousse | I81: REM107627 | J81: 24950 | K81: 1700 | L81: 27 | M81: 14 | N81: REM107627 | O81: ala | P81: 0.41666667 | Q81: 0.6875 | R81: 0.75 | S81: 0.81597222 | T81: 0.93055556 | U81: 0.20833333 | V81: 0.20833333 | W81: =IFERROR(IF(S81<R81,100%,"100"%-(S81-R81)*1.2),"-") -> 0.92083333 | AB81: retard production | AC81: =IFERROR(IF(Y81<X81,100%,"100"%-(Y81-X81)*1.2),"-") -> 1
B82: VOY2026COFTN63 | C82: 46031 | D82: Janvier | E82: Location | F82: Location | G82: VOY2026COFTN63 | H82: ELECTROCONTACT TUNISIE | I82: Location | M82: 27 | N82: SEMI REMORQUE | O82: SEMI REMORQUE | P82: 0.33333333 | W82: =IFERROR(IF(S82<R82,100%,"100"%-(S82-R82)*1.2),"-") -> 1 | AC82: =IFERROR(IF(Y82<X82,100%,"100"%-(Y82-X82)*1.2),"-") -> 1
B83: VOY2026COFTN63 | C83: 46031 | D83: Janvier | E83: Location | F83: Location | G83: VOY2026COFTN63 | H83: CABLISYS TUNISIE | I83: Location | M83: 2 | N83: SEMI REMORQUE | O83: SEMI REMORQUE | P83: 0.33333333 | W83: =IFERROR(IF(S83<R83,100%,"100"%-(S83-R83)*1.2),"-") -> 1 | AC83: =IFERROR(IF(Y83<X83,100%,"100"%-(Y83-X83)*1.2),"-") -> 1
B84: VOY2026COFTN64 | C84: 46031 | D84: Janvier | E84: 5735tu217 | F84: Bilel | G84: VOY2026COFTN64 | H84: YURA CORPORATION TUNISIA | I84: 5735tu217 | J84: 10200 | K84: 11000 | L84: 14 | M84: 17 | N84: 5735tu217 | O84: Bilel | P84: 0.29166667 | Q84: 0.375 | R84: 0.625 | S84: 0.5 | T84: 0.54166667 | U84: 0.66666667 | V84: 0.66666667 | W84: =IFERROR(IF(S84<R84,100%,"100"%-(S84-R84)*1.2),"-") -> 1 | AC84: =IFERROR(IF(Y84<X84,100%,"100"%-(Y84-X84)*1.2),"-") -> 1
B85: VOY2026COFTN65 | C85: 46031 | D85: Janvier | E85: 626tu203 | F85: Hbib | G85: VOY2026COFTN65 | H85: Kromberg & Schubert Tunisie SARL | I85: 626tu203 | J85: 8500 | K85: 186.9 | L85: 14 | M85: 7 | N85: 626tu203 | O85: Hbib | P85: 0.41666667 | Q85: 0.67361111 | R85: 0.875 | S85: 0.78819444 | T85: 0.80208333 | U85: 0.33333333 | V85: 0.33333333 | W85: =IFERROR(IF(S85<R85,100%,"100"%-(S85-R85)*1.2),"-") -> 1 | AC85: =IFERROR(IF(Y85<X85,100%,"100"%-(Y85-X85)*1.2),"-") -> 1
B86: VOY2026COFTN65 | C86: 46031 | D86: Janvier | E86: 626tu203 | F86: Hbib | G86: VOY2026COFTN65 | H86: Kromberg & Schubert Tunisie SARL | I86: 626tu203 | J86: 8500 | K86: 186.9 | L86: 14 | M86: 7 | N86: 626tu203 | O86: Hbib | P86: 0.41666667 | Q86: 0.67361111 | R86: 0.875 | S86: 0.78819444 | T86: 0.80208333 | U86: 0.33333333 | V86: 0.33333333 | W86: =IFERROR(IF(S86<R86,100%,"100"%-(S86-R86)*1.2),"-") -> 1 | AC86: =IFERROR(IF(Y86<X86,100%,"100"%-(Y86-X86)*1.2),"-") -> 1
B87: VOY2026COFTN65 | C87: 46031 | D87: Janvier | E87: 626tu203 | F87: Hbib | G87: VOY2026COFTN65 | H87: SEBN (SUMITOMO) | I87: 626tu203 | J87: 8500 | K87: 986.7 | L87: 14 | M87: 4 | N87: 626tu203 | O87: Hbib | P87: 0.41666667 | Q87: 0.67361111 | R87: 0.875 | S87: 0.85763889 | T87: 0.88888889 | U87: 0.33333333 | V87: 0.33333333 | W87: =IFERROR(IF(S87<R87,100%,"100"%-(S87-R87)*1.2),"-") -> 1 | AC87: =IFERROR(IF(Y87<X87,100%,"100"%-(Y87-X87)*1.2),"-") -> 1
B88: VOY2026COFTN66 | C88: 46031 | D88: Janvier | E88: 9524TU238 | F88: Ridha | G88: VOY2026COFTN66 | H88: COFAT MATEUR | I88: 9524TU238 | J88: 10230 | K88: 5300 | L88: 14 | M88: 9 | N88: 9524TU238 | O88: Ridha | P88: 0.29166667 | Q88: 0.34027778 | R88: 0.5 | S88: 0.40972222 | T88: 0.4375 | U88: 0.5 | V88: 0.5 | W88: =IFERROR(IF(S88<R88,100%,"100"%-(S88-R88)*1.2),"-") -> 1 | AC88: =IFERROR(IF(Y88<X88,100%,"100"%-(Y88-X88)*1.2),"-") -> 1
B89: VOY2026COFTN67 | C89: 46031 | D89: Janvier | E89: 9524TU238 | F89: Ridha | G89: VOY2026COFTN67 | H89: SCHULTE AUTOMOTIVE TUNISIA srl | I89: 9524TU238 | J89: 10230 | K89: 10230 | L89: 14 | M89: 14 | N89: 9524TU238 | O89: Ridha | P89: 0.58333333 | Q89: 0.8125 | R89: 0.91666667 | S89: 0.85416667 | T89: 0.875 | U89: 0.95833333 | V89: 0.95833333 | W89: =IFERROR(IF(S89<R89,100%,"100"%-(S89-R89)*1.2),"-") -> 1 | AC89: =IFERROR(IF(Y89<X89,100%,"100"%-(Y89-X89)*1.2),"-") -> 1
B90: VOY2026COFTN68 | C90: 46031 | D90: Janvier | E90: 7797tu218 | F90: Houssem | G90: VOY2026COFTN68 | H90: ERA CONTACTS TUNISIA | I90: 7797tu218 | J90: 927 | K90: 257 | L90: 3 | M90: 1 | N90: 7797tu218 | O90: Houssem | P90: 0.29166667 | Q90: 0.3125 | R90: 0.75 | S90: 0.36805556 | T90: 0.39930556 | U90: 0.46180556 | V90: 0.46180556 | W90: =IFERROR(IF(S90<R90,100%,"100"%-(S90-R90)*1.2),"-") -> 1 | AC90: =IFERROR(IF(Y90<X90,100%,"100"%-(Y90-X90)*1.2),"-") -> 1
B91: VOY2026COFTN69 | C91: 46031 | D91: Janvier | E91: 7797tu218 | F91: Houssem | G91: VOY2026COFTN69 | H91: MEDITERRANEAN ELECTRIC WIRING | I91: 7797tu218 | J91: 927 | K91: 506 | L91: 3 | M91: 2 | N91: 7797tu218 | O91: Houssem | P91: 0.5 | Q91: 0.5 | R91: 0.75 | S91: 0.61458333 | T91: 0.64583333 | U91: 0.71875 | V91: 0.71875 | W91: =IFERROR(IF(S91<R91,100%,"100"%-(S91-R91)*1.2),"-") -> 1 | AC91: =IFERROR(IF(Y91<X91,100%,"100"%-(Y91-X91)*1.2),"-") -> 1
B92: VOY2026COFTN69 | C92: 46031 | D92: Janvier | E92: 7797tu218 | F92: Houssem | G92: VOY2026COFTN69 | H92: STE S.C.E.E.T | I92: 7797tu218 | J92: 927 | K92: 156 | L92: 3 | M92: 1 | N92: 7797tu218 | O92: Houssem | P92: 0.5 | Q92: 0.5 | R92: 0.75 | S92: 0.54513889 | T92: 0.57291667 | U92: 0.71875 | V92: 0.71875 | W92: =IFERROR(IF(S92<R92,100%,"100"%-(S92-R92)*1.2),"-") -> 1 | AC92: =IFERROR(IF(Y92<X92,100%,"100"%-(Y92-X92)*1.2),"-") -> 1
B93: VOY2026COFTN70 | C93: 46031 | D93: Janvier | E93: 7797tu218 | F93: Houssem | G93: VOY2026COFTN70 | H93: cofat mateur | I93: 7797tu218 | J93: 927 | K93: 281 | L93: 3 | M93: 1 | N93: 7797tu218 | O93: Houssem | P93: 0.5 | Q93: 0.75 | R93: 0.75 | S93: 0.84375 | T93: 0.86458333 | U93: 0.91666667 | V93: 0.91666667 | W93: =IFERROR(IF(S93<R93,100%,"100"%-(S93-R93)*1.2),"-") -> 0.8875 | AB93: retard production | AC93: =IFERROR(IF(Y93<X93,100%,"100"%-(Y93-X93)*1.2),"-") -> 1
B94: VOY2026COFTN70 | C94: 46031 | D94: Janvier | E94: 7797tu218 | F94: Houssem | G94: VOY2026COFTN70 | H94: LEONI Wiring Systems Tunisia NORD | I94: 7797tu218 | J94: 927 | K94: 281 | L94: 3 | M94: 1 | N94: 7797tu218 | O94: Houssem | P94: 0.5 | Q94: 0.75 | R94: 0.75 | S94: 0.81944444 | T94: 0.83680556 | U94: 0.91666667 | V94: 0.91666667 | W94: =IFERROR(IF(S94<R94,100%,"100"%-(S94-R94)*1.2),"-") -> 0.91666667 | AB94: retard production | AC94: =IFERROR(IF(Y94<X94,100%,"100"%-(Y94-X94)*1.2),"-") -> 1
B95: VOY2026COFTN71 | C95: 46031 | D95: Janvier | E95: 4331tu175 | F95: mehrez | G95: VOY2026COFTN71 | H95: LEONI Wiring Systems Tunisia SUD | I95: 4331tu175 | J95: 9200 | K95: 1100 | L95: 14 | M95: 1 | N95: 4331tu175 | O95: mehrez | P95: 0.375 | Q95: 0.91666667 | R95: 0.5 | S95: 0.97222222 | T95: 0 | U95: 0.125 | V95: 0.125 | W95: =IFERROR(IF(S95<R95,100%,"100"%-(S95-R95)*1.2),"-") -> 0.43333333 | AB95: retard production | AC95: =IFERROR(IF(Y95<X95,100%,"100"%-(Y95-X95)*1.2),"-") -> 1
B96: VOY2026COFTN72 | C96: 46032 | D96: Janvier | E96: 5735tu217 | F96: Bilel | G96: VOY2026COFTN72 | H96: LEONI Wiring Systems Tunisia SUD | I96: 5735tu217 | J96: 10200 | K96: 7100 | L96: 14 | M96: 6 | N96: 5735tu217 | O96: Bilel | P96: 0.33333333 | W96: =IFERROR(IF(S96<R96,100%,"100"%-(S96-R96)*1.2),"-") -> 1 | AC96: =IFERROR(IF(Y96<X96,100%,"100"%-(Y96-X96)*1.2),"-") -> 1
B97: VOY2026COFTN73 | C97: 46032 | D97: Janvier | E97: 9524TU238 | F97: Houssem | G97: VOY2026COFTN73 | H97: COFAT TUNIS | I97: 9524TU238 | J97: 10230 | K97: 6000 | L97: 14 | M97: 8 | N97: 9524TU238 | O97: Houssem | P97: 0.29166667 | Q97: 0.29166667 | R97: 0.5 | S97: 0.29513889 | T97: 0.33680556 | U97: 0.34027778 | V97: 0.34027778 | W97: =IFERROR(IF(S97<R97,100%,"100"%-(S97-R97)*1.2),"-") -> 1 | AC97: =IFERROR(IF(Y97<X97,100%,"100"%-(Y97-X97)*1.2),"-") -> 1
B98: VOY2026COFTN74 | C98: 46032 | D98: Janvier | E98: 9524TU238 | F98: Houssem | G98: VOY2026COFTN74 | H98: COFAT MATEUR | I98: 9524TU238 | J98: 10230 | K98: 6000 | L98: 14 | M98: 10 | N98: 9524TU238 | O98: Houssem | P98: 0.375 | Q98: 0.4375 | R98: 0.5 | S98: 0.5 | T98: 0.59722222 | U98: 0.68402778 | V98: 0.68402778 | W98: =IFERROR(IF(S98<R98,100%,"100"%-(S98-R98)*1.2),"-") -> 1 | AC98: =IFERROR(IF(Y98<X98,100%,"100"%-(Y98-X98)*1.2),"-") -> 1
B99: VOY2026COFTN75 | C99: 46032 | D99: Janvier | E99: REM107627 | F99: ala | G99: VOY2026COFTN75 | H99: ADC Sousse | I99: REM107627 | J99: 24950 | K99: 16000 | L99: 27 | M99: 14 | N99: REM107627 | O99: ala | P99: 0.33333333 | Q99: 0.46527778 | R99: 0.625 | S99: 0.57638889 | T99: 0.65625 | U99: 0.78125 | V99: 0.78125 | W99: =IFERROR(IF(S99<R99,100%,"100"%-(S99-R99)*1.2),"-") -> 1 | AC99: =IFERROR(IF(Y99<X99,100%,"100"%-(Y99-X99)*1.2),"-") -> 1
B100: VOY2026COFTN76 | C100: 46034 | D100: Janvier | E100: REM107627 | F100: ala | G100: VOY2026COFTN76 | H100: WeWire Hammamet Tunisia SARL | I100: REM107627 | J100: 24950 | K100: 23000 | L100: 27 | M100: 24 | N100: REM107627 | O100: ala | P100: 0.29166667 | Q100: 0.3125 | R100: 0.625 | S100: 0.375 | T100: 0.44791667 | U100: 0.79166667 | V100: 0.79166667 | W100: =IFERROR(IF(S100<R100,100%,"100"%-(S100-R100)*1.2),"-") -> 1 | AC100: =IFERROR(IF(Y100<X100,100%,"100"%-(Y100-X100)*1.2),"-") -> 1
B101: VOY2026COFTN77 | C101: 46034 | D101: Janvier | E101: 7797tu218 | F101: Houssem | G101: VOY2026COFTN77 | H101: COELEC TUNISIA | I101: 7797tu218 | J101: 927 | K101: 147 | L101: 3 | M101: 1 | N101: 7797tu218 | O101: Houssem | P101: 0.33333333 | Q101: 0.3125 | R101: 0.5 | S101: 0.33333333 | T101: 0.35416667 | U101: 0.38541667 | V101: 0.38541667 | W101: =IFERROR(IF(S101<R101,100%,"100"%-(S101-R101)*1.2),"-") -> 1 | AC101: =IFERROR(IF(Y101<X101,100%,"100"%-(Y101-X101)*1.2),"-") -> 1
B102: VOY2026COFTN78 | C102: 46034 | D102: Janvier | E102: Location | F102: Location | G102: VOY2026COFTN78 | H102: LEONI Wiring Systems Tunisia NORD | I102: Location | K102: 6200 | M102: 5 | N102: SEMI REMORQUE | O102: SEMI REMORQUE | P102: 0.375 | W102: =IFERROR(IF(S102<R102,100%,"100"%-(S102-R102)*1.2),"-") -> 1 | AC102: =IFERROR(IF(Y102<X102,100%,"100"%-(Y102-X102)*1.2),"-") -> 1
B103: VOY2026COFTN78 | C103: 46034 | D103: Janvier | E103: Location | F103: Location | G103: VOY2026COFTN78 | H103: COFAT MATEUR | I103: Location | K103: 2100 | M103: 6 | N103: SEMI REMORQUE | O103: SEMI REMORQUE | P103: 0.375 | W103: =IFERROR(IF(S103<R103,100%,"100"%-(S103-R103)*1.2),"-") -> 1 | AC103: =IFERROR(IF(Y103<X103,100%,"100"%-(Y103-X103)*1.2),"-") -> 1
B104: VOY2026COFTN78 | C104: 46034 | D104: Janvier | E104: Location | F104: Location | G104: VOY2026COFTN78 | H104: LEONI Wiring Systems Tunisia SUD | I104: Location | K104: 7100 | M104: 13 | N104: SEMI REMORQUE | O104: SEMI REMORQUE | P104: 0.375 | W104: =IFERROR(IF(S104<R104,100%,"100"%-(S104-R104)*1.2),"-") -> 1 | AC104: =IFERROR(IF(Y104<X104,100%,"100"%-(Y104-X104)*1.2),"-") -> 1
B105: VOY2026COFTN79 | C105: 46034 | D105: Janvier | E105: Location | F105: Location | G105: VOY2026COFTN79 | H105: ELECTROCONTACT TUNISIE | I105: Location | K105: 22303 | M105: 27 | N105: SEMI REMORQUE | O105: SEMI REMORQUE | P105: 0.375 | W105: =IFERROR(IF(S105<R105,100%,"100"%-(S105-R105)*1.2),"-") -> 1 | AC105: =IFERROR(IF(Y105<X105,100%,"100"%-(Y105-X105)*1.2),"-") -> 1
B106: VOY2026COFTN80 | C106: 46034 | D106: Janvier | E106: 4331tu175 | F106: mehrez | G106: VOY2026COFTN80 | H106: Aptiv Services Tunisia SARL | I106: 4331tu175 | J106: 9200 | K106: 6500 | L106: 14 | M106: 14 | N106: 4331tu175 | O106: mehrez | P106: 0.29166667 | Q106: 0.33333333 | R106: 0.5 | S106: 0.375 | T106: 0.45833333 | U106: 0.5 | V106: 0.5 | W106: =IFERROR(IF(S106<R106,100%,"100"%-(S106-R106)*1.2),"-") -> 1 | AC106: =IFERROR(IF(Y106<X106,100%,"100"%-(Y106-X106)*1.2),"-") -> 1
B107: VOY2026COFTN81 | C107: 46034 | D107: Janvier | E107: 4331tu175 | F107: mehrez | G107: VOY2026COFTN81 | H107: Yazaki Automotive Products Tunisia | I107: 4331tu175 | J107: 9200 | K107: 4200 | L107: 14 | M107: 14 | N107: 4331tu175 | O107: mehrez | P107: 0.5 | Q107: 0.52083333 | R107: 0.75 | S107: 0.59722222 | T107: 0.625 | U107: 0.80555556 | V107: 0.80555556 | W107: =IFERROR(IF(S107<R107,100%,"100"%-(S107-R107)*1.2),"-") -> 1 | AC107: =IFERROR(IF(Y107<X107,100%,"100"%-(Y107-X107)*1.2),"-") -> 1
B108: VOY2026COFTN82 | C108: 46034 | D108: Janvier | E108: 626tu203 | F108: Hbib | G108: VOY2026COFTN82 | H108: METS MANUFAC ELECTRO.DE SOUSSE | I108: 626tu203 | J108: 8500 | K108: 9013 | L108: 14 | M108: 16 | N108: 626tu203 | O108: Hbib | P108: 0.29166667 | Q108: 0.375 | R108: 0.75 | S108: 0.53472222 | T108: 0.60763889 | U108: 0.79166667 | V108: 0.79166667 | W108: =IFERROR(IF(S108<R108,100%,"100"%-(S108-R108)*1.2),"-") -> 1 | AC108: =IFERROR(IF(Y108<X108,100%,"100"%-(Y108-X108)*1.2),"-") -> 1
B109: VOY2026COFTN83 | C109: 46034 | D109: Janvier | E109: 5735tu217 | F109: Bilel | G109: VOY2026COFTN83 | H109: A C T Assemblage Cable Tunisie | I109: 5735tu217 | J109: 10200 | K109: 7100 | L109: 14 | M109: 7 | N109: 5735tu217 | O109: Bilel | P109: 0.3125 | Q109: 0.3125 | R109: 0.625 | S109: 0.35416667 | T109: 0.41666667 | U109: 0.5 | V109: 0.5 | W109: =IFERROR(IF(S109<R109,100%,"100"%-(S109-R109)*1.2),"-") -> 1 | AC109: =IFERROR(IF(Y109<X109,100%,"100"%-(Y109-X109)*1.2),"-") -> 1
B110: VOY2026COFTN84 | C110: 46034 | D110: Janvier | E110: 5735tu217 | F110: Bilel | G110: VOY2026COFTN84 | H110: TTE International | I110: 5735tu217 | J110: 10200 | K110: 6690 | L110: 14 | M110: 10 | N110: 5735tu217 | O110: Bilel | P110: 0.5 | Q110: 0.5 | R110: 0.75 | S110: 0.58333333 | T110: 0.625 | U110: 0.75 | V110: 0.75 | W110: =IFERROR(IF(S110<R110,100%,"100"%-(S110-R110)*1.2),"-") -> 1 | AC110: =IFERROR(IF(Y110<X110,100%,"100"%-(Y110-X110)*1.2),"-") -> 1
B111: VOY2026COFTN84 | C111: 46034 | D111: Janvier | E111: 5735tu217 | F111: Bilel | G111: VOY2026COFTN84 | H111: KAB-LEM Tunisia SARL | I111: 5735tu217 | J111: 10200 | K111: 936 | L111: 14 | M111: 4 | N111: 5735tu217 | O111: Bilel | P111: 0.5 | Q111: 0.5 | R111: 0.75 | S111: 0.62847222 | T111: 0.66666667 | U111: 0.75 | V111: 0.75 | W111: =IFERROR(IF(S111<R111,100%,"100"%-(S111-R111)*1.2),"-") -> 1 | AC111: =IFERROR(IF(Y111<X111,100%,"100"%-(Y111-X111)*1.2),"-") -> 1
B112: VOY2026COFTN85 | C112: 46034 | D112: Janvier | E112: 9524TU238 | F112: Ridha | G112: VOY2026COFTN85 | H112: perplastic | I112: 9524TU238 | J112: 10230 | K112: 10000 | L112: 14 | M112: 10 | N112: 9524TU238 | O112: Ridha | P112: 0.29166667 | Q112: 0.33333333 | R112: 0.5 | S112: 0.34722222 | T112: 0.41666667 | U112: 0.5 | V112: 0.5 | W112: =IFERROR(IF(S112<R112,100%,"100"%-(S112-R112)*1.2),"-") -> 1 | AC112: =IFERROR(IF(Y112<X112,100%,"100"%-(Y112-X112)*1.2),"-") -> 1
...

Sheet Delivery Plan
A1: Planning de Livraison
A3: 45663 | B3: LEONI Wiring Systems Tunisia SUD | C3: 2282tu131 | D3: houssem | E3: 0.20833333
A4: 45663 | B4: LEONI Wiring Systems Tunisia Nord | C4: 2282tu131 | D4: houssem | E4: 0.20833333
A5: 45663 | B5: COFAT MATEUR | C5: 2282tu131 | D5: houssem | E5: 0.54166667
A6: 45663 | B6: Yazaki Automotive Products Tunisia | C6: 626tu203 | D6: hbib | E6: 0.20833333
A7: 45663 | B7: TTE International | C7: 626tu203 | D7: hbib | E7: 0.20833333
A8: 45663 | B8: METS MANUFAC ELECTRO.DE SOUSSE | C8: REM107627 | D8: KARIM | E8: 0.125
A9: 45663 | B9: SEWS TN SARL | C9: REM107627 | D9: KARIM | E9: 0.5
A10: 45663 | B10: ELECTROCONTACT TUNISIE | C10: 9524tu238 | D10: Ridha | E10: 0.54166667
A11: 45663 | B11: ELECTROCONTACT TUNISIE | C11: 5735tu217 | D11: bilel | E11: 0.54166667
A12: 45663 | B12: Aptiv Services Tunisia SARL | C12: 4331tu175 | D12: Mehrez | E12: 0.25
A13: 45663 | B13: WeWire Hammamet Tunisia SARL | C13: 4331tu175 | D13: Mehrez | E13: 0.41666667
A14: 45663 | B14: Perplastic TN | C14: 6502tu247 | D14: Mehrez | E14: 0.625
... A18: 45663 | B18: STE S.C.E.E.T | C18: 9524tu238 | D18: Ridha | E18: 0.25
A21: Date PICK UP | B21: Delivery address | C21: Matricule | D21: Chauffeur | E21: ETD COF TN
A22: 45665 | B22: COFAT TUNIS | C22: 5735tu217 | D22: bilel | E22: 0.29166667
A23: 45665 | B23: SCHULTE AUTOMOTIVE TUNISIA srl | C23: 5735tu217 | D23: bilel | E23: 0.41666667
A24: 45665 | B24: LEONI Wiring Systems Tunisia NORD | C24: 9524tu238 | D24: ridha | E24: 0.29166667
A25: 45665 | B25: WeWire Hammamet Tunisia SARL | C25: 2282tu131 | D25: houssem | E25: 0.5
A26: 45665 | B26: COFAT MATEUR | C26: 2282tu131 | D26: houssem | E26: 0.25
A27: 45665 | B27: LEONI Wiring Systems Tunisia SUD | C27: 2282tu131 | D27: houssem | E27: 0.25
A28: 45665 | B28: kroshu | C28: 2282tu131 | D28: houssem | E28: 0.54166667
A29: 45299 | B29: ADC SOUSSE | C29: REM107627 | D29: KARIM | E29: 0.33333333
A30: 45665 | B30: SEWS TN SARL | C30: REM107627 | D30: KARIM | E30: 0.33333333
A31: 45665 | B31: AMPHENOL | C31: 6502tu247 | D31: mehrez | E31: 0.25
A32: 45665 | B32: DIS Draxlmaier Indust Solution Gmbh | C32: 6502tu247 | D32: mehrez | E32: 0.25
A33: 45665 | B33: PERPLASTIC PVC | C33: 6502tu247 | D33: mehrez | E33: 0.54166667
... A37: 45665 | B37: kroshu | C37: vehicule | D37: barkia | E37: 0.70833333
A38: Date PICK UP | B38: Delivery address | C38: Matricule | D38: Chauffeur | E38: ETD COF TN
A39: 45666 | B39: ADC SOUSSE | C39: 5735tu217 | D39: bilel | E39: 0.20833333
A40: 45666 | B40: COFAT MATEUR | C40: 6502tu247 | D40: hbib | E40: 0.25
A41: 45666 | B41: LEONI Wiring Systems Tunisia SUD | C41: 6502tu247 | D41: hbib | E41: 0.25
A42: 45666 | B42: AMPHENOL TUNISIE | C42: 6502tu247 | D42: hbib | E42: 0.45833333
A43: 45666 | B43: Aptiv Services Tunisia SARL | C43: REM107627 | D43: KARIM | E43: 0.29166667
A44: 45666 | B44: SCHULTE AUTOMOTIVE TUNISIA srl | C44: REM107627 | D44: KARIM | E44: 0.29166667
A45: 45666 | B45: YURA CORPORATION TUNISIA | C45: 9524tu238 | D45: ridha | E45: 0.25
A46: 45666 | B46: COFAT TUNIS | C46: 2282tu131 | D46: houssem | E46: 0.29166667
A47: 45666 | B47: WeWire Hammamet Tunisia SARL | C47: 2282tu131 | D47: houssem | E47: 0.41666667
A48: 45666 | B48: I.C.eM | C48: 2282tu131 | D48: houssem | E48: 0.41666667
A49: 45666 | B49: METS MANUFAC ELECTRO.DE SOUSSE | C49: 2282tu131 | D49: houssem | E49: 0.41666667
A50: 45666 | B50: COAELEC | C50: 7797tu218 | D50: mehrez | E50: 0.45833333
... A52: 45666 | B52: Yazaki Automotive Products Tunisia | C52: 7797tu218 | D52: mehrez | E52: 0.29166667
A54: Date PICK UP | B54: Delivery address | C54: Matricule | D54: Chauffeur | E54: ETD COF TN
A55: 45667 | B55: YURA CORPORATION TUNISIA | C55: REM107627 | D55: KARIM | E55: 0.25
A56: 45667 | B56: COFAT KAIROUAN | C56: REM107627 | D56: KARIM | E56: 0.25
A57: 45667 | B57: amphenol | C57: 2282tu131 | D57: houssem | E57: 0.25
A58: 45667 | B58: SEWS TN SARL | C58: 2282tu131 | D58: houssem | E58: 0.29166667
A59: 45667 | B59: LEONI Wiring Systems Tunisia SUD | C59: 5735TU217 | D59: BILEL | E59: 0.29166667
A60: 45667 | B60: COFAT MATEUR | C60: 5735TU217 | D60: BILEL | E60: 0.29166667
A61: 45667 | B61: SCHULTE AUTOMOTIVE TUNISIA srl | C61: 5735TU217 | D61: BILEL | E61: 0.54166667
A62: 45667 | B62: PERPLASTIC | C62: 6502TU247 | D62: MEHREZ | E62: 0.33333333
A63: 45667 | B63: SCHULTE AUTOMOTIVE TUNISIA srl | C63: 6502TU247 | D63: MEHREZ | E63: 0.5
A64: 45667 | B64: COFAT TUNIS | C64: 9524tu238 | D64: ridha | E64: 0.29166667
A65: 45667 | B65: ADC SOUSSE | C65: 9524tu238 | D65: ridha | E65: 0.35416667
A66: 45667 | B66: I.C.eM | C66: 7797tu218 | D66: hbib | E66: 0.29166667
A69: Date PICK UP | B69: Delivery address | C69: Matricule | D69: Chauffeur | E69: ETD COF TN
A70: 45668 | B70: ADC SOUSSE | C70: 6205tu247 | D70: hbib | E70: 0.29166667
A71: 45668 | B71: CARTONS MGHIRA | C71: 7797TU218 | D71: HOUSSEM | E71: 0.29166667
A72: 45668 | B72: SEBN | C72: VEHICULE | D72: RIDHA | E72: 0.20833333
A73: 45668 | B73: LEONI SUD | C73: 5735TU217 | D73: BILEL | E73: 0.29166667
A74: Date PICK UP | B74: Delivery address | C74: Matricule | D74: Chauffeur | E74: ETD COF TN
A75: 45670 | B75: WeWire Hammamet Tunisia SARL | C75: REM107627 | D75: KARIM | E75: 0.25
A76: 45670 | B76: ELECTROCONTACT TUNISIE | C76: REM107627 | D76: KARIM | E76: 0.45833333
A77: 45670 | B77: cablisis | C77: REM107627 | D77: KARIM | E77: 0.41666667
A78: 45670 | B78: LEONI Wiring Systems Tunisia NORD | C78: 5735TU217 | D78: BILEL | E78: 0.25
A79: 45670 | B79: TTE International | C79: 5735TU217 | D79: BILEL | E79: 0.5
A80: 45670 | B80: LEONI Wiring Systems Tunisia SUD | C80: 9524tu238 | D80: RIDHA | E80: 0.25
A81: 45670 | B81: Yazaki Automotive Products Tunisia | C81: 9524tu238 | D81: RIDHA | E81: 0.5
A82: 45670 | B82: KAB-LEM Tunisia SARL | C82: 9524tu238 | D82: RIDHA | E82: 0.5
A83: 45670 | B83: COFAT MATEUR | C83: 2282tu131 | D83: HOUSSEM | E83: 0.25
A84: 45670 | B84: Aptiv Services Tunisia SARL | C84: 2282tu131 | D84: houssem | E84: 0.45833333
A85: 45670 | B85: COFAT TUNIS | C85: 6502tu247 | D85: mehrez | E85: 0.29166667
A86: 45670 | B86: perplastic | C86: 6502tu247 | D86: mehrez | E86: 0.375
A87: 45670 | B87: lectric | C87: 7797TU218 | D87: hbib | E87: 0.41666667
A89: Date PICK UP | B89: Delivery address | C89: Matricule | D89: Chauffeur | E89: ETD COF TN | H89: REAL ETD
A90: 45671 | B90: COFAT MATEUR | C90: 2282TU131 | D90: HOUSSEM | E90: 0.25 | H90: 0.45833333
A91: 45671 | B91: LEONI Wiring Systems Tunisia SUD | C91: 2282TU131 | D91: HOUSSEM | E91: 0.25 | H91: 0.45833333
A92: 45671 | B92: COFAT TN | C92: 626TU203 | D92: HBIB | E92: 0.29166667 | H92: 0.41666667
A93: 45671 | B93: SCHULTE Zaghouane | C93: 6502tu247 | D93: mehrez | E93: 0.25 | H93: 0.3125
A94: 45671 | B94: MEDITERRANEAN ELECTRIC WIRING | C94: 5735tu217 | D94: bilel | E94: 0.20833333 | H94: 0.29166667
A95: 45671 | B95: ADC SOUSSE | C95: 9524tu238 | D95: ridha | E95: 0.41666667 | H95: 0.45833333
A96: 45671 | B96: ADC SOUSSE | C96: vehicule | D96: barkia | E96: 0.5 | H96: 0.58333333
A97: 45671 | B97: perplastic | C97: 6502tu247 | D97: mehrez | E97: 0.375 | H97: 0.45833333
A98: 45671 | B98: TTEI | C98: 7797TU218 | D98: HBIB | E98: 0.33333333 | H98: 0.52083333
A99: 45671 | B99: YAZAKI BIZERTE | C99: 7797TU218 | D99: HBIB | E99: 0.33333333 | H99: 0.52083333
A100: 45671 | B100: Aptiv Services Tunisia SARL | C100: 6502tu247 | D100: mehrez | E100: 0.5 | H100: 0.47916667
A101: 45671 | B101: LEONI Wiring Systems Tunisia SUD | C101: 6502tu247 | D101: mehrez | E101: 0.5 | H101: 0.47916667
... A107: 45671 | B107: SCHULTE AUTOMOTIVE TUNISIA srl | C107: 2282TU131 | D107: ridha | E107: 0.29166667 | H107: 0.75
A113: Date PICK UP | B113: Delivery address | C113: Matricule | D113: Chauffeur | E113: ETD COF TN | H113: REAL ETD
A114: 45672 | B114: LEONI Wiring Systems Tunisia SUD | C114: 5735tu217 | D114: bilel | E114: 0.125
A115: 45672 | B115: LEONI Wiring Systems Tunisia NORD | C115: 5735tu217 | D115: bilel | E115: 0.125
A116: 45672 | B116: COFAT MATEUR | C116: 5735tu217 | D116: bilel | E116: 0.5
A117: 45672 | B117: LEONI Wiring Systems Tunisia SUD | C117: 5735tu217 | D117: bilel | E117: 0.5
A118: 45672 | B118: METS MANUFAC ELECTRO.DE SOUSSE | C118: 9524tu238 | D118: ridha | E118: 0.375
A119: 45672 | B119: RESTE ADC SOUSSE URGENT | C119: 9524tu238 | D119: ridha | E119: 0.33333333 | H119: 0.83333333
A120: 45672 | B120: COFAT TUNIS | C120: 6502TU247 | D120: hbib | E120: 0.29166667
A121: 45672 | B121: perplastic retour silicone | C121: 6502TU247 | D121: hbib | E121: 0.375
A122: 45672 | B122: SCHULTE AUTOMOTIVE TUNISIA srl | C122: 6502TU247 | D122: hbib | E122: 0.45833333
A123: 45672 | B123: DIS Draxlmaier Indust Solution Gmbh | C123: 6502TU247 | D123: hbib | E123: 0.45833333
A124: 45672 | B124: adc sousse | C124: 2282tu131 | D124: houssem | E124: 0.25
...

Sheet RECAP Delivery Plan 
A1: N° Voyage | B1: Date de Livraison | C1: Month | D1: matricule | E1: Capacite Truck Position | F1: Nbr Position Truck | G1: Max weigh t truck | H1: Weight /Truck | I1: Stationnement | J1: otd | K1: Trajet AllE(H) | L1: Trajet Retour (H) | M1: Trajet entre les clients(H) | N1: Loading Rate % | O1: Charging Rate % | P1: Total Heure Active | Q1: Total Heure sur route | R1: Taux Occupation | S1: Loading Efficiency | T1: Km traveled | U1: ROOT CAUSE | V1: ARTICLE RETARD | W1: ACTION | X1: Frais déplacement
A2: VOY2026COFTN01 | B2: =+IFERROR(VLOOKUP(A2,'Details local delivery'!B:C,2,0),"-") -> 46024 | C2: =B2 -> 46024 | D2: =+IFERROR(VLOOKUP(A2,'Details local delivery'!B:E,4,0),"-") -> 5735tu217 | E2: =VLOOKUP(A2,'Details local delivery'!B:L,11,0) -> 14 | F2: =SUMIFS('Details local delivery'!M:M,'Details local delivery'!G:G,'RECAP Delivery Plan '!A2) -> 10 | G2: =VLOOKUP(A2,'Details local delivery'!B:J,9,0) -> 10200 | H2: =SUMIFS('Details local delivery'!K:K,'Details local delivery'!G:G,'RECAP Delivery Plan '!A2) -> 7100 | I2: =SUMIFS('Details local delivery'!Y:Y,'Details local delivery'!B:B,A:A) -> 0 | J2: =AVERAGEIFS('Details local delivery'!W:W,'Details local delivery'!B:B,A2) -> 1 | K2: =_xlfn.MAXIFS('Details local delivery'!Z:Z,'Details local delivery'!B:B,A2) -> 0 | L2: =_xlfn.MAXIFS('Details local delivery'!AA:AA,'Details local delivery'!B:B,A2) -> 0 | M2: =_xlfn.MAXIFS('Details local delivery'!AB:AB,'Details local delivery'!B:B,A2) -> 0 | N2: =+F2/E2 -> 0.71428571 | O2: =+H2/G2 -> 0.69607843 | P2: =K2+L2+M2 -> 0 | Q2: =P2+I2 -> 0 | R2: =Q2/P2 -> #DIV/0! | S2: =MAX(N2,O2) -> 0.71428571
A3: VOY2026COFTN02 | B3: =+IFERROR(VLOOKUP(A3,'Details local delivery'!B:C,2,0),"-") -> 46024 | C3: =B3 -> 46024 | D3: =+IFERROR(VLOOKUP(A3,'Details local delivery'!B:E,4,0),"-") -> 4331tu175 | E3: =VLOOKUP(A3,'Details local delivery'!B:L,11,0) -> 14 | F3: =SUMIFS('Details local delivery'!M:M,'Details local delivery'!G:G,'RECAP Delivery Plan '!A3) -> 10 | G3: =VLOOKUP(A3,'Details local delivery'!B:J,9,0) -> 9200 | H3: =SUMIFS('Details local delivery'!K:K,'Details local delivery'!G:G,'RECAP Delivery Plan '!A3) -> 7000 | I3: =SUMIFS('Details local delivery'!Y:Y,'Details local delivery'!B:B,A:A) -> 0 | J3: =AVERAGEIFS('Details local delivery'!W:W,'Details local delivery'!B:B,A3) -> 1 | K3: =_xlfn.MAXIFS('Details local delivery'!Z:Z,'Details local delivery'!B:B,A3) -> 0 | L3: =_xlfn.MAXIFS('Details local delivery'!AA:AA,'Details local delivery'!B:B,A3) -> 0 | M3: =_xlfn.MAXIFS('Details local delivery'!AB:AB,'Details local delivery'!B:B,A3) -> 0 | N3: =+F3/E3 -> 0.71428571 | O3: =+H3/G3 -> 0.76086957 | P3: =K3+L3+M3 -> 0 | Q3: =P3+I3 -> 0 | R3: =Q3/P3 -> #DIV/0! | S3: =MAX(N3,O3) -> 0.76086957
A4: VOY2026COFTN03 | B4: =+IFERROR(VLOOKUP(A4,'Details local delivery'!B:C,2,0),"-") -> 46024 | C4: =B4 -> 46024 | D4: =+IFERROR(VLOOKUP(A4,'Details local delivery'!B:E,4,0),"-") -> 4331tu175 | E4: =VLOOKUP(A4,'Details local delivery'!B:L,11,0) -> 14 | F4: =SUMIFS('Details local delivery'!M:M,'Details local delivery'!G:G,'RECAP Delivery Plan '!A4) -> 10 | G4: =VLOOKUP(A4,'Details local delivery'!B:J,9,0) -> 9200 | H4: =SUMIFS('Details local delivery'!K:K,'Details local delivery'!G:G,'RECAP Delivery Plan '!A4) -> 7000 | I4: =SUMIFS('Details local delivery'!Y:Y,'Details local delivery'!B:B,A:A) -> 0 | J4: =AVERAGEIFS('Details local delivery'!W:W,'Details local delivery'!B:B,A4) -> 1 | K4: =_xlfn.MAXIFS('Details local delivery'!Z:Z,'Details local delivery'!B:B,A4) -> 0 | L4: =_xlfn.MAXIFS('Details local delivery'!AA:AA,'Details local delivery'!B:B,A4) -> 0 | M4: =IFERROR(_xlfn.MAXIFS('Details local delivery'!AB:AB,'Details local delivery'!B:B,A4),"-") -> 0 | N4: =+F4/E4 -> 0.71428571 | O4: =+H4/G4 -> 0.76086957 | P4: =K4+L4+M4 -> 0 | Q4: =P4+I4 -> 0 | R4: =Q4/P4 -> #DIV/0! | S4: =MAX(N4,O4) -> 0.76086957
A5: VOY2026COFTN04 | B5: =+IFERROR(VLOOKUP(A5,'Details local delivery'!B:C,2,0),"-") -> 46025 | C5: =B5 -> 46025 | D5: =+IFERROR(VLOOKUP(A5,'Details local delivery'!B:E,4,0),"-") -> 4331tu175 | E5: =VLOOKUP(A5,'Details local delivery'!B:L,11,0) -> 14 | F5: =SUMIFS('Details local delivery'!M:M,'Details local delivery'!G:G,'RECAP Delivery Plan '!A5) -> 10 | G5: =VLOOKUP(A5,'Details local delivery'!B:J,9,0) -> 9200 | H5: =SUMIFS('Details local delivery'!K:K,'Details local delivery'!G:G,'RECAP Delivery Plan '!A5) -> 7000 | I5: =SUMIFS('Details local delivery'!Y:Y,'Details local delivery'!B:B,A:A) -> 0 | J5: =AVERAGEIFS('Details local delivery'!W:W,'Details local delivery'!B:B,A5) -> 1 | K5: =_xlfn.MAXIFS('Details local delivery'!Z:Z,'Details local delivery'!B:B,A5) -> 0 | L5: =_xlfn.MAXIFS('Details local delivery'!AA:AA,'Details local delivery'!B:B,A5) -> 0 | M5: =_xlfn.MAXIFS('Details local delivery'!AB:AB,'Details local delivery'!B:B,A5) -> 0 | N5: =+F5/E5 -> 0.71428571 | O5: =+H5/G5 -> 0.76086957 | P5: =K5+L5+M5 -> 0 | Q5: =P5+I5 -> 0 | R5: =Q5/P5 -> #DIV/0! | S5: =MAX(N5,O5) -> 0.76086957
A6: VOY2026COFTN05 | B6: =+IFERROR(VLOOKUP(A6,'Details local delivery'!B:C,2,0),"-") -> 46027 | C6: =B6 -> 46027 | D6: =+IFERROR(VLOOKUP(A6,'Details local delivery'!B:E,4,0),"-") -> REM107627 | E6: =VLOOKUP(A6,'Details local delivery'!B:L,11,0) -> 27 | F6: =SUMIFS('Details local delivery'!M:M,'Details local delivery'!G:G,'RECAP Delivery Plan '!A6) -> 10 | G6: =VLOOKUP(A6,'Details local delivery'!B:J,9,0) -> 24950 | H6: =SUMIFS('Details local delivery'!K:K,'Details local delivery'!G:G,'RECAP Delivery Plan '!A6) -> 23000 | I6: =SUMIFS('Details local delivery'!Y:Y,'Details local delivery'!B:B,A:A) -> 0 | J6: =AVERAGEIFS('Details local delivery'!W:W,'Details local delivery'!B:B,A6) -> 1 | K6: =_xlfn.MAXIFS('Details local delivery'!Z:Z,'Details local delivery'!B:B,A6) -> 0 | L6: =_xlfn.MAXIFS('Details local delivery'!AA:AA,'Details local delivery'!B:B,A6) -> 0 | M6: =_xlfn.MAXIFS('Details local delivery'!AB:AB,'Details local delivery'!B:B,A6) -> 0 | N6: =+F6/E6 -> 0.37037037 | O6: =+H6/G6 -> 0.92184369 | P6: =K6+L6+M6 -> 0 | Q6: =P6+I6 -> 0 | R6: =Q6/P6 -> #DIV/0! | S6: =MAX(N6,O6) -> 0.92184369
A7: VOY2026COFTN06 | B7: =+IFERROR(VLOOKUP(A7,'Details local delivery'!B:C,2,0),"-") -> 46027 | C7: =B7 -> 46027 | D7: =+IFERROR(VLOOKUP(A7,'Details local delivery'!B:E,4,0),"-") -> REM107627 | E7: =VLOOKUP(A7,'Details local delivery'!B:L,11,0) -> 27 | F7: =SUMIFS('Details local delivery'!M:M,'Details local delivery'!G:G,'RECAP Delivery Plan '!A7) -> 10 | G7: =VLOOKUP(A7,'Details local delivery'!B:J,9,0) -> 24950 | H7: =SUMIFS('Details local delivery'!K:K,'Details local delivery'!G:G,'RECAP Delivery Plan '!A7) -> 22303 | I7: =SUMIFS('Details local delivery'!Y:Y,'Details local delivery'!B:B,A:A) -> 0 | J7: =AVERAGEIFS('Details local delivery'!W:W,'Details local delivery'!B:B,A7) -> 1 | K7: =_xlfn.MAXIFS('Details local delivery'!Z:Z,'Details local delivery'!B:B,A7) -> 0 | L7: =_xlfn.MAXIFS('Details local delivery'!AA:AA,'Details local delivery'!B:B,A7) -> 0 | M7: =IFERROR(_xlfn.MAXIFS('Details local delivery'!AB:AB,'Details local delivery'!B:B,A7),"-") -> 0 | N7: =+F7/E7 -> 0.37037037 | O7: =+H7/G7 -> 0.89390782 | P7: =K7+L7+M7 -> 0 | Q7: =P7+I7 -> 0 | R7: =Q7/P7 -> #DIV/0! | S7: =MAX(N7,O7) -> 0.89390782
A8: VOY2026COFTN07 | B8: =+IFERROR(VLOOKUP(A8,'Details local delivery'!B:C,2,0),"-") -> 46027 | C8: =B8 -> 46027 | D8: =+IFERROR(VLOOKUP(A8,'Details local delivery'!B:E,4,0),"-") -> 7797tu218 | E8: =VLOOKUP(A8,'Details local delivery'!B:L,11,0) -> 3 | F8: =SUMIFS('Details local delivery'!M:M,'Details local delivery'!G:G,'RECAP Delivery Plan '!A8) -> 1 | G8: =VLOOKUP(A8,'Details local delivery'!B:J,9,0) -> 927 | H8: =SUMIFS('Details local delivery'!K:K,'Details local delivery'!G:G,'RECAP Delivery Plan '!A8) -> 500 | I8: =SUMIFS('Details local delivery'!Y:Y,'Details local delivery'!B:B,A:A) -> 0 | J8: =AVERAGEIFS('Details local delivery'!W:W,'Details local delivery'!B:B,A8) -> 0.88055556 | K8: =_xlfn.MAXIFS('Details local delivery'!Z:Z,'Details local delivery'!B:B,A8) -> 0 | L8: =_xlfn.MAXIFS('Details local delivery'!AA:AA,'Details local delivery'!B:B,A8) -> 0 | M8: =IFERROR(_xlfn.MAXIFS('Details local delivery'!AB:AB,'Details local delivery'!B:B,A8),"-") -> 0 | N8: =+F8/E8 -> 0.33333333 | O8: =+H8/G8 -> 0.53937433 | P8: =K8+L8+M8 -> 0 | Q8: =P8+I8 -> 0 | R8: =Q8/P8 -> #DIV/0! | S8: =MAX(N8,O8) -> 0.53937433
A9: VOY2026COFTN08 | B9: =+IFERROR(VLOOKUP(A9,'Details local delivery'!B:C,2,0),"-") -> 46027 | C9: =B9 -> 46027 | D9: =+IFERROR(VLOOKUP(A9,'Details local delivery'!B:E,4,0),"-") -> Location | E9: =VLOOKUP(A9,'Details local delivery'!B:L,11,0) -> 4 | F9: =SUMIFS('Details local delivery'!M:M,'Details local delivery'!G:G,'RECAP Delivery Plan '!A9) -> 0 | G9: =VLOOKUP(A9,'Details local delivery'!B:J,9,0) -> 0 | H9: =SUMIFS('Details local delivery'!K:K,'Details local delivery'!G:G,'RECAP Delivery Plan '!A9) -> 936 | I9: =SUMIFS('Details local delivery'!Y:Y,'Details local delivery'!B:B,A:A) -> 0 | J9: =AVERAGEIFS('Details local delivery'!W:W,'Details local delivery'!B:B,A9) -> 1 | K9: =_xlfn.MAXIFS('Details local delivery'!Z:Z,'Details local delivery'!B:B,A9) -> 0 | L9: =_xlfn.MAXIFS('Details local delivery'!AA:AA,'Details local delivery'!B:B,A9) -> 0 | M9: =IFERROR(_xlfn.MAXIFS('Details local delivery'!AB:AB,'Details local delivery'!B:B,A9),"-") -> 0 | N9: =+F9/E9 -> 0 | O9: =+H9/G9 -> #DIV/0! | P9: =K9+L9+M9 -> 0 | Q9: =P9+I9 -> 0 | R9: =Q9/P9 -> #DIV/0! | S9: =MAX(N9,O9) -> #DIV/0!
A10: VOY2026COFTN09 | B10: =+IFERROR(VLOOKUP(A10,'Details local delivery'!B:C,2,0),"-") -> 46027 | C10: =B10 -> 46027 | D10: =+IFERROR(VLOOKUP(A10,'Details local delivery'!B:E,4,0),"-") -> 4331tu175 | E10: =VLOOKUP(A10,'Details local delivery'!B:L,11,0) -> 14 | F10: =SUMIFS('Details local delivery'!M:M,'Details local delivery'!G:G,'RECAP Delivery Plan '!A10) -> 10 | G10: =VLOOKUP(A10,'Details local delivery'!B:J,9,0) -> 9200 | H10: =SUMIFS('Details local delivery'!K:K,'Details local delivery'!G:G,'RECAP Delivery Plan '!A10) -> 2100 | I10: =SUMIFS('Details local delivery'!Y:Y,'Details local delivery'!B:B,A:A) -> 0 | J10: =AVERAGEIFS('Details local delivery'!W:W,'Details local delivery'!B:B,A10) -> 0.64166667 | K10: =_xlfn.MAXIFS('Details local delivery'!Z:Z,'Details local delivery'!B:B,A10) -> 0 | L10: =_xlfn.MAXIFS('Details local delivery'!AA:AA,'Details local delivery'!B:B,A10) -> 0 | M10: =IFERROR(_xlfn.MAXIFS('Details local delivery'!AB:AB,'Details local delivery'!B:B,A10),"-") -> 0 | N10: =+F10/E10 -> 0.71428571 | O10: =+H10/G10 -> 0.22826087 | P10: =K10+L10+M10 -> 0 | Q10: =P10+I10 -> 0 | R10: =Q10/P10 -> #DIV/0! | S10: =MAX(N10,O10) -> 0.71428571
A11: VOY2026COFTN10 | B11: =+IFERROR(VLOOKUP(A11,'Details local delivery'!B:C,2,0),"-") -> 46027 | C11: =B11 -> 46027 | D11: =+IFERROR(VLOOKUP(A11,'Details local delivery'!B:E,4,0),"-") -> 7797tu218 | E11: =VLOOKUP(A11,'Details local delivery'!B:L,11,0) -> 3 | F11: =SUMIFS('Details local delivery'!M:M,'Details local delivery'!G:G,'RECAP Delivery Plan '!A11) -> 1 | G11: =VLOOKUP(A11,'Details local delivery'!B:J,9,0) -> 927 | H11: =SUMIFS('Details local delivery'!K:K,'Details local delivery'!G:G,'RECAP Delivery Plan '!A11) -> 500 | I11: =SUMIFS('Details local delivery'!Y:Y,'Details local delivery'!B:B,A:A) -> 0 | J11: =AVERAGEIFS('Details local delivery'!W:W,'Details local delivery'!B:B,A11) -> 1 | K11: =_xlfn.MAXIFS('Details local delivery'!Z:Z,'Details local delivery'!B:B,A11) -> 0 | L11: =_xlfn.MAXIFS('Details local delivery'!AA:AA,'Details local delivery'!B:B,A11) -> 0 | M11: =IFERROR(_xlfn.MAXIFS('Details local delivery'!AB:AB,'Details local delivery'!B:B,A11),"-") -> 0 | N11: =+F11/E11 -> 0.33333333 | O11: =+H11/G11 -> 0.53937433 | P11: =K11+L11+M11 -> 0 | Q11: =P11+I11 -> 0 | R11: =Q11/P11 -> #DIV/0! | S11: =MAX(N11,O11) -> 0.53937433
A12: VOY2026COFTN11 | B12: =+IFERROR(VLOOKUP(A12,'Details local delivery'!B:C,2,0),"-") -> 46027 | C12: =B12 -> 46027 | D12: =+IFERROR(VLOOKUP(A12,'Details local delivery'!B:E,4,0),"-") -> 5735tu217 | E12: =VLOOKUP(A12,'Details local delivery'!B:L,11,0) -> 14 | F12: =SUMIFS('Details local delivery'!M:M,'Details local delivery'!G:G,'RECAP Delivery Plan '!A12) -> 10 | G12: =VLOOKUP(A12,'Details local delivery'!B:J,9,0) -> 10200 | H12: =SUMIFS('Details local delivery'!K:K,'Details local delivery'!G:G,'RECAP Delivery Plan '!A12) -> 7100 | I12: =SUMIFS('Details local delivery'!Y:Y,'Details local delivery'!B:B,A:A) -> 0 | J12: =AVERAGEIFS('Details local delivery'!W:W,'Details local delivery'!B:B,A12) -> 1 | K12: =_xlfn.MAXIFS('Details local delivery'!Z:Z,'Details local delivery'!B:B,A12) -> 0 | L12: =_xlfn.MAXIFS('Details local delivery'!AA:AA,'Details local delivery'!B:B,A12) -> 0 | M12: =IFERROR(_xlfn.MAXIFS('Details local delivery'!AB:AB,'Details local delivery'!B:B,A12),"-") -> 0 | N12: =+F12/E12 -> 0.71428571 | O12: =+H12/G12 -> 0.69607843 | P12: =K12+L12+M12 -> 0 | Q12: =P12+I12 -> 0 | R12: =Q12/P12 -> #DIV/0! | S12: =MAX(N12,O12) -> 0.71428571
A13: VOY2026COFTN12 | B13: =+IFERROR(VLOOKUP(A13,'Details local delivery'!B:C,2,0),"-") -> 46027 | C13: =B13 -> 46027 | D13: =+IFERROR(VLOOKUP(A13,'Details local delivery'!B:E,4,0),"-") -> 2282tu131 | E13: =VLOOKUP(A13,'Details local delivery'!B:L,11,0) -> 14 | F13: =SUMIFS('Details local delivery'!M:M,'Details local delivery'!G:G,'RECAP Delivery Plan '!A13) -> 10 | G13: =VLOOKUP(A13,'Details local delivery'!B:J,9,0) -> 10200 | H13: =SUMIFS('Details local delivery'!K:K,'Details local delivery'!G:G,'RECAP Delivery Plan '!A13) -> 2810.6 | I13: =SUMIFS('Details local delivery'!Y:Y,'Details local delivery'!B:B,A:A) -> 0 | J13: =AVERAGEIFS('Details local delivery'!W:W,'Details local delivery'!B:B,A13) -> 0.90833333 | K13: =_xlfn.MAXIFS('Details local delivery'!Z:Z,'Details local delivery'!B:B,A13) -> 0 | L13: =_xlfn.MAXIFS('Details local delivery'!AA:AA,'Details local delivery'!B:B,A13) -> 0 | M13: =IFERROR(_xlfn.MAXIFS('Details local delivery'!AB:AB,'Details local delivery'!B:B,A13),"-") -> 0 | N13: =+F13/E13 -> 0.71428571 | O13: =+H13/G13 -> 0.27554902 | P13: =K13+L13+M13 -> 0 | Q13: =P13+I13 -> 0 | R13: =Q13/P13 -> #DIV/0! | S13: =MAX(N13,O13) -> 0.71428571
A14: VOY2026COFTN13 | B14: =+IFERROR(VLOOKUP(A14,'Details local delivery'!B:C,2,0),"-") -> 46027 | C14: =B14 -> 46027 | D14: =+IFERROR(VLOOKUP(A14,'Details local delivery'!B:E,4,0),"-") -> 5735tu217 | E14: =VLOOKUP(A14,'Details local delivery'!B:L,11,0) -> 14 | F14: =SUMIFS('Details local delivery'!M:M,'Details local delivery'!G:G,'RECAP Delivery Plan '!A14) -> 10 | G14: =VLOOKUP(A14,'Details local delivery'!B:J,9,0) -> 10200 | H14: =SUMIFS('Details local delivery'!K:K,'Details local delivery'!G:G,'RECAP Delivery Plan '!A14) -> 6500 | I14: =SUMIFS('Details local delivery'!Y:Y,'Details local delivery'!B:B,A:A) -> 0 | J14: =AVERAGEIFS('Details local delivery'!W:W,'Details local delivery'!B:B,A14) -> 1 | K14: =_xlfn.MAXIFS('Details local delivery'!Z:Z,'Details local delivery'!B:B,A14) -> 0 | L14: =_xlfn.MAXIFS('Details local delivery'!AA:AA,'Details local delivery'!B:B,A14) -> 0 | M14: =IFERROR(_xlfn.MAXIFS('Details local delivery'!AB:AB,'Details local delivery'!B:B,A14),"-") -> 0 | N14: =+F14/E14 -> 0.71428571 | O14: =+H14/G14 -> 0.6372549 | P14: =K14+L14+M14 -> 0 | Q14: =P14+I14 -> 0 | R14: =Q14/P14 -> #DIV/0! | S14: =MAX(N14,O14) -> 0.71428571
A15: VOY2026COFTN14 | B15: =+IFERROR(VLOOKUP(A15,'Details local delivery'!B:C,2,0),"-") -> 46027 | C15: =B15 -> 46027 | D15: =+IFERROR(VLOOKUP(A15,'Details local delivery'!B:E,4,0),"-") -> 5735tu217 | E15: =VLOOKUP(A15,'Details local delivery'!B:L,11,0) -> 14 | F15: =SUMIFS('Details local delivery'!M:M,'Details local delivery'!G:G,'RECAP Delivery Plan '!A15) -> 10 | G15: =VLOOKUP(A15,'Details local delivery'!B:J,9,0) -> 10200 | H15: =SUMIFS('Details local delivery'!K:K,'Details local delivery'!G:G,'RECAP Delivery Plan '!A15) -> 7100 | I15: =SUMIFS('Details local delivery'!Y:Y,'Details local delivery'!B:B,A:A) -> 0 | J15: =AVERAGEIFS('Details local delivery'!W:W,'Details local delivery'!B:B,A15) -> 1 | K15: =_xlfn.MAXIFS('Details local delivery'!Z:Z,'Details local delivery'!B:B,A15) -> 0 | L15: =_xlfn.MAXIFS('Details local delivery'!AA:AA,'Details local delivery'!B:B,A15) -> 0 | M15: =IFERROR(_xlfn.MAXIFS('Details local delivery'!AB:AB,'Details local delivery'!B:B,A15),"-") -> 0 | N15: =+F15/E15 -> 0.71428571 | O15: =+H15/G15 -> 0.69607843 | P15: =K15+L15+M15 -> 0 | Q15: =P15+I15 -> 0 | R15: =Q15/P15 -> #DIV/0! | S15: =MAX(N15,O15) -> 0.71428571
A16: VOY2026COFTN15 | B16: =+IFERROR(VLOOKUP(A16,'Details local delivery'!B:C,2,0),"-") -> 46027 | C16: =B16 -> 46027 | D16: =+IFERROR(VLOOKUP(A16,'Details local delivery'!B:E,4,0),"-") -> 7797tu218 | E16: =VLOOKUP(A16,'Details local delivery'!B:L,11,0) -> 3 | F16: =SUMIFS('Details local delivery'!M:M,'Details local delivery'!G:G,'RECAP Delivery Plan '!A16) -> 1 | G16: =VLOOKUP(A16,'Details local delivery'!B:J,9,0) -> 927 | H16: =SUMIFS('Details local delivery'!K:K,'Details local delivery'!G:G,'RECAP Delivery Plan '!A16) -> 500 | I16: =SUMIFS('Details local delivery'!Y:Y,'Details local delivery'!B:B,A:A) -> 0 | J16: =AVERAGEIFS('Details local delivery'!W:W,'Details local delivery'!B:B,A16) -> 1 | K16: =_xlfn.MAXIFS('Details local delivery'!Z:Z,'Details local delivery'!B:B,A16) -> 0 | L16: =_xlfn.MAXIFS('Details local delivery'!AA:AA,'Details local delivery'!B:B,A16) -> 0 | M16: =_xlfn.MAXIFS('Details local delivery'!AB:AB,'Details local delivery'!B:B,A16) -> 0 | N16: =+F16/E16 -> 0.33333333 | O16: =+H16/G16 -> 0.53937433 | P16: =K16+L16+M16 -> 0 | Q16: =P16+I16 -> 0 | R16: =Q16/P16 -> #DIV/0! | S16: =MAX(N16,O16) -> 0.53937433
A17: VOY2026COFTN16 | B17: =+IFERROR(VLOOKUP(A17,'Details local delivery'!B:C,2,0),"-") -> 46027 | C17: =B17 -> 46027 | D17: =+IFERROR(VLOOKUP(A17,'Details local delivery'!B:E,4,0),"-") -> 9524TU238 | E17: =VLOOKUP(A17,'Details local delivery'!B:L,11,0) -> 14 | F17: =SUMIFS('Details local delivery'!M:M,'Details local delivery'!G:G,'RECAP Delivery Plan '!A17) -> 10 | G17: =VLOOKUP(A17,'Details local delivery'!B:J,9,0) -> 10230 | H17: =SUMIFS('Details local delivery'!K:K,'Details local delivery'!G:G,'RECAP Delivery Plan '!A17) -> 10000 | I17: =SUMIFS('Details local delivery'!Y:Y,'Details local delivery'!B:B,A:A) -> 0 | J17: =AVERAGEIFS('Details local delivery'!W:W,'Details local delivery'!B:B,A17) -> 0.85 | K17: =_xlfn.MAXIFS('Details local delivery'!Z:Z,'Details local delivery'!B:B,A17) -> 0 | L17: =_xlfn.MAXIFS('Details local delivery'!AA:AA,'Details local delivery'!B:B,A17) -> 0 | M17: =_xlfn.MAXIFS('Details local delivery'!AB:AB,'Details local delivery'!B:B,A17) -> 0 | N17: =+F17/E17 -> 0.71428571 | O17: =+H17/G17 -> 0.97751711 | P17: =K17+L17+M17 -> 0 | Q17: =P17+I17 -> 0 | R17: =Q17/P17 -> #DIV/0! | S17: =MAX(N17,O17) -> 0.97751711
A18: VOY2026COFTN17 | B18: =+IFERROR(VLOOKUP(A18,'Details local delivery'!B:C,2,0),"-") -> 46027 | C18: =B18 -> 46027 | D18: =+IFERROR(VLOOKUP(A18,'Details local delivery'!B:E,4,0),"-") -> 5735tu217 | E18: =VLOOKUP(A18,'Details local delivery'!B:L,11,0) -> 14 | F18: =SUMIFS('Details local delivery'!M:M,'Details local delivery'!G:G,'RECAP Delivery Plan '!A18) -> 10 | G18: =VLOOKUP(A18,'Details local delivery'!B:J,9,0) -> 10200 | H18: =SUMIFS('Details local delivery'!K:K,'Details local delivery'!G:G,'RECAP Delivery Plan '!A18) -> 7100 | I18: =SUMIFS('Details local delivery'!Y:Y,'Details local delivery'!B:B,A:A) -> 0 | J18: =AVERAGEIFS('Details local delivery'!W:W,'Details local delivery'!B:B,A18) -> 1 | K18: =_xlfn.MAXIFS('Details local delivery'!Z:Z,'Details local delivery'!B:B,A18) -> 0 | L18: =_xlfn.MAXIFS('Details local delivery'!AA:AA,'Details local delivery'!B:B,A18) -> 0 | M18: =IFERROR(_xlfn.MAXIFS('Details local delivery'!AB:AB,'Details local delivery'!B:B,A18),"-") -> 0 | N18: =+F18/E18 -> 0.71428571 | O18: =+H18/G18 -> 0.69607843 | P18: =K18+L18+M18 -> 0 | Q18: =P18+I18 -> 0 | R18: =Q18/P18 -> #DIV/0! | S18: =MAX(N18,O18) -> 0.71428571
A19: VOY2026COFTN18 | B19: =+IFERROR(VLOOKUP(A19,'Details local delivery'!B:C,2,0),"-") -> 46027 | C19: =B19 -> 46027 | D19: =+IFERROR(VLOOKUP(A19,'Details local delivery'!B:E,4,0),"-") -> 5735tu217 | E19: =VLOOKUP(A19,'Details local delivery'!B:L,11,0) -> 14 | F19: =SUMIFS('Details local delivery'!M:M,'Details local delivery'!G:G,'RECAP Delivery Plan '!A19) -> 10 | G19: =VLOOKUP(A19,'Details local delivery'!B:J,9,0) -> 10200 | H19: =SUMIFS('Details local delivery'!K:K,'Details local delivery'!G:G,'RECAP Delivery Plan '!A19) -> 7100 | I19: =SUMIFS('Details local delivery'!Y:Y,'Details local delivery'!B:B,A:A) -> 0 | J19: =AVERAGEIFS('Details local delivery'!W:W,'Details local delivery'!B:B,A19) -> 1 | K19: =_xlfn.MAXIFS('Details local delivery'!Z:Z,'Details local delivery'!B:B,A19) -> 0 | L19: =_xlfn.MAXIFS('Details local delivery'!AA:AA,'Details local delivery'!B:B,A19) -> 0 | M19: =_xlfn.MAXIFS('Details local delivery'!AB:AB,'Details local delivery'!B:B,A19) -> 0 | N19: =+F19/E19 -> 0.71428571 | O19: =+H19/G19 -> 0.69607843 | P19: =K19+L19+M19 -> 0 | Q19: =P19+I19 -> 0 | R19: =Q19/P19 -> #DIV/0! | S19: =MAX(N19,O19) -> 0.71428571
A20: VOY2026COFTN19 | B20: =+IFERROR(VLOOKUP(A20,'Details local delivery'!B:C,2,0),"-") -> 46028 | C20: =B20 -> 46028 | D20: =+IFERROR(VLOOKUP(A20,'Details local delivery'!B:E,4,0),"-") -> REM107627 | E20: =VLOOKUP(A20,'Details local delivery'!B:L,11,0) -> 27 | F20: =SUMIFS('Details local delivery'!M:M,'Details local delivery'!G:G,'RECAP Delivery Plan '!A20) -> 24 | G20: =VLOOKUP(A20,'Details local delivery'!B:J,9,0) -> 24950 | H20: =SUMIFS('Details local delivery'!K:K,'Details local delivery'!G:G,'RECAP Delivery Plan '!A20) -> 20400 | I20: =SUMIFS('Details local delivery'!Y:Y,'Details local delivery'!B:B,A:A) -> 0 | J20: =AVERAGEIFS('Details local delivery'!W:W,'Details local delivery'!B:B,A20) -> 0.9375 | K20: =_xlfn.MAXIFS('Details local delivery'!Z:Z,'Details local delivery'!B:B,A20) -> 0 | L20: =_xlfn.MAXIFS('Details local delivery'!AA:AA,'Details local delivery'!B:B,A20) -> 0 | M20: =IFERROR(_xlfn.MAXIFS('Details local delivery'!AB:AB,'Details local delivery'!B:B,A20),"-") -> 0 | N20: =+F20/E20 -> 0.88888889 | O20: =+H20/G20 -> 0.81763527 | P20: =K20+L20+M20 -> 0 | Q20: =P20+I20 -> 0 | R20: =Q20/P20 -> #DIV/0! | S20: =MAX(N20,O20) -> 0.88888889
A21: VOY2026COFTN20 | B21: =+IFERROR(VLOOKUP(A21,'Details local delivery'!B:C,2,0),"-") -> 46028 | C21: =B21 -> 46028 | D21: =+IFERROR(VLOOKUP(A21,'Details local delivery'!B:E,4,0),"-") -> 4331tu175 | E21: =VLOOKUP(A21,'Details local delivery'!B:L,11,0) -> 14 | F21: =SUMIFS('Details local delivery'!M:M,'Details local delivery'!G:G,'RECAP Delivery Plan '!A21) -> 14 | G21: =VLOOKUP(A21,'Details local delivery'!B:J,9,0) -> 9200 | H21: =SUMIFS('Details local delivery'!K:K,'Details local delivery'!G:G,'RECAP Delivery Plan '!A21) -> 5500 | I21: =SUMIFS('Details local delivery'!Y:Y,'Details local delivery'!B:B,A:A) -> 0 | J21: =AVERAGEIFS('Details local delivery'!W:W,'Details local delivery'!B:B,A21) -> 1 | K21: =_xlfn.MAXIFS('Details local delivery'!Z:Z,'Details local delivery'!B:B,A21) -> 0 | L21: =_xlfn.MAXIFS('Details local delivery'!AA:AA,'Details local delivery'!B:B,A21) -> 0 | M21: =IFERROR(_xlfn.MAXIFS('Details local delivery'!AB:AB,'Details local delivery'!B:B,A21),"-") -> 0 | N21: =+F21/E21 -> 1 | O21: =+H21/G21 -> 0.59782609 | P21: =K21+L21+M21 -> 0 | Q21: =P21+I21 -> 0 | R21: =Q21/P21 -> #DIV/0! | S21: =MAX(N21,O21) -> 1
A22: VOY2026COFTN21 | B22: =+IFERROR(VLOOKUP(A22,'Details local delivery'!B:C,2,0),"-") -> 46028 | C22: =B22 -> 46028 | D22: =+IFERROR(VLOOKUP(A22,'Details local delivery'!B:E,4,0),"-") -> Location | E22: =VLOOKUP(A22,'Details local delivery'!B:L,11,0) -> 0 | F22: =SUMIFS('Details local delivery'!M:M,'Details local delivery'!G:G,'RECAP Delivery Plan '!A22) -> 33 | G22: =VLOOKUP(A22,'Details local delivery'!B:J,9,0) -> 0 | H22: =SUMIFS('Details local delivery'!K:K,'Details local delivery'!G:G,'RECAP Delivery Plan '!A22) -> 0 | I22: =SUMIFS('Details local delivery'!Y:Y,'Details local delivery'!B:B,A:A) -> 0 | J22: =AVERAGEIFS('Details local delivery'!W:W,'Details local delivery'!B:B,A22) -> 1 | K22: =_xlfn.MAXIFS('Details local delivery'!Z:Z,'Details local delivery'!B:B,A22) -> 0 | L22: =_xlfn.MAXIFS('Details local delivery'!AA:AA,'Details local delivery'!B:B,A22) -> 0 | M22: =IFERROR(_xlfn.MAXIFS('Details local delivery'!AB:AB,'Details local delivery'!B:B,A22),"-") -> 0 | N22: =+F22/E22 -> #DIV/0! | O22: =+H22/G22 -> #DIV/0! | P22: =K22+L22+M22 -> 0 | Q22: =P22+I22 -> 0 | R22: =Q22/P22 -> #DIV/0! | S22: =MAX(N22,O22) -> #DIV/0!
A23: VOY2026COFTN22 | B23: =+IFERROR(VLOOKUP(A23,'Details local delivery'!B:C,2,0),"-") -> 46028 | C23: =B23 -> 46028 | D23: =+IFERROR(VLOOKUP(A23,'Details local delivery'!B:E,4,0),"-") -> 2282tu131 | E23: =VLOOKUP(A23,'Details local delivery'!B:L,11,0) -> 14 | F23: =SUMIFS('Details local delivery'!M:M,'Details local delivery'!G:G,'RECAP Delivery Plan '!A23) -> 11 | G23: =VLOOKUP(A23,'Details local delivery'!B:J,9,0) -> 10200 | H23: =SUMIFS('Details local delivery'!K:K,'Details local delivery'!G:G,'RECAP Delivery Plan '!A23) -> 10200 | I23: =SUMIFS('Details local delivery'!Y:Y,'Details local delivery'!B:B,A:A) -> 0 | J23: =AVERAGEIFS('Details local delivery'!W:W,'Details local delivery'!B:B,A23) -> 1 | K23: =_xlfn.MAXIFS('Details local delivery'!Z:Z,'Details local delivery'!B:B,A23) -> 0 | L23: =_xlfn.MAXIFS('Details local delivery'!AA:AA,'Details local delivery'!B:B,A23) -> 0 | M23: =IFERROR(_xlfn.MAXIFS('Details local delivery'!AB:AB,'Details local delivery'!B:B,A23),"-") -> 0 | N23: =+F23/E23 -> 0.78571429 | O23: =+H23/G23 -> 1 | P23: =K23+L23+M23 -> 0 | Q23: =P23+I23 -> 0 | R23: =Q23/P23 -> #DIV/0! | S23: =MAX(N23,O23) -> 1
A24: VOY2026COFTN23 | B24: =+IFERROR(VLOOKUP(A24,'Details local delivery'!B:C,2,0),"-") -> 46028 | C24: =B24 -> 46028 | D24: =+IFERROR(VLOOKUP(A24,'Details local delivery'!B:E,4,0),"-") -> 2282tu131 | E24: =VLOOKUP(A24,'Details local delivery'!B:L,11,0) -> 14 | F24: =SUMIFS('Details local delivery'!M:M,'Details local delivery'!G:G,'RECAP Delivery Plan '!A24) -> 10 | G24: =VLOOKUP(A24,'Details local delivery'!B:J,9,0) -> 10200 | H24: =SUMIFS('Details local delivery'!K:K,'Details local delivery'!G:G,'RECAP Delivery Plan '!A24) -> 10000 | I24: =SUMIFS('Details local delivery'!Y:Y,'Details local delivery'!B:B,A:A) -> 0 | J24: =AVERAGEIFS('Details local delivery'!W:W,'Details local delivery'!B:B,A24) -> 1 | K24: =_xlfn.MAXIFS('Details local delivery'!Z:Z,'Details local delivery'!B:B,A24) -> 0 | L24: =_xlfn.MAXIFS('Details local delivery'!AA:AA,'Details local delivery'!B:B,A24) -> 0 | M24: =_xlfn.MAXIFS('Details local delivery'!AB:AB,'Details local delivery'!B:B,A24) -> 0 | N24: =+F24/E24 -> 0.71428571 | O24: =+H24/G24 -> 0.98039216 | P24: =K24+L24+M24 -> 0 | Q24: =P24+I24 -> 0 | R24: =Q24/P24 -> #DIV/0! | S24: =MAX(N24,O24) -> 0.98039216
A25: VOY2026COFTN24 | B25: =+IFERROR(VLOOKUP(A25,'Details local delivery'!B:C,2,0),"-") -> 46028 | C25: =B25 -> 46028 | D25: =+IFERROR(VLOOKUP(A25,'Details local delivery'!B:E,4,0),"-") -> 7797tu218 | E25: =VLOOKUP(A25,'Details local delivery'!B:L,11,0) -> 3 | F25: =SUMIFS('Details local delivery'!M:M,'Details local delivery'!G:G,'RECAP Delivery Plan '!A25) -> 3 | G25: =VLOOKUP(A25,'Details local delivery'!B:J,9,0) -> 927 | H25: =SUMIFS('Details local delivery'!K:K,'Details local delivery'!G:G,'RECAP Delivery Plan '!A25) -> 500 | I25: =SUMIFS('Details local delivery'!Y:Y,'Details local delivery'!B:B,A:A) -> 0 | J25: =AVERAGEIFS('Details local delivery'!W:W,'Details local delivery'!B:B,A25) -> 1 | K25: =_xlfn.MAXIFS('Details local delivery'!Z:Z,'Details local delivery'!B:B,A25) -> 0 | L25: =_xlfn.MAXIFS('Details local delivery'!AA:AA,'Details local delivery'!B:B,A25) -> 0 | M25: =IFERROR(_xlfn.MAXIFS('Details local delivery'!AB:AB,'Details local delivery'!B:B,A25),"-") -> 0 | N25: =+F25/E25 -> 1 | O25: =+H25/G25 -> 0.53937433 | P25: =K25+L25+M25 -> 0 | Q25: =P25+I25 -> 0 | R25: =Q25/P25 -> #DIV/0! | S25: =MAX(N25,O25) -> 1
A26: VOY2026COFTN25 | B26: =+IFERROR(VLOOKUP(A26,'Details local delivery'!B:C,2,0),"-") -> 46028 | C26: =B26 -> 46028 | D26: =+IFERROR(VLOOKUP(A26,'Details local delivery'!B:E,4,0),"-") -> 9524TU238 | E26: =VLOOKUP(A26,'Details local delivery'!B:L,11,0) -> 14 | F26: =SUMIFS('Details local delivery'!M:M,'Details local delivery'!G:G,'RECAP Delivery Plan '!A26) -> 10 | G26: =VLOOKUP(A26,'Details local delivery'!B:J,9,0) -> 10230 | H26: =SUMIFS('Details local delivery'!K:K,'Details local delivery'!G:G,'RECAP Delivery Plan '!A26) -> 10200 | I26: =SUMIFS('Details local delivery'!Y:Y,'Details local delivery'!B:B,A:A) -> 0 | J26: =AVERAGEIFS('Details local delivery'!W:W,'Details local delivery'!B:B,A26) -> 1 | K26: =_xlfn.MAXIFS('Details local delivery'!Z:Z,'Details local delivery'!B:B,A26) -> 0 | L26: =_xlfn.MAXIFS('Details local delivery'!AA:AA,'Details local delivery'!B:B,A26) -> 0 | M26: =IFERROR(_xlfn.MAXIFS('Details local delivery'!AB:AB,'Details local delivery'!B:B,A26),"-") -> 0 | N26: =+F26/E26 -> 0.71428571 | O26: =+H26/G26 -> 0.99706745 | P26: =K26+L26+M26 -> 0 | Q26: =P26+I26 -> 0 | R26: =Q26/P26 -> #DIV/0! | S26: =MAX(N26,O26) -> 0.99706745
A27: VOY2026COFTN26 | B27: =+IFERROR(VLOOKUP(A27,'Details local delivery'!B:C,2,0),"-") -> 46028 | C27: =B27 -> 46028 | D27: =+IFERROR(VLOOKUP(A27,'Details local delivery'!B:E,4,0),"-") -> 9524TU238 | E27: =VLOOKUP(A27,'Details local delivery'!B:L,11,0) -> 14 | F27: =SUMIFS('Details local delivery'!M:M,'Details local delivery'!G:G,'RECAP Delivery Plan '!A27) -> 14 | G27: =VLOOKUP(A27,'Details local delivery'!B:J,9,0) -> 10230 | H27: =SUMIFS('Details local delivery'!K:K,'Details local delivery'!G:G,'RECAP Delivery Plan '!A27) -> 10200 | I27: =SUMIFS('Details local delivery'!Y:Y,'Details local delivery'!B:B,A:A) -> 0 | J27: =AVERAGEIFS('Details local delivery'!W:W,'Details local delivery'!B:B,A27) -> 1 | K27: =_xlfn.MAXIFS('Details local delivery'!Z:Z,'Details local delivery'!B:B,A27) -> 0 | L27: =_xlfn.MAXIFS('Details local delivery'!AA:AA,'Details local delivery'!B:B,A27) -> 0 | M27: =IFERROR(_xlfn.MAXIFS('Details local delivery'!AB:AB,'Details local delivery'!B:B,A27),"-") -> 0 | N27: =+F27/E27 -> 1 | O27: =+H27/G27 -> 0.99706745 | P27: =K27+L27+M27 -> 0 | Q27: =P27+I27 -> 0 | R27: =Q27/P27 -> #DIV/0! | S27: =MAX(N27,O27) -> 1
A28: VOY2026COFTN27 | B28: =+IFERROR(VLOOKUP(A28,'Details local delivery'!B:C,2,0),"-") -> 46028 | C28: =B28 -> 46028 | D28: =+IFERROR(VLOOKUP(A28,'Details local delivery'!B:E,4,0),"-") -> 4331tu175 | E28: =VLOOKUP(A28,'Details local delivery'!B:L,11,0) -> 14 | F28: =SUMIFS('Details local delivery'!M:M,'Details local delivery'!G:G,'RECAP Delivery Plan '!A28) -> 7 | G28: =VLOOKUP(A28,'Details local delivery'!B:J,9,0) -> 9200 | H28: =SUMIFS('Details local delivery'!K:K,'Details local delivery'!G:G,'RECAP Delivery Plan '!A28) -> 5000 | I28: =SUMIFS('Details local delivery'!Y:Y,'Details local delivery'!B:B,A:A) -> 0 | J28: =AVERAGEIFS('Details local delivery'!W:W,'Details local delivery'!B:B,A28) -> 1 | K28: =_xlfn.MAXIFS('Details local delivery'!Z:Z,'Details local delivery'!B:B,A28) -> 0 | L28: =_xlfn.MAXIFS('Details local delivery'!AA:AA,'Details local delivery'!B:B,A28) -> 0 | M28: =_xlfn.MAXIFS('Details local delivery'!AB:AB,'Details local delivery'!B:B,A28) -> 0 | N28: =+F28/E28 -> 0.5 | O28: =+H28/G28 -> 0.54347826 | P28: =K28+L28+M28 -> 0 | Q28: =P28+I28 -> 0 | R28: =Q28/P28 -> #DIV/0! | S28: =MAX(N28,O28) -> 0.54347826
A29: VOY2026COFTN28 | B29: =+IFERROR(VLOOKUP(A29,'Details local delivery'!B:C,2,0),"-") -> 46028 | C29: =B29 -> 46028 | D29: =+IFERROR(VLOOKUP(A29,'Details local delivery'!B:E,4,0),"-") -> 4331tu175 | E29: =VLOOKUP(A29,'Details local delivery'!B:L,11,0) -> 14 | F29: =SUMIFS('Details local delivery'!M:M,'Details local delivery'!G:G,'RECAP Delivery Plan '!A29) -> 14 | G29: =VLOOKUP(A29,'Details local delivery'!B:J,9,0) -> 9200 | H29: =SUMIFS('Details local delivery'!K:K,'Details local delivery'!G:G,'RECAP Delivery Plan '!A29) -> 6000 | I29: =SUMIFS('Details local delivery'!Y:Y,'Details local delivery'!B:B,A:A) -> 0 | J29: =AVERAGEIFS('Details local delivery'!W:W,'Details local delivery'!B:B,A29) -> 0.98333333 | K29: =_xlfn.MAXIFS('Details local delivery'!Z:Z,'Details local delivery'!B:B,A29) -> 0 | L29: =_xlfn.MAXIFS('Details local delivery'!AA:AA,'Details local delivery'!B:B,A29) -> 0 | M29: =_xlfn.MAXIFS('Details local delivery'!AB:AB,'Details local delivery'!B:B,A29) -> 0 | N29: =+F29/E29 -> 1 | O29: =+H29/G29 -> 0.65217391 | P29: =K29+L29+M29 -> 0 | Q29: =P29+I29 -> 0 | R29: =Q29/P29 -> #DIV/0! | S29: =MAX(N29,O29) -> 1
A30: VOY2026COFTN29 | B30: =+IFERROR(VLOOKUP(A30,'Details local delivery'!B:C,2,0),"-") -> 46028 | C30: =B30 -> 46028 | D30: =+IFERROR(VLOOKUP(A30,'Details local delivery'!B:E,4,0),"-") -> Location | E30: =VLOOKUP(A30,'Details local delivery'!B:L,11,0) -> 0 | F30: =SUMIFS('Details local delivery'!M:M,'Details local delivery'!G:G,'RECAP Delivery Plan '!A30) -> 27 | G30: =VLOOKUP(A30,'Details local delivery'!B:J,9,0) -> 0 | H30: =SUMIFS('Details local delivery'!K:K,'Details local delivery'!G:G,'RECAP Delivery Plan '!A30) -> 0 | I30: =SUMIFS('Details local delivery'!Y:Y,'Details local delivery'!B:B,A:A) -> 0 | J30: =AVERAGEIFS('Details local delivery'!W:W,'Details local delivery'!B:B,A30) -> 1 | K30: =_xlfn.MAXIFS('Details local delivery'!Z:Z,'Details local delivery'!B:B,A30) -> 0 | L30: =_xlfn.MAXIFS('Details local delivery'!AA:AA,'Details local delivery'!B:B,A30) -> 0 | M30: =_xlfn.MAXIFS('Details local delivery'!AB:AB,'Details local delivery'!B:B,A30) -> 0 | N30: =+F30/E30 -> #DIV/0! | O30: =+H30/G30 -> #DIV/0! | P30: =K30+L30+M30 -> 0 | Q30: =P30+I30 -> 0 | R30: =Q30/P30 -> #DIV/0! | S30: =MAX(N30,O30) -> #DIV/0!
A31: VOY2026COFTN30 | B31: =+IFERROR(VLOOKUP(A31,'Details local delivery'!B:C,2,0),"-") -> 46028 | C31: =B31 -> 46028 | D31: =+IFERROR(VLOOKUP(A31,'Details local delivery'!B:E,4,0),"-") -> 2282tu131 | E31: =VLOOKUP(A31,'Details local delivery'!B:L,11,0) -> 14 | F31: =SUMIFS('Details local delivery'!M:M,'Details local delivery'!G:G,'RECAP Delivery Plan '!A31) -> 10 | G31: =VLOOKUP(A31,'Details local delivery'!B:J,9,0) -> 10200 | H31: =SUMIFS('Details local delivery'!K:K,'Details local delivery'!G:G,'RECAP Delivery Plan '!A31) -> 10000 | I31: =SUMIFS('Details local delivery'!Y:Y,'Details local delivery'!B:B,A:A) -> 0 | J31: =AVERAGEIFS('Details local delivery'!W:W,'Details local delivery'!B:B,A31) -> 1 | K31: =_xlfn.MAXIFS('Details local delivery'!Z:Z,'Details local delivery'!B:B,A31) -> 0 | L31: =_xlfn.MAXIFS('Details local delivery'!AA:AA,'Details local delivery'!B:B,A31) -> 0 | M31: =_xlfn.MAXIFS('Details local delivery'!AB:AB,'Details local delivery'!B:B,A31) -> 0 | N31: =+F31/E31 -> 0.71428571 | O31: =+H31/G31 -> 0.98039216 | P31: =K31+L31+M31 -> 0 | Q31: =P31+I31 -> 0 | R31: =Q31/P31 -> #DIV/0! | S31: =MAX(N31,O31) -> 0.98039216
A32: VOY2026COFTN31 | B32: =+IFERROR(VLOOKUP(A32,'Details local delivery'!B:C,2,0),"-") -> 46029 | C32: =B32 -> 46029 | D32: =+IFERROR(VLOOKUP(A32,'Details local delivery'!B:E,4,0),"-") -> 9524TU238 | E32: =VLOOKUP(A32,'Details local delivery'!B:L,11,0) -> 14 | F32: =SUMIFS('Details local delivery'!M:M,'Details local delivery'!G:G,'RECAP Delivery Plan '!A32) -> 11 | G32: =VLOOKUP(A32,'Details local delivery'!B:J,9,0) -> 10230 | H32: =SUMIFS('Details local delivery'!K:K,'Details local delivery'!G:G,'RECAP Delivery Plan '!A32) -> 8000 | I32: =SUMIFS('Details local delivery'!Y:Y,'Details local delivery'!B:B,A:A) -> 0 | J32: =AVERAGEIFS('Details local delivery'!W:W,'Details local delivery'!B:B,A32) -> 1 | K32: =_xlfn.MAXIFS('Details local delivery'!Z:Z,'Details local delivery'!B:B,A32) -> 0 | L32: =_xlfn.MAXIFS('Details local delivery'!AA:AA,'Details local delivery'!B:B,A32) -> 0 | M32: =IFERROR(_xlfn.MAXIFS('Details local delivery'!AB:AB,'Details local delivery'!B:B,A32),"-") -> 0 | N32: =+F32/E32 -> 0.78571429 | O32: =+H32/G32 -> 0.78201369 | P32: =K32+L32+M32 -> 0 | Q32: =P32+I32 -> 0 | R32: =Q32/P32 -> #DIV/0! | S32: =MAX(N32,O32) -> 0.78571429
A33: VOY2026COFTN32 | B33: =+IFERROR(VLOOKUP(A33,'Details local delivery'!B:C,2,0),"-") -> 46029 | C33: =B33 -> 46029 | D33: =+IFERROR(VLOOKUP(A33,'Details local delivery'!B:E,4,0),"-") -> 9524TU238 | E33: =VLOOKUP(A33,'Details local delivery'!B:L,11,0) -> 14 | F33: =SUMIFS('Details local delivery'!M:M,'Details local delivery'!G:G,'RECAP Delivery Plan '!A33) -> 9 | G33: =VLOOKUP(A33,'Details local delivery'!B:J,9,0) -> 10230 | H33: =SUMIFS('Details local delivery'!K:K,'Details local delivery'!G:G,'RECAP Delivery Plan '!A33) -> 10000 | I33: =SUMIFS('Details local delivery'!Y:Y,'Details local delivery'!B:B,A:A) -> 0 | J33: =AVERAGEIFS('Details local delivery'!W:W,'Details local delivery'!B:B,A33) -> 1 | K33: =_xlfn.MAXIFS('Details local delivery'!Z:Z,'Details local delivery'!B:B,A33) -> 0 | L33: =_xlfn.MAXIFS('Details local delivery'!AA:AA,'Details local delivery'!B:B,A33) -> 0 | M33: =_xlfn.MAXIFS('Details local delivery'!AB:AB,'Details local delivery'!B:B,A33) -> 0 | N33: =+F33/E33 -> 0.64285714 | O33: =+H33/G33 -> 0.97751711 | P33: =K33+L33+M33 -> 0 | Q33: =P33+I33 -> 0 | R33: =Q33/P33 -> #DIV/0! | S33: =MAX(N33,O33) -> 0.97751711
A34: VOY2026COFTN33 | B34: =+IFERROR(VLOOKUP(A34,'Details local delivery'!B:C,2,0),"-") -> 46029 | C34: =B34 -> 46029 | D34: =+IFERROR(VLOOKUP(A34,'Details local delivery'!B:E,4,0),"-") -> Location | E34: =VLOOKUP(A34,'Details local delivery'!B:L,11,0) -> 0 | F34: =SUMIFS('Details local delivery'!M:M,'Details local delivery'!G:G,'RECAP Delivery Plan '!A34) -> 22 | G34: =VLOOKUP(A34,'Details local delivery'!B:J,9,0) -> 0 | H34: =SUMIFS('Details local delivery'!K:K,'Details local delivery'!G:G,'RECAP Delivery Plan '!A34) -> 0 | I34: =SUMIFS('Details local delivery'!Y:Y,'Details local delivery'!B:B,A:A) -> 0 | J34: =AVERAGEIFS('Details local delivery'!W:W,'Details local delivery'!B:B,A34) -> 1 | K34: =_xlfn.MAXIFS('Details local delivery'!Z:Z,'Details local delivery'!B:B,A34) -> 0 | L34: =_xlfn.MAXIFS('Details local delivery'!AA:AA,'Details local delivery'!B:B,A34) -> 0 | M34: =IFERROR(_xlfn.MAXIFS('Details local delivery'!AB:AB,'Details local delivery'!B:B,A34),"-") -> 0 | N34: =+F34/E34 -> #DIV/0! | O34: =+H34/G34 -> #DIV/0! | P34: =K34+L34+M34 -> 0 | Q34: =P34+I34 -> 0 | R34: =Q34/P34 -> #DIV/0! | S34: =MAX(N34,O34) -> #DIV/0! | U34: change in delivery planning | V34: commande non planifier
A35: VOY2026COFTN34 | B35: =+IFERROR(VLOOKUP(A35,'Details local delivery'!B:C,2,0),"-") -> 46029 | C35: =B35 -> 46029 | D35: =+IFERROR(VLOOKUP(A35,'Details local delivery'!B:E,4,0),"-") -> 4331tu175 | E35: =VLOOKUP(A35,'Details local delivery'!B:L,11,0) -> 14 | F35: =SUMIFS('Details local delivery'!M:M,'Details local delivery'!G:G,'RECAP Delivery Plan '!A35) -> 11 | G35: =VLOOKUP(A35,'Details local delivery'!B:J,9,0) -> 9200 | H35: =SUMIFS('Details local delivery'!K:K,'Details local delivery'!G:G,'RECAP Delivery Plan '!A35) -> 6000 | I35: =SUMIFS('Details local delivery'!Y:Y,'Details local delivery'!B:B,A:A) -> 0 | J35: =AVERAGEIFS('Details local delivery'!W:W,'Details local delivery'!B:B,A35) -> 1 | K35: =_xlfn.MAXIFS('Details local delivery'!Z:Z,'Details local delivery'!B:B,A35) -> 0 | L35: =_xlfn.MAXIFS('Details local delivery'!AA:AA,'Details local delivery'!B:B,A35) -> 0 | M35: =_xlfn.MAXIFS('Details local delivery'!AB:AB,'Details local delivery'!B:B,A35) -> 0 | N35: =+F35/E35 -> 0.78571429 | O35: =+H35/G35 -> 0.65217391 | P35: =K35+L35+M35 -> 0 | Q35: =P35+I35 -> 0 | R35: =Q35/P35 -> #DIV/0! | S35: =MAX(N35,O35) -> 0.78571429 | U35: change in delivery planning | V35: commande non planifier
A36: VOY2026COFTN35 | B36: =+IFERROR(VLOOKUP(A36,'Details local delivery'!B:C,2,0),"-") -> 46029 | C36: =B36 -> 46029 | D36: =+IFERROR(VLOOKUP(A36,'Details local delivery'!B:E,4,0),"-") -> 2282tu131 | E36: =VLOOKUP(A36,'Details local delivery'!B:L,11,0) -> 14 | F36: =SUMIFS('Details local delivery'!M:M,'Details local delivery'!G:G,'RECAP Delivery Plan '!A36) -> 10 | G36: =VLOOKUP(A36,'Details local delivery'!B:J,9,0) -> 10200 | H36: =SUMIFS('Details local delivery'!K:K,'Details local delivery'!G:G,'RECAP Delivery Plan '!A36) -> 10000 | I36: =SUMIFS('Details local delivery'!Y:Y,'Details local delivery'!B:B,A:A) -> 0 | J36: =AVERAGEIFS('Details local delivery'!W:W,'Details local delivery'!B:B,A36) -> 1 | K36: =_xlfn.MAXIFS('Details local delivery'!Z:Z,'Details local delivery'!B:B,A36) -> 0 | L36: =_xlfn.MAXIFS('Details local delivery'!AA:AA,'Details local delivery'!B:B,A36) -> 0 | M36: =IFERROR(_xlfn.MAXIFS('Details local delivery'!AB:AB,'Details local delivery'!B:B,A36),"-") -> 0 | N36: =+F36/E36 -> 0.71428571 | O36: =+H36/G36 -> 0.98039216 | P36: =K36+L36+M36 -> 0 | Q36: =P36+I36 -> 0 | R36: =Q36/P36 -> #DIV/0! | S36: =MAX(N36,O36) -> 0.98039216
A37: VOY2026COFTN36 | B37: =+IFERROR(VLOOKUP(A37,'Details local delivery'!B:C,2,0),"-") -> 46029 | C37: =B37 -> 46029 | D37: =+IFERROR(VLOOKUP(A37,'Details local delivery'!B:E,4,0),"-") -> 2282tu131 | E37: =VLOOKUP(A37,'Details local delivery'!B:L,11,0) -> 14 | F37: =SUMIFS('Details local delivery'!M:M,'Details local delivery'!G:G,'RECAP Delivery Plan '!A37) -> 8 | G37: =VLOOKUP(A37,'Details local delivery'!B:J,9,0) -> 10200 | H37: =SUMIFS('Details local delivery'!K:K,'Details local delivery'!G:G,'RECAP Delivery Plan '!A37) -> 7300 | I37: =SUMIFS('Details local delivery'!Y:Y,'Details local delivery'!B:B,A:A) -> 0 | J37: =AVERAGEIFS('Details local delivery'!W:W,'Details local delivery'!B:B,A37) -> 0.875 | K37: =_xlfn.MAXIFS('Details local delivery'!Z:Z,'Details local delivery'!B:B,A37) -> 0 | L37: =_xlfn.MAXIFS('Details local delivery'!AA:AA,'Details local delivery'!B:B,A37) -> 0 | M37: =IFERROR(_xlfn.MAXIFS('Details local delivery'!AB:AB,'Details local delivery'!B:B,A37),"-") -> 0 | N37: =+F37/E37 -> 0.57142857 | O37: =+H37/G37 -> 0.71568627 | P37: =K37+L37+M37 -> 0 | Q37: =P37+I37 -> 0 | R37: =Q37/P37 -> #DIV/0! | S37: =MAX(N37,O37) -> 0.71568627
A38: VOY2026COFTN37 | B38: =+IFERROR(VLOOKUP(A38,'Details local delivery'!B:C,2,0),"-") -> 46029 | C38: =B38 -> 46029 | D38: =+IFERROR(VLOOKUP(A38,'Details local delivery'!B:E,4,0),"-") -> 5735tu217 | E38: =VLOOKUP(A38,'Details local delivery'!B:L,11,0) -> 14 | F38: =SUMIFS('Details local delivery'!M:M,'Details local delivery'!G:G,'RECAP Delivery Plan '!A38) -> 10 | G38: =VLOOKUP(A38,'Details local delivery'!B:J,9,0) -> 10200 | H38: =SUMIFS('Details local delivery'!K:K,'Details local delivery'!G:G,'RECAP Delivery Plan '!A38) -> 7100 | I38: =SUMIFS('Details local delivery'!Y:Y,'Details local delivery'!B:B,A:A) -> 0 | J38: =AVERAGEIFS('Details local delivery'!W:W,'Details local delivery'!B:B,A38) -> 1 | K38: =_xlfn.MAXIFS('Details local delivery'!Z:Z,'Details local delivery'!B:B,A38) -> 0 | L38: =_xlfn.MAXIFS('Details local delivery'!AA:AA,'Details local delivery'!B:B,A38) -> 0 | M38: =IFERROR(_xlfn.MAXIFS('Details local delivery'!AB:AB,'Details local delivery'!B:B,A38),"-") -> 0 | N38: =+F38/E38 -> 0.71428571 | O38: =+H38/G38 -> 0.69607843 | P38: =K38+L38+M38 -> 0 | Q38: =P38+I38 -> 0 | R38: =Q38/P38 -> #DIV/0! | S38: =MAX(N38,O38) -> 0.71428571
A39: VOY2026COFTN38 | B39: =+IFERROR(VLOOKUP(A39,'Details local delivery'!B:C,2,0),"-") -> 46029 | C39: =B39 -> 46029 | D39: =+IFERROR(VLOOKUP(A39,'Details local delivery'!B:E,4,0),"-") -> REM107627 | E39: =VLOOKUP(A39,'Details local delivery'!B:L,11,0) -> 27 | F39: =SUMIFS('Details local delivery'!M:M,'Details local delivery'!G:G,'RECAP Delivery Plan '!A39) -> 27 | G39: =VLOOKUP(A39,'Details local delivery'!B:J,9,0) -> 24950 | H39: =SUMIFS('Details local delivery'!K:K,'Details local delivery'!G:G,'RECAP Delivery Plan '!A39) -> 14000 | I39: =SUMIFS('Details local delivery'!Y:Y,'Details local delivery'!B:B,A:A) -> 0 | J39: =AVERAGEIFS('Details local delivery'!W:W,'Details local delivery'!B:B,A39) -> 1 | K39: =_xlfn.MAXIFS('Details local delivery'!Z:Z,'Details local delivery'!B:B,A39) -> 0 | L39: =_xlfn.MAXIFS('Details local delivery'!AA:AA,'Details local delivery'!B:B,A39) -> 0 | M39: =_xlfn.MAXIFS('Details local delivery'!AB:AB,'Details local delivery'!B:B,A39) -> 0 | N39: =+F39/E39 -> 1 | O39: =+H39/G39 -> 0.56112224 | P39: =K39+L39+M39 -> 0 | Q39: =P39+I39 -> 0 | R39: =Q39/P39 -> #DIV/0! | S39: =MAX(N39,O39) -> 1
A40: VOY2026COFTN39 | B40: =+IFERROR(VLOOKUP(A40,'Details local delivery'!B:C,2,0),"-") -> 46029 | C40: =B40 -> 46029 | D40: =+IFERROR(VLOOKUP(A40,'Details local delivery'!B:E,4,0),"-") -> 7797tu218 | E40: =VLOOKUP(A40,'Details local delivery'!B:L,11,0) -> 3 | F40: =SUMIFS('Details local delivery'!M:M,'Details local delivery'!G:G,'RECAP Delivery Plan '!A40) -> 3 | G40: =VLOOKUP(A40,'Details local delivery'!B:J,9,0) -> 927 | H40: =SUMIFS('Details local delivery'!K:K,'Details local delivery'!G:G,'RECAP Delivery Plan '!A40) -> 500 | I40: =SUMIFS('Details local delivery'!Y:Y,'Details local delivery'!B:B,A:A) -> 0 | J40: =AVERAGEIFS('Details local delivery'!W:W,'Details local delivery'!B:B,A40) -> 1 | K40: =_xlfn.MAXIFS('Details local delivery'!Z:Z,'Details local delivery'!B:B,A40) -> 0 | L40: =_xlfn.MAXIFS('Details local delivery'!AA:AA,'Details local delivery'!B:B,A40) -> 0 | M40: =IFERROR(_xlfn.MAXIFS('Details local delivery'!AB:AB,'Details local delivery'!B:B,A40),"-") -> 0 | N40: =+F40/E40 -> 1 | O40: =+H40/G40 -> 0.53937433 | P40: =K40+L40+M40 -> 0 | Q40: =P40+I40 -> 0 | R40: =Q40/P40 -> #DIV/0! | S40: =MAX(N40,O40) -> 1
A41: VOY2026COFTN40 | B41: =+IFERROR(VLOOKUP(A41,'Details local delivery'!B:C,2,0),"-") -> 46029 | C41: =B41 -> 46029 | D41: =+IFERROR(VLOOKUP(A41,'Details local delivery'!B:E,4,0),"-") -> 7797tu218 | E41: =VLOOKUP(A41,'Details local delivery'!B:L,11,0) -> 3 | F41: =SUMIFS('Details local delivery'!M:M,'Details local delivery'!G:G,'RECAP Delivery Plan '!A41) -> 2 | G41: =VLOOKUP(A41,'Details local delivery'!B:J,9,0) -> 927 | H41: =SUMIFS('Details local delivery'!K:K,'Details local delivery'!G:G,'RECAP Delivery Plan '!A41) -> 500 | I41: =SUMIFS('Details local delivery'!Y:Y,'Details local delivery'!B:B,A:A) -> 0 | J41: =AVERAGEIFS('Details local delivery'!W:W,'Details local delivery'!B:B,A41) -> 1 | K41: =_xlfn.MAXIFS('Details local delivery'!Z:Z,'Details local delivery'!B:B,A41) -> 0 | L41: =_xlfn.MAXIFS('Details local delivery'!AA:AA,'Details local delivery'!B:B,A41) -> 0 | M41: =_xlfn.MAXIFS('Details local delivery'!AB:AB,'Details local delivery'!B:B,A41) -> 0 | N41: =+F41/E41 -> 0.66666667 | O41: =+H41/G41 -> 0.53937433 | P41: =K41+L41+M41 -> 0 | Q41: =P41+I41 -> 0 | R41: =Q41/P41 -> #DIV/0! | S41: =MAX(N41,O41) -> 0.66666667
A42: VOY2026COFTN41 | B42: =+IFERROR(VLOOKUP(A42,'Details local delivery'!B:C,2,0),"-") -> 46029 | C42: =B42 -> 46029 | D42: =+IFERROR(VLOOKUP(A42,'Details local delivery'!B:E,4,0),"-") -> 7797tu218 | E42: =VLOOKUP(A42,'Details local delivery'!B:L,11,0) -> 3 | F42: =SUMIFS('Details local delivery'!M:M,'Details local delivery'!G:G,'RECAP Delivery Plan '!A42) -> 1 | G42: =VLOOKUP(A42,'Details local delivery'!B:J,9,0) -> 927 | H42: =SUMIFS('Details local delivery'!K:K,'Details local delivery'!G:G,'RECAP Delivery Plan '!A42) -> 500 | I42: =SUMIFS('Details local delivery'!Y:Y,'Details local delivery'!B:B,A:A) -> 0 | J42: =AVERAGEIFS('Details local delivery'!W:W,'Details local delivery'!B:B,A42) -> 0.92083333 | K42: =_xlfn.MAXIFS('Details local delivery'!Z:Z,'Details local delivery'!B:B,A42) -> 0 | L42: =_xlfn.MAXIFS('Details local delivery'!AA:AA,'Details local delivery'!B:B,A42) -> 0 | M42: =_xlfn.MAXIFS('Details local delivery'!AB:AB,'Details local delivery'!B:B,A42) -> 0 | N42: =+F42/E42 -> 0.33333333 | O42: =+H42/G42 -> 0.53937433 | P42: =K42+L42+M42 -> 0 | Q42: =P42+I42 -> 0 | R42: =Q42/P42 -> #DIV/0! | S42: =MAX(N42,O42) -> 0.53937433
A43: VOY2026COFTN42 | B43: =+IFERROR(VLOOKUP(A43,'Details local delivery'!B:C,2,0),"-") -> 46029 | C43: =B43 -> 46029 | D43: =+IFERROR(VLOOKUP(A43,'Details local delivery'!B:E,4,0),"-") -> 7797tu218 | E43: =VLOOKUP(A43,'Details local delivery'!B:L,11,0) -> 3 | F43: =SUMIFS('Details local delivery'!M:M,'Details local delivery'!G:G,'RECAP Delivery Plan '!A43) -> 1 | G43: =VLOOKUP(A43,'Details local delivery'!B:J,9,0) -> 927 | H43: =SUMIFS('Details local delivery'!K:K,'Details local delivery'!G:G,'RECAP Delivery Plan '!A43) -> 500 | I43: =SUMIFS('Details local delivery'!Y:Y,'Details local delivery'!B:B,A:A) -> 0 | J43: =AVERAGEIFS('Details local delivery'!W:W,'Details local delivery'!B:B,A43) -> 1 | K43: =_xlfn.MAXIFS('Details local delivery'!Z:Z,'Details local delivery'!B:B,A43) -> 0 | L43: =_xlfn.MAXIFS('Details local delivery'!AA:AA,'Details local delivery'!B:B,A43) -> 0 | M43: =_xlfn.MAXIFS('Details local delivery'!AB:AB,'Details local delivery'!B:B,A43) -> 0 | N43: =+F43/E43 -> 0.33333333 | O43: =+H43/G43 -> 0.53937433 | P43: =K43+L43+M43 -> 0 | Q43: =P43+I43 -> 0 | R43: =Q43/P43 -> #DIV/0! | S43: =MAX(N43,O43) -> 0.53937433
A44: VOY2026COFTN43 | B44: =+IFERROR(VLOOKUP(A44,'Details local delivery'!B:C,2,0),"-") -> 46029 | C44: =B44 -> 46029 | D44: =+IFERROR(VLOOKUP(A44,'Details local delivery'!B:E,4,0),"-") -> Location | E44: =VLOOKUP(A44,'Details local delivery'!B:L,11,0) -> 0 | F44: =SUMIFS('Details local delivery'!M:M,'Details local delivery'!G:G,'RECAP Delivery Plan '!A44) -> 5 | G44: =VLOOKUP(A44,'Details local delivery'!B:J,9,0) -> 0 | H44: =SUMIFS('Details local delivery'!K:K,'Details local delivery'!G:G,'RECAP Delivery Plan '!A44) -> 0 | I44: =SUMIFS('Details local delivery'!Y:Y,'Details local delivery'!B:B,A:A) -> 0 | J44: =AVERAGEIFS('Details local delivery'!W:W,'Details local delivery'!B:B,A44) -> 1 | K44: =_xlfn.MAXIFS('Details local delivery'!Z:Z,'Details local delivery'!B:B,A44) -> 0 | L44: =_xlfn.MAXIFS('Details local delivery'!AA:AA,'Details local delivery'!B:B,A44) -> 0 | M44: =_xlfn.MAXIFS('Details local delivery'!AB:AB,'Details local delivery'!B:B,A44) -> 0 | N44: =+F44/E44 -> #DIV/0! | O44: =+H44/G44 -> #DIV/0! | P44: =K44+L44+M44 -> 0 | Q44: =P44+I44 -> 0 | R44: =Q44/P44 -> #DIV/0! | S44: =MAX(N44,O44) -> #DIV/0!
A45: VOY2026COFTN44 | B45: =+IFERROR(VLOOKUP(A45,'Details local delivery'!B:C,2,0),"-") -> 46029 | C45: =B45 -> 46029 | D45: =+IFERROR(VLOOKUP(A45,'Details local delivery'!B:E,4,0),"-") -> 5735tu217 | E45: =VLOOKUP(A45,'Details local delivery'!B:L,11,0) -> 14 | F45: =SUMIFS('Details local delivery'!M:M,'Details local delivery'!G:G,'RECAP Delivery Plan '!A45) -> 5 | G45: =VLOOKUP(A45,'Details local delivery'!B:J,9,0) -> 10200 | H45: =SUMIFS('Details local delivery'!K:K,'Details local delivery'!G:G,'RECAP Delivery Plan '!A45) -> 7100 | I45: =SUMIFS('Details local delivery'!Y:Y,'Details local delivery'!B:B,A:A) -> 0 | J45: =AVERAGEIFS('Details local delivery'!W:W,'Details local delivery'!B:B,A45) -> #DIV/0! | K45: =_xlfn.MAXIFS('Details local delivery'!Z:Z,'Details local delivery'!B:B,A45) -> 0 | L45: =_xlfn.MAXIFS('Details local delivery'!AA:AA,'Details local delivery'!B:B,A45) -> 0 | M45: =IFERROR(_xlfn.MAXIFS('Details local delivery'!AB:AB,'Details local delivery'!B:B,A45),"-") -> 0 | N45: =+F45/E45 -> 0.35714286 | O45: =+H45/G45 -> 0.69607843 | P45: =K45+L45+M45 -> 0 | Q45: =P45+I45 -> 0 | R45: =Q45/P45 -> #DIV/0! | S45: =MAX(N45,O45) -> 0.69607843
A46: VOY2026COFTN45 | B46: =+IFERROR(VLOOKUP(A46,'Details local delivery'!B:C,2,0),"-") -> 46029 | C46: =B46 -> 46029 | D46: =+IFERROR(VLOOKUP(A46,'Details local delivery'!B:E,4,0),"-") -> 2282tu131 | E46: =VLOOKUP(A46,'Details local delivery'!B:L,11,0) -> 14 | F46: =SUMIFS('Details local delivery'!M:M,'Details local delivery'!G:G,'RECAP Delivery Plan '!A46) -> 15 | G46: =VLOOKUP(A46,'Details local delivery'!B:J,9,0) -> 10200 | H46: =SUMIFS('Details local delivery'!K:K,'Details local delivery'!G:G,'RECAP Delivery Plan '!A46) -> 6900 | I46: =SUMIFS('Details local delivery'!Y:Y,'Details local delivery'!B:B,A:A) -> 0 | J46: =AVERAGEIFS('Details local delivery'!W:W,'Details local delivery'!B:B,A46) -> 0.95416667 | K46: =_xlfn.MAXIFS('Details local delivery'!Z:Z,'Details local delivery'!B:B,A46) -> 0 | L46: =_xlfn.MAXIFS('Details local delivery'!AA:AA,'Details local delivery'!B:B,A46) -> 0 | M46: =_xlfn.MAXIFS('Details local delivery'!AB:AB,'Details local delivery'!B:B,A46) -> 0 | N46: =+F46/E46 -> 1.0714286 | O46: =+H46/G46 -> 0.67647059 | P46: =K46+L46+M46 -> 0 | Q46: =P46+I46 -> 0 | R46: =Q46/P46 -> #DIV/0! | S46: =MAX(N46,O46) -> 1.0714286
A47: VOY2026COFTN46 | B47: =+IFERROR(VLOOKUP(A47,'Details local delivery'!B:C,2,0),"-") -> 46030 | C47: =B47 -> 46030 | D47: =+IFERROR(VLOOKUP(A47,'Details local delivery'!B:E,4,0),"-") -> 7797tu218 | E47: =VLOOKUP(A47,'Details local delivery'!B:L,11,0) -> 3 | F47: =SUMIFS('Details local delivery'!M:M,'Details local delivery'!G:G,'RECAP Delivery Plan '!A47) -> 1 | G47: =VLOOKUP(A47,'Details local delivery'!B:J,9,0) -> 927 | H47: =SUMIFS('Details local delivery'!K:K,'Details local delivery'!G:G,'RECAP Delivery Plan '!A47) -> 1000 | I47: =SUMIFS('Details local delivery'!Y:Y,'Details local delivery'!B:B,A:A) -> 0 | J47: =AVERAGEIFS('Details local delivery'!W:W,'Details local delivery'!B:B,A47) -> 1 | K47: =_xlfn.MAXIFS('Details local delivery'!Z:Z,'Details local delivery'!B:B,A47) -> 0 | L47: =_xlfn.MAXIFS('Details local delivery'!AA:AA,'Details local delivery'!B:B,A47) -> 0 | M47: =_xlfn.MAXIFS('Details local delivery'!AB:AB,'Details local delivery'!B:B,A47) -> 0 | N47: =+F47/E47 -> 0.33333333 | O47: =+H47/G47 -> 1.0787487 | P47: =K47+L47+M47 -> 0 | Q47: =P47+I47 -> 0 | R47: =Q47/P47 -> #DIV/0! | S47: =MAX(N47,O47) -> 1.0787487
A48: VOY2026COFTN47 | B48: =+IFERROR(VLOOKUP(A48,'Details local delivery'!B:C,2,0),"-") -> 46030 | C48: =B48 -> 46030 | D48: =+IFERROR(VLOOKUP(A48,'Details local delivery'!B:E,4,0),"-") -> 7797tu218 | E48: =VLOOKUP(A48,'Details local delivery'!B:L,11,0) -> 3 | F48: =SUMIFS('Details local delivery'!M:M,'Details local delivery'!G:G,'RECAP Delivery Plan '!A48) -> 3 | G48: =VLOOKUP(A48,'Details local delivery'!B:J,9,0) -> 927 | H48: =SUMIFS('Details local delivery'!K:K,'Details local delivery'!G:G,'RECAP Delivery Plan '!A48) -> 1000 | I48: =SUMIFS('Details local delivery'!Y:Y,'Details local delivery'!B:B,A:A) -> 0 | J48: =AVERAGEIFS('Details local delivery'!W:W,'Details local delivery'!B:B,A48) -> 1 | K48: =_xlfn.MAXIFS('Details local delivery'!Z:Z,'Details local delivery'!B:B,A48) -> 0 | L48: =_xlfn.MAXIFS('Details local delivery'!AA:AA,'Details local delivery'!B:B,A48) -> 0 | M48: =IFERROR(_xlfn.MAXIFS('Details local delivery'!AB:AB,'Details local delivery'!B:B,A48),"-") -> 0 | N48: =+F48/E48 -> 1 | O48: =+H48/G48 -> 1.0787487 | P48: =K48+L48+M48 -> 0 | Q48: =P48+I48 -> 0 | R48: =Q48/P48 -> #DIV/0! | S48: =MAX(N48,O48) -> 1.0787487
A49: VOY2026COFTN48 | B49: =+IFERROR(VLOOKUP(A49,'Details local delivery'!B:C,2,0),"-") -> 46030 | C49: =B49 -> 46030 | D49: =+IFERROR(VLOOKUP(A49,'Details local delivery'!B:E,4,0),"-") -> 7797tu218 | E49: =VLOOKUP(A49,'Details local delivery'!B:L,11,0) -> 3 | F49: =SUMIFS('Details local delivery'!M:M,'Details local delivery'!G:G,'RECAP Delivery Plan '!A49) -> 2 | G49: =VLOOKUP(A49,'Details local delivery'!B:J,9,0) -> 927 | H49: =SUMIFS('Details local delivery'!K:K,'Details local delivery'!G:G,'RECAP Delivery Plan '!A49) -> 1000 | I49: =SUMIFS('Details local delivery'!Y:Y,'Details local delivery'!B:B,A:A) -> 0 | J49: =AVERAGEIFS('Details local delivery'!W:W,'Details local delivery'!B:B,A49) -> 1 | K49: =_xlfn.MAXIFS('Details local delivery'!Z:Z,'Details local delivery'!B:B,A49) -> 0 | L49: =_xlfn.MAXIFS('Details local delivery'!AA:AA,'Details local delivery'!B:B,A49) -> 0 | M49: =IFERROR(_xlfn.MAXIFS('Details local delivery'!AB:AB,'Details local delivery'!B:B,A49),"-") -> 0 | N49: =+F49/E49 -> 0.66666667 | O49: =+H49/G49 -> 1.0787487 | P49: =K49+L49+M49 -> 0 | Q49: =P49+I49 -> 0 | R49: =Q49/P49 -> #DIV/0! | S49: =MAX(N49,O49) -> 1.0787487
A50: VOY2026COFTN49 | B50: =+IFERROR(VLOOKUP(A50,'Details local delivery'!B:C,2,0),"-") -> 46030 | C50: =B50 -> 46030 | D50: =+IFERROR(VLOOKUP(A50,'Details local delivery'!B:E,4,0),"-") -> 5735tu217 | E50: =VLOOKUP(A50,'Details local delivery'!B:L,11,0) -> 14 | F50: =SUMIFS('Details local delivery'!M:M,'Details local delivery'!G:G,'RECAP Delivery Plan '!A50) -> 13 | G50: =VLOOKUP(A50,'Details local delivery'!B:J,9,0) -> 10200 | H50: =SUMIFS('Details local delivery'!K:K,'Details local delivery'!G:G,'RECAP Delivery Plan '!A50) -> 10000 | I50: =SUMIFS('Details local delivery'!Y:Y,'Details local delivery'!B:B,A:A) -> 0 | J50: =AVERAGEIFS('Details local delivery'!W:W,'Details local delivery'!B:B,A50) -> 1 | K50: =_xlfn.MAXIFS('Details local delivery'!Z:Z,'Details local delivery'!B:B,A50) -> 0 | L50: =_xlfn.MAXIFS('Details local delivery'!AA:AA,'Details local delivery'!B:B,A50) -> 0 | M50: =IFERROR(_xlfn.MAXIFS('Details local delivery'!AB:AB,'Details local delivery'!B:B,A50),"-") -> 0 | N50: =+F50/E50 -> 0.92857143 | O50: =+H50/G50 -> 0.98039216 | P50: =K50+L50+M50 -> 0 | Q50: =P50+I50 -> 0 | R50: =Q50/P50 -> #DIV/0! | S50: =MAX(N50,O50) -> 0.98039216
A51: VOY2026COFTN50 | B51: =+IFERROR(VLOOKUP(A51,'Details local delivery'!B:C,2,0),"-") -> 46030 | C51: =B51 -> 46030 | D51: =+IFERROR(VLOOKUP(A51,'Details local delivery'!B:E,4,0),"-") -> 5735tu217 | E51: =VLOOKUP(A51,'Details local delivery'!B:L,11,0) -> 14 | F51: =SUMIFS('Details local delivery'!M:M,'Details local delivery'!G:G,'RECAP Delivery Plan '!A51) -> 14 | G51: =VLOOKUP(A51,'Details local delivery'!B:J,9,0) -> 10200 | H51: =SUMIFS('Details local delivery'!K:K,'Details local delivery'!G:G,'RECAP Delivery Plan '!A51) -> 11000 | I51: =SUMIFS('Details local delivery'!Y:Y,'Details local delivery'!B:B,A:A) -> 0 | J51: =AVERAGEIFS('Details local delivery'!W:W,'Details local delivery'!B:B,A51) -> 1 | K51: =_xlfn.MAXIFS('Details local delivery'!Z:Z,'Details local delivery'!B:B,A51) -> 0 | L51: =_xlfn.MAXIFS('Details local delivery'!AA:AA,'Details local delivery'!B:B,A51) -> 0 | M51: =IFERROR(_xlfn.MAXIFS('Details local delivery'!AB:AB,'Details local delivery'!B:B,A51),"-") -> 0 | N51: =+F51/E51 -> 1 | O51: =+H51/G51 -> 1.0784314 | P51: =K51+L51+M51 -> 0 | Q51: =P51+I51 -> 0 | R51: =Q51/P51 -> #DIV/0! | S51: =MAX(N51,O51) -> 1.0784314
A52: VOY2026COFTN51 | B52: =+IFERROR(VLOOKUP(A52,'Details local delivery'!B:C,2,0),"-") -> 46030 | C52: =B52 -> 46030 | D52: =+IFERROR(VLOOKUP(A52,'Details local delivery'!B:E,4,0),"-") -> 9524TU238 | E52: =VLOOKUP(A52,'Details local delivery'!B:L,11,0) -> 14 | F52: =SUMIFS('Details local delivery'!M:M,'Details local delivery'!G:G,'RECAP Delivery Plan '!A52) -> 4 | G52: =VLOOKUP(A52,'Details local delivery'!B:J,9,0) -> 10230 | H52: =SUMIFS('Details local delivery'!K:K,'Details local delivery'!G:G,'RECAP Delivery Plan '!A52) -> 11100 | I52: =SUMIFS('Details local delivery'!Y:Y,'Details local delivery'!B:B,A:A) -> 0 | J52: =AVERAGEIFS('Details local delivery'!W:W,'Details local delivery'!B:B,A52) -> 1 | K52: =_xlfn.MAXIFS('Details local delivery'!Z:Z,'Details local delivery'!B:B,A52) -> 0 | L52: =_xlfn.MAXIFS('Details local delivery'!AA:AA,'Details local delivery'!B:B,A52) -> 0 | M52: =IFERROR(_xlfn.MAXIFS('Details local delivery'!AB:AB,'Details local delivery'!B:B,A52),"-") -> 0 | N52: =+F52/E52 -> 0.28571429 | O52: =+H52/G52 -> 1.085044 | P52: =K52+L52+M52 -> 0 | Q52: =P52+I52 -> 0 | R52: =Q52/P52 -> #DIV/0! | S52: =MAX(N52,O52) -> 1.085044
A53: VOY2026COFTN52 | B53: =+IFERROR(VLOOKUP(A53,'Details local delivery'!B:C,2,0),"-") -> 46030 | C53: =B53 -> 46030 | D53: =+IFERROR(VLOOKUP(A53,'Details local delivery'!B:E,4,0),"-") -> 9524TU238 | E53: =VLOOKUP(A53,'Details local delivery'!B:L,11,0) -> 14 | F53: =SUMIFS('Details local delivery'!M:M,'Details local delivery'!G:G,'RECAP Delivery Plan '!A53) -> 26 | G53: =VLOOKUP(A53,'Details local delivery'!B:J,9,0) -> 10230 | H53: =SUMIFS('Details local delivery'!K:K,'Details local delivery'!G:G,'RECAP Delivery Plan '!A53) -> 19638 | I53: =SUMIFS('Details local delivery'!Y:Y,'Details local delivery'!B:B,A:A) -> 0 | J53: =AVERAGEIFS('Details local delivery'!W:W,'Details local delivery'!B:B,A53) -> 1 | K53: =_xlfn.MAXIFS('Details local delivery'!Z:Z,'Details local delivery'!B:B,A53) -> 0 | L53: =_xlfn.MAXIFS('Details local delivery'!AA:AA,'Details local delivery'!B:B,A53) -> 0 | M53: =IFERROR(_xlfn.MAXIFS('Details local delivery'!AB:AB,'Details local delivery'!B:B,A53),"-") -> 0 | N53: =+F53/E53 -> 1.8571429 | O53: =+H53/G53 -> 1.9196481 | P53: =K53+L53+M53 -> 0 | Q53: =P53+I53 -> 0 | R53: =Q53/P53 -> #DIV/0! | S53: =MAX(N53,O53) -> 1.9196481
A54: VOY2026COFTN53 | B54: =+IFERROR(VLOOKUP(A54,'Details local delivery'!B:C,2,0),"-") -> 46030 | C54: =B54 -> 46030 | D54: =+IFERROR(VLOOKUP(A54,'Details local delivery'!B:E,4,0),"-") -> 4331tu175 | E54: =VLOOKUP(A54,'Details local delivery'!B:L,11,0) -> 14 | F54: =SUMIFS('Details local delivery'!M:M,'Details local delivery'!G:G,'RECAP Delivery Plan '!A54) -> 6 | G54: =VLOOKUP(A54,'Details local delivery'!B:J,9,0) -> 9200 | H54: =SUMIFS('Details local delivery'!K:K,'Details local delivery'!G:G,'RECAP Delivery Plan '!A54) -> 177 | I54: =SUMIFS('Details local delivery'!Y:Y,'Details local delivery'!B:B,A:A) -> 0 | J54: =AVERAGEIFS('Details local delivery'!W:W,'Details local delivery'!B:B,A54) -> 1 | K54: =_xlfn.MAXIFS('Details local delivery'!Z:Z,'Details local delivery'!B:B,A54) -> 0 | L54: =_xlfn.MAXIFS('Details local delivery'!AA:AA,'Details local delivery'!B:B,A54) -> 0 | M54: =_xlfn.MAXIFS('Details local delivery'!AB:AB,'Details local delivery'!B:B,A54) -> 0 | N54: =+F54/E54 -> 0.42857143 | O54: =+H54/G54 -> 0.01923913 | P54: =K54+L54+M54 -> 0 | Q54: =P54+I54 -> 0 | R54: =Q54/P54 -> #DIV/0! | S54: =MAX(N54,O54) -> 0.42857143
A55: VOY2026COFTN54 | B55: =+IFERROR(VLOOKUP(A55,'Details local delivery'!B:C,2,0),"-") -> 46030 | C55: =B55 -> 46030 | D55: =+IFERROR(VLOOKUP(A55,'Details local delivery'!B:E,4,0),"-") -> 4331tu175 | E55: =VLOOKUP(A55,'Details local delivery'!B:L,11,0) -> 14 | F55: =SUMIFS('Details local delivery'!M:M,'Details local delivery'!G:G,'RECAP Delivery Plan '!A55) -> 13 | G55: =VLOOKUP(A55,'Details local delivery'!B:J,9,0) -> 9200 | H55: =SUMIFS('Details local delivery'!K:K,'Details local delivery'!G:G,'RECAP Delivery Plan '!A55) -> 4600 | I55: =SUMIFS('Details local delivery'!Y:Y,'Details local delivery'!B:B,A:A) -> 0 | J55: =AVERAGEIFS('Details local delivery'!W:W,'Details local delivery'!B:B,A55) -> 1 | K55: =_xlfn.MAXIFS('Details local delivery'!Z:Z,'Details local delivery'!B:B,A55) -> 0 | L55: =_xlfn.MAXIFS('Details local delivery'!AA:AA,'Details local delivery'!B:B,A55) -> 0 | M55: =_xlfn.MAXIFS('Details local delivery'!AB:AB,'Details local delivery'!B:B,A55) -> 0 | N55: =+F55/E55 -> 0.92857143 | O55: =+H55/G55 -> 0.5 | P55: =K55+L55+M55 -> 0 | Q55: =P55+I55 -> 0 | R55: =Q55/P55 -> #DIV/0! | S55: =MAX(N55,O55) -> 0.92857143
A56: VOY2026COFTN55 | B56: =+IFERROR(VLOOKUP(A56,'Details local delivery'!B:C,2,0),"-") -> 46030 | C56: =B56 -> 46030 | D56: =+IFERROR(VLOOKUP(A56,'Details local delivery'!B:E,4,0),"-") -> REM107627 | E56: =VLOOKUP(A56,'Details local delivery'!B:L,11,0) -> 27 | F56: =SUMIFS('Details local delivery'!M:M,'Details local delivery'!G:G,'RECAP Delivery Plan '!A56) -> 17 | G56: =VLOOKUP(A56,'Details local delivery'!B:J,9,0) -> 24950 | H56: =SUMIFS('Details local delivery'!K:K,'Details local delivery'!G:G,'RECAP Delivery Plan '!A56) -> 15900 | I56: =SUMIFS('Details local delivery'!Y:Y,'Details local delivery'!B:B,A:A) -> 0 | J56: =AVERAGEIFS('Details local delivery'!W:W,'Details local delivery'!B:B,A56) -> 1 | K56: =_xlfn.MAXIFS('Details local delivery'!Z:Z,'Details local delivery'!B:B,A56) -> 0 | L56: =_xlfn.MAXIFS('Details local delivery'!AA:AA,'Details local delivery'!B:B,A56) -> 0 | M56: =_xlfn.MAXIFS('Details local delivery'!AB:AB,'Details local delivery'!B:B,A56) -> 0 | N56: =+F56/E56 -> 0.62962963 | O56: =+H56/G56 -> 0.63727455 | P56: =K56+L56+M56 -> 0 | Q56: =P56+I56 -> 0 | R56: =Q56/P56 -> #DIV/0! | S56: =MAX(N56,O56) -> 0.63727455
A57: VOY2026COFTN56 | B57: =+IFERROR(VLOOKUP(A57,'Details local delivery'!B:C,2,0),"-") -> 46030 | C57: =B57 -> 46030 | D57: =+IFERROR(VLOOKUP(A57,'Details local delivery'!B:E,4,0),"-") -> 626tu203 | E57: =VLOOKUP(A57,'Details local delivery'!B:L,11,0) -> 14 | F57: =SUMIFS('Details local delivery'!M:M,'Details local delivery'!G:G,'RECAP Delivery Plan '!A57) -> 8 | G57: =VLOOKUP(A57,'Details local delivery'!B:J,9,0) -> 8500 | H57: =SUMIFS('Details local delivery'!K:K,'Details local delivery'!G:G,'RECAP Delivery Plan '!A57) -> 6000 | I57: =SUMIFS('Details local delivery'!Y:Y,'Details local delivery'!B:B,A:A) -> 0 | J57: =AVERAGEIFS('Details local delivery'!W:W,'Details local delivery'!B:B,A57) -> 1 | K57: =_xlfn.MAXIFS('Details local delivery'!Z:Z,'Details local delivery'!B:B,A57) -> 0 | L57: =_xlfn.MAXIFS('Details local delivery'!AA:AA,'Details local delivery'!B:B,A57) -> 0 | M57: =IFERROR(_xlfn.MAXIFS('Details local delivery'!AB:AB,'Details local delivery'!B:B,A57),"-") -> 0 | N57: =+F57/E57 -> 0.57142857 | O57: =+H57/G57 -> 0.70588235 | P57: =K57+L57+M57 -> 0 | Q57: =P57+I57 -> 0 | R57: =Q57/P57 -> #DIV/0! | S57: =MAX(N57,O57) -> 0.70588235
A58: VOY2026COFTN57 | B58: =+IFERROR(VLOOKUP(A58,'Details local delivery'!B:C,2,0),"-") -> 46030 | C58: =B58 -> 46030 | D58: =+IFERROR(VLOOKUP(A58,'Details local delivery'!B:E,4,0),"-") -> 626tu203 | E58: =VLOOKUP(A58,'Details local delivery'!B:L,11,0) -> 14 | F58: =SUMIFS('Details local delivery'!M:M,'Details local delivery'!G:G,'RECAP Delivery Plan '!A58) -> 5 | G58: =VLOOKUP(A58,'Details local delivery'!B:J,9,0) -> 8500 | H58: =SUMIFS('Details local delivery'!K:K,'Details local delivery'!G:G,'RECAP Delivery Plan '!A58) -> 5000 | I58: =SUMIFS('Details local delivery'!Y:Y,'Details local delivery'!B:B,A:A) -> 0 | J58: =AVERAGEIFS('Details local delivery'!W:W,'Details local delivery'!B:B,A58) -> 1 | K58: =_xlfn.MAXIFS('Details local delivery'!Z:Z,'Details local delivery'!B:B,A58) -> 0 | L58: =_xlfn.MAXIFS('Details local delivery'!AA:AA,'Details local delivery'!B:B,A58) -> 0 | M58: =_xlfn.MAXIFS('Details local delivery'!AB:AB,'Details local delivery'!B:B,A58) -> 0 | N58: =+F58/E58 -> 0.35714286 | O58: =+H58/G58 -> 0.58823529 | P58: =K58+L58+M58 -> 0 | Q58: =P58+I58 -> 0 | R58: =Q58/P58 -> #DIV/0! | S58: =MAX(N58,O58) -> 0.58823529
A59: VOY2026COFTN58 | B59: =+IFERROR(VLOOKUP(A59,'Details local delivery'!B:C,2,0),"-") -> 46030 | C59: =B59 -> 46030 | D59: =+IFERROR(VLOOKUP(A59,'Details local delivery'!B:E,4,0),"-") -> 626tu203 | E59: =VLOOKUP(A59,'Details local delivery'!B:L,11,0) -> 14 | F59: =SUMIFS('Details local delivery'!M:M,'Details local delivery'!G:G,'RECAP Delivery Plan '!A59) -> 24 | G59: =VLOOKUP(A59,'Details local delivery'!B:J,9,0) -> 8500 | H59: =SUMIFS('Details local delivery'!K:K,'Details local delivery'!G:G,'RECAP Delivery Plan '!A59) -> 2334 | I59: =SUMIFS('Details local delivery'!Y:Y,'Details local delivery'!B:B,A:A) -> 0 | J59: =AVERAGEIFS('Details local delivery'!W:W,'Details local delivery'!B:B,A59) -> 1 | K59: =_xlfn.MAXIFS('Details local delivery'!Z:Z,'Details local delivery'!B:B,A59) -> 0 | L59: =_xlfn.MAXIFS('Details local delivery'!AA:AA,'Details local delivery'!B:B,A59) -> 0 | M59: =_xlfn.MAXIFS('Details local delivery'!AB:AB,'Details local delivery'!B:B,A59) -> 0 | N59: =+F59/E59 -> 1.7142857 | O59: =+H59/G59 -> 0.27458824 | P59: =K59+L59+M59 -> 0 | Q59: =P59+I59 -> 0 | R59: =Q59/P59 -> #DIV/0! | S59: =MAX(N59,O59) -> 1.7142857
A60: VOY2026COFTN59 | B60: =+IFERROR(VLOOKUP(A60,'Details local delivery'!B:C,2,0),"-") -> 46031 | C60: =B60 -> 46031 | D60: =+IFERROR(VLOOKUP(A60,'Details local delivery'!B:E,4,0),"-") -> 4331tu175 | E60: =VLOOKUP(A60,'Details local delivery'!B:L,11,0) -> 14 | F60: =SUMIFS('Details local delivery'!M:M,'Details local delivery'!G:G,'RECAP Delivery Plan '!A60) -> 5 | G60: =VLOOKUP(A60,'Details local delivery'!B:J,9,0) -> 9200 | H60: =SUMIFS('Details local delivery'!K:K,'Details local delivery'!G:G,'RECAP Delivery Plan '!A60) -> 5600 | I60: =SUMIFS('Details local delivery'!Y:Y,'Details local delivery'!B:B,A:A) -> 0 | J60: =AVERAGEIFS('Details local delivery'!W:W,'Details local delivery'!B:B,A60) -> 1 | K60: =_xlfn.MAXIFS('Details local delivery'!Z:Z,'Details local delivery'!B:B,A60) -> 0 | L60: =_xlfn.MAXIFS('Details local delivery'!AA:AA,'Details local delivery'!B:B,A60) -> 0 | M60: =IFERROR(_xlfn.MAXIFS('Details local delivery'!AB:AB,'Details local delivery'!B:B,A60),"-") -> 0 | N60: =+F60/E60 -> 0.35714286 | O60: =+H60/G60 -> 0.60869565 | P60: =K60+L60+M60 -> 0 | Q60: =P60+I60 -> 0 | R60: =Q60/P60 -> #DIV/0! | S60: =MAX(N60,O60) -> 0.60869565
A61: VOY2026COFTN60 | B61: =+IFERROR(VLOOKUP(A61,'Details local delivery'!B:C,2,0),"-") -> 46031 | C61: =B61 -> 46031 | D61: =+IFERROR(VLOOKUP(A61,'Details local delivery'!B:E,4,0),"-") -> 4331tu175 | E61: =VLOOKUP(A61,'Details local delivery'!B:L,11,0) -> 14 | F61: =SUMIFS('Details local delivery'!M:M,'Details local delivery'!G:G,'RECAP Delivery Plan '!A61) -> 12 | G61: =VLOOKUP(A61,'Details local delivery'!B:J,9,0) -> 9200 | H61: =SUMIFS('Details local delivery'!K:K,'Details local delivery'!G:G,'RECAP Delivery Plan '!A61) -> 7300 | I61: =SUMIFS('Details local delivery'!Y:Y,'Details local delivery'!B:B,A:A) -> 0 | J61: =AVERAGEIFS('Details local delivery'!W:W,'Details local delivery'!B:B,A61) -> 1 | K61: =_xlfn.MAXIFS('Details local delivery'!Z:Z,'Details local delivery'!B:B,A61) -> 0 | L61: =_xlfn.MAXIFS('Details local delivery'!AA:AA,'Details local delivery'!B:B,A61) -> 0 | M61: =IFERROR(_xlfn.MAXIFS('Details local delivery'!AB:AB,'Details local delivery'!B:B,A61),"-") -> 0 | N61: =+F61/E61 -> 0.85714286 | O61: =+H61/G61 -> 0.79347826 | P61: =K61+L61+M61 -> 0 | Q61: =P61+I61 -> 0 | R61: =Q61/P61 -> #DIV/0! | S61: =MAX(N61,O61) -> 0.85714286
A62: VOY2026COFTN61 | B62: =+IFERROR(VLOOKUP(A62,'Details local delivery'!B:C,2,0),"-") -> 46031 | C62: =B62 -> 46031 | D62: =+IFERROR(VLOOKUP(A62,'Details local delivery'!B:E,4,0),"-") -> REM107627 | E62: =VLOOKUP(A62,'Details local delivery'!B:L,11,0) -> 27 | F62: =SUMIFS('Details local delivery'!M:M,'Details local delivery'!G:G,'RECAP Delivery Plan '!A62) -> 10 | G62: =VLOOKUP(A62,'Details local delivery'!B:J,9,0) -> 24950 | H62: =SUMIFS('Details local delivery'!K:K,'Details local delivery'!G:G,'RECAP Delivery Plan '!A62) -> 8500 | I62: =SUMIFS('Details local delivery'!Y:Y,'Details local delivery'!B:B,A:A) -> 0 | J62: =AVERAGEIFS('Details local delivery'!W:W,'Details local delivery'!B:B,A62) -> 1 | K62: =_xlfn.MAXIFS('Details local delivery'!Z:Z,'Details local delivery'!B:B,A62) -> 0 | L62: =_xlfn.MAXIFS('Details local delivery'!AA:AA,'Details local delivery'!B:B,A62) -> 0 | M62: =IFERROR(_xlfn.MAXIFS('Details local delivery'!AB:AB,'Details local delivery'!B:B,A62),"-") -> 0 | N62: =+F62/E62 -> 0.37037037 | O62: =+H62/G62 -> 0.34068136 | P62: =K62+L62+M62 -> 0 | Q62: =P62+I62 -> 0 | R62: =Q62/P62 -> #DIV/0! | S62: =MAX(N62,O62) -> 0.37037037
A63: VOY2026COFTN62 | B63: =+IFERROR(VLOOKUP(A63,'Details local delivery'!B:C,2,0),"-") -> 46031 | C63: =B63 -> 46031 | D63: =+IFERROR(VLOOKUP(A63,'Details local delivery'!B:E,4,0),"-") -> REM107627 | E63: =VLOOKUP(A63,'Details local delivery'!B:L,11,0) -> 27 | F63: =SUMIFS('Details local delivery'!M:M,'Details local delivery'!G:G,'RECAP Delivery Plan '!A63) -> 14 | G63: =VLOOKUP(A63,'Details local delivery'!B:J,9,0) -> 24950 | H63: =SUMIFS('Details local delivery'!K:K,'Details local delivery'!G:G,'RECAP Delivery Plan '!A63) -> 1700 | I63: =SUMIFS('Details local delivery'!Y:Y,'Details local delivery'!B:B,A:A) -> 0 | J63: =AVERAGEIFS('Details local delivery'!W:W,'Details local delivery'!B:B,A63) -> 0.92083333 | K63: =_xlfn.MAXIFS('Details local delivery'!Z:Z,'Details local delivery'!B:B,A63) -> 0 | L63: =_xlfn.MAXIFS('Details local delivery'!AA:AA,'Details local delivery'!B:B,A63) -> 0 | M63: =IFERROR(_xlfn.MAXIFS('Details local delivery'!AB:AB,'Details local delivery'!B:B,A63),"-") -> 0 | N63: =+F63/E63 -> 0.51851852 | O63: =+H63/G63 -> 0.068136273 | P63: =K63+L63+M63 -> 0 | Q63: =P63+I63 -> 0 | R63: =Q63/P63 -> #DIV/0! | S63: =MAX(N63,O63) -> 0.51851852
A64: VOY2026COFTN63 | B64: =+IFERROR(VLOOKUP(A64,'Details local delivery'!B:C,2,0),"-") -> 46031 | C64: =B64 -> 46031 | D64: =+IFERROR(VLOOKUP(A64,'Details local delivery'!B:E,4,0),"-") -> Location | E64: =VLOOKUP(A64,'Details local delivery'!B:L,11,0) -> 0 | F64: =SUMIFS('Details local delivery'!M:M,'Details local delivery'!G:G,'RECAP Delivery Plan '!A64) -> 29 | G64: =VLOOKUP(A64,'Details local delivery'!B:J,9,0) -> 0 | H64: =SUMIFS('Details local delivery'!K:K,'Details local delivery'!G:G,'RECAP Delivery Plan '!A64) -> 0 | I64: =SUMIFS('Details local delivery'!Y:Y,'Details local delivery'!B:B,A:A) -> 0 | J64: =AVERAGEIFS('Details local delivery'!W:W,'Details local delivery'!B:B,A64) -> 1 | K64: =_xlfn.MAXIFS('Details local delivery'!Z:Z,'Details local delivery'!B:B,A64) -> 0 | L64: =_xlfn.MAXIFS('Details local delivery'!AA:AA,'Details local delivery'!B:B,A64) -> 0 | M64: =_xlfn.MAXIFS('Details local delivery'!AB:AB,'Details local delivery'!B:B,A64) -> 0 | N64: =+F64/E64 -> #DIV/0! | O64: =+H64/G64 -> #DIV/0! | P64: =K64+L64+M64 -> 0 | Q64: =P64+I64 -> 0 | R64: =Q64/P64 -> #DIV/0! | S64: =MAX(N64,O64) -> #DIV/0!
A65: VOY2026COFTN64 | B65: =+IFERROR(VLOOKUP(A65,'Details local delivery'!B:C,2,0),"-") -> 46031 | C65: =B65 -> 46031 | D65: =+IFERROR(VLOOKUP(A65,'Details local delivery'!B:E,4,0),"-") -> 5735tu217 | E65: =VLOOKUP(A65,'Details local delivery'!B:L,11,0) -> 14 | F65: =SUMIFS('Details local delivery'!M:M,'Details local delivery'!G:G,'RECAP Delivery Plan '!A65) -> 17 | G65: =VLOOKUP(A65,'Details local delivery'!B:J,9,0) -> 10200 | H65: =SUMIFS('Details local delivery'!K:K,'Details local delivery'!G:G,'RECAP Delivery Plan '!A65) -> 11000 | I65: =SUMIFS('Details local delivery'!Y:Y,'Details local delivery'!B:B,A:A) -> 0 | J65: =AVERAGEIFS('Details local delivery'!W:W,'Details local delivery'!B:B,A65) -> 1 | K65: =_xlfn.MAXIFS('Details local delivery'!Z:Z,'Details local delivery'!B:B,A65) -> 0 | L65: =_xlfn.MAXIFS('Details local delivery'!AA:AA,'Details local delivery'!B:B,A65) -> 0 | M65: =_xlfn.MAXIFS('Details local delivery'!AB:AB,'Details local delivery'!B:B,A65) -> 0 | N65: =+F65/E65 -> 1.2142857 | O65: =+H65/G65 -> 1.0784314 | P65: =K65+L65+M65 -> 0 | Q65: =P65+I65 -> 0 | R65: =Q65/P65 -> #DIV/0! | S65: =MAX(N65,O65) -> 1.2142857
A66: VOY2026COFTN65 | B66: =+IFERROR(VLOOKUP(A66,'Details local delivery'!B:C,2,0),"-") -> 46031 | C66: =B66 -> 46031 | D66: =+IFERROR(VLOOKUP(A66,'Details local delivery'!B:E,4,0),"-") -> 626tu203 | E66: =VLOOKUP(A66,'Details local delivery'!B:L,11,0) -> 14 | F66: =SUMIFS('Details local delivery'!M:M,'Details local delivery'!G:G,'RECAP Delivery Plan '!A66) -> 18 | G66: =VLOOKUP(A66,'Details local delivery'!B:J,9,0) -> 8500 | H66: =SUMIFS('Details local delivery'!K:K,'Details local delivery'!G:G,'RECAP Delivery Plan '!A66) -> 1360.5 | I66: =SUMIFS('Details local delivery'!Y:Y,'Details local delivery'!B:B,A:A) -> 0 | J66: =AVERAGEIFS('Details local delivery'!W:W,'Details local delivery'!B:B,A66) -> 1 | K66: =_xlfn.MAXIFS('Details local delivery'!Z:Z,'Details local delivery'!B:B,A66) -> 0 | L66: =_xlfn.MAXIFS('Details local delivery'!AA:AA,'Details local delivery'!B:B,A66) -> 0 | M66: =IFERROR(_xlfn.MAXIFS('Details local delivery'!AB:AB,'Details local delivery'!B:B,A66),"-") -> 0 | N66: =+F66/E66 -> 1.2857143 | O66: =+H66/G66 -> 0.16005882 | P66: =K66+L66+M66 -> 0 | Q66: =P66+I66 -> 0 | R66: =Q66/P66 -> #DIV/0! | S66: =MAX(N66,O66) -> 1.2857143
A67: VOY2026COFTN66 | B67: =+IFERROR(VLOOKUP(A67,'Details local delivery'!B:C,2,0),"-") -> 46031 | C67: =B67 -> 46031 | D67: =+IFERROR(VLOOKUP(A67,'Details local delivery'!B:E,4,0),"-") -> 9524TU238 | E67: =VLOOKUP(A67,'Details local delivery'!B:L,11,0) -> 14 | F67: =SUMIFS('Details local delivery'!M:M,'Details local delivery'!G:G,'RECAP Delivery Plan '!A67) -> 9 | G67: =VLOOKUP(A67,'Details local delivery'!B:J,9,0) -> 10230 | H67: =SUMIFS('Details local delivery'!K:K,'Details local delivery'!G:G,'RECAP Delivery Plan '!A67) -> 5300 | I67: =SUMIFS('Details local delivery'!Y:Y,'Details local delivery'!B:B,A:A) -> 0 | J67: =AVERAGEIFS('Details local delivery'!W:W,'Details local delivery'!B:B,A67) -> 1 | K67: =_xlfn.MAXIFS('Details local delivery'!Z:Z,'Details local delivery'!B:B,A67) -> 0 | L67: =_xlfn.MAXIFS('Details local delivery'!AA:AA,'Details local delivery'!B:B,A67) -> 0 | M67: =IFERROR(_xlfn.MAXIFS('Details local delivery'!AB:AB,'Details local delivery'!B:B,A67),"-") -> 0 | N67: =+F67/E67 -> 0.64285714 | O67: =+H67/G67 -> 0.51808407 | P67: =K67+L67+M67 -> 0 | Q67: =P67+I67 -> 0 | R67: =Q67/P67 -> #DIV/0! | S67: =MAX(N67,O67) -> 0.64285714
A68: VOY2026COFTN67 | B68: =+IFERROR(VLOOKUP(A68,'Details local delivery'!B:C,2,0),"-") -> 46031 | C68: =B68 -> 46031 | D68: =+IFERROR(VLOOKUP(A68,'Details local delivery'!B:E,4,0),"-") -> 9524TU238 | E68: =VLOOKUP(A68,'Details local delivery'!B:L,11,0) -> 14 | F68: =SUMIFS('Details local delivery'!M:M,'Details local delivery'!G:G,'RECAP Delivery Plan '!A68) -> 14 | G68: =VLOOKUP(A68,'Details local delivery'!B:J,9,0) -> 10230 | H68: =SUMIFS('Details local delivery'!K:K,'Details local delivery'!G:G,'RECAP Delivery Plan '!A68) -> 10230 | I68: =SUMIFS('Details local delivery'!Y:Y,'Details local delivery'!B:B,A:A) -> 0 | J68: =AVERAGEIFS('Details local delivery'!W:W,'Details local delivery'!B:B,A68) -> 1 | K68: =_xlfn.MAXIFS('Details local delivery'!Z:Z,'Details local delivery'!B:B,A68) -> 0 | L68: =_xlfn.MAXIFS('Details local delivery'!AA:AA,'Details local delivery'!B:B,A68) -> 0 | M68: =_xlfn.MAXIFS('Details local delivery'!AB:AB,'Details local delivery'!B:B,A68) -> 0 | N68: =+F68/E68 -> 1 | O68: =+H68/G68 -> 1 | P68: =K68+L68+M68 -> 0 | Q68: =P68+I68 -> 0 | R68: =Q68/P68 -> #DIV/0! | S68: =MAX(N68,O68) -> 1
A69: VOY2026COFTN68 | B69: =+IFERROR(VLOOKUP(A69,'Details local delivery'!B:C,2,0),"-") -> 46031 | C69: =B69 -> 46031 | D69: =+IFERROR(VLOOKUP(A69,'Details local delivery'!B:E,4,0),"-") -> 7797tu218 | E69: =VLOOKUP(A69,'Details local delivery'!B:L,11,0) -> 3 | F69: =SUMIFS('Details local delivery'!M:M,'Details local delivery'!G:G,'RECAP Delivery Plan '!A69) -> 1 | G69: =VLOOKUP(A69,'Details local delivery'!B:J,9,0) -> 927 | H69: =SUMIFS('Details local delivery'!K:K,'Details local delivery'!G:G,'RECAP Delivery Plan '!A69) -> 257 | I69: =SUMIFS('Details local delivery'!Y:Y,'Details local delivery'!B:B,A:A) -> 0 | J69: =AVERAGEIFS('Details local delivery'!W:W,'Details local delivery'!B:B,A69) -> 1 | K69: =_xlfn.MAXIFS('Details local delivery'!Z:Z,'Details local delivery'!B:B,A69) -> 0 | L69: =_xlfn.MAXIFS('Details local delivery'!AA:AA,'Details local delivery'!B:B,A69) -> 0 | M69: =_xlfn.MAXIFS('Details local delivery'!AB:AB,'Details local delivery'!B:B,A69) -> 0 | N69: =+F69/E69 -> 0.33333333 | O69: =+H69/G69 -> 0.2772384 | P69: =K69+L69+M69 -> 0 | Q69: =P69+I69 -> 0 | R69: =Q69/P69 -> #DIV/0! | S69: =MAX(N69,O69) -> 0.33333333
A70: VOY2026COFTN69 | B70: =+IFERROR(VLOOKUP(A70,'Details local delivery'!B:C,2,0),"-") -> 46031 | C70: =B70 -> 46031 | D70: =+IFERROR(VLOOKUP(A70,'Details local delivery'!B:E,4,0),"-") -> 7797tu218 | E70: =VLOOKUP(A70,'Details local delivery'!B:L,11,0) -> 3 | F70: =SUMIFS('Details local delivery'!M:M,'Details local delivery'!G:G,'RECAP Delivery Plan '!A70) -> 3 | G70: =VLOOKUP(A70,'Details local delivery'!B:J,9,0) -> 927 | H70: =SUMIFS('Details local delivery'!K:K,'Details local delivery'!G:G,'RECAP Delivery Plan '!A70) -> 662 | I70: =SUMIFS('Details local delivery'!Y:Y,'Details local delivery'!B:B,A:A) -> 0 | J70: =AVERAGEIFS('Details local delivery'!W:W,'Details local delivery'!B:B,A70) -> 1 | K70: =_xlfn.MAXIFS('Details local delivery'!Z:Z,'Details local delivery'!B:B,A70) -> 0 | L70: =_xlfn.MAXIFS('Details local delivery'!AA:AA,'Details local delivery'!B:B,A70) -> 0 | M70: =IFERROR(_xlfn.MAXIFS('Details local delivery'!AB:AB,'Details local delivery'!B:B,A70),"-") -> 0 | N70: =+F70/E70 -> 1 | O70: =+H70/G70 -> 0.71413161 | P70: =K70+L70+M70 -> 0 | Q70: =P70+I70 -> 0 | R70: =Q70/P70 -> #DIV/0! | S70: =MAX(N70,O70) -> 1
A71: VOY2026COFTN70 | B71: =+IFERROR(VLOOKUP(A71,'Details local delivery'!B:C,2,0),"-") -> 46031 | C71: =B71 -> 46031 | D71: =+IFERROR(VLOOKUP(A71,'Details local delivery'!B:E,4,0),"-") -> 7797tu218 | E71: =VLOOKUP(A71,'Details local delivery'!B:L,11,0) -> 3 | F71: =SUMIFS('Details local delivery'!M:M,'Details local delivery'!G:G,'RECAP Delivery Plan '!A71) -> 2 | G71: =VLOOKUP(A71,'Details local delivery'!B:J,9,0) -> 927 | H71: =SUMIFS('Details local delivery'!K:K,'Details local delivery'!G:G,'RECAP Delivery Plan '!A71) -> 562 | I71: =SUMIFS('Details local delivery'!Y:Y,'Details local delivery'!B:B,A:A) -> 0 | J71: =AVERAGEIFS('Details local delivery'!W:W,'Details local delivery'!B:B,A71) -> 0.90208333 | K71: =_xlfn.MAXIFS('Details local delivery'!Z:Z,'Details local delivery'!B:B,A71) -> 0 | L71: =_xlfn.MAXIFS('Details local delivery'!AA:AA,'Details local delivery'!B:B,A71) -> 0 | M71: =IFERROR(_xlfn.MAXIFS('Details local delivery'!AB:AB,'Details local delivery'!B:B,A71),"-") -> 0 | N71: =+F71/E71 -> 0.66666667 | O71: =+H71/G71 -> 0.60625674 | P71: =K71+L71+M71 -> 0 | Q71: =P71+I71 -> 0 | R71: =Q71/P71 -> #DIV/0! | S71: =MAX(N71,O71) -> 0.66666667
A72: VOY2026COFTN71 | B72: =+IFERROR(VLOOKUP(A72,'Details local delivery'!B:C,2,0),"-") -> 46031 | C72: =B72 -> 46031 | D72: =+IFERROR(VLOOKUP(A72,'Details local delivery'!B:E,4,0),"-") -> 4331tu175 | E72: =VLOOKUP(A72,'Details local delivery'!B:L,11,0) -> 14 | F72: =SUMIFS('Details local delivery'!M:M,'Details local delivery'!G:G,'RECAP Delivery Plan '!A72) -> 1 | G72: =VLOOKUP(A72,'Details local delivery'!B:J,9,0) -> 9200 | H72: =SUMIFS('Details local delivery'!K:K,'Details local delivery'!G:G,'RECAP Delivery Plan '!A72) -> 1100 | I72: =SUMIFS('Details local delivery'!Y:Y,'Details local delivery'!B:B,A:A) -> 0 | J72: =AVERAGEIFS('Details local delivery'!W:W,'Details local delivery'!B:B,A72) -> 0.43333333 | K72: =_xlfn.MAXIFS('Details local delivery'!Z:Z,'Details local delivery'!B:B,A72) -> 0 | L72: =_xlfn.MAXIFS('Details local delivery'!AA:AA,'Details local delivery'!B:B,A72) -> 0 | M72: =IFERROR(_xlfn.MAXIFS('Details local delivery'!AB:AB,'Details local delivery'!B:B,A72),"-") -> 0 | N72: =+F72/E72 -> 0.071428571 | O72: =+H72/G72 -> 0.11956522 | P72: =K72+L72+M72 -> 0 | Q72: =P72+I72 -> 0 | R72: =Q72/P72 -> #DIV/0! | S72: =MAX(N72,O72) -> 0.11956522
A73: VOY2026COFTN72 | B73: =+IFERROR(VLOOKUP(A73,'Details local delivery'!B:C,2,0),"-") -> 46032 | C73: =B73 -> 46032 | D73: =+IFERROR(VLOOKUP(A73,'Details local delivery'!B:E,4,0),"-") -> 5735tu217 | E73: =VLOOKUP(A73,'Details local delivery'!B:L,11,0) -> 14 | F73: =SUMIFS('Details local delivery'!M:M,'Details local delivery'!G:G,'RECAP Delivery Plan '!A73) -> 6 | G73: =VLOOKUP(A73,'Details local delivery'!B:J,9,0) -> 10200 | H73: =SUMIFS('Details local delivery'!K:K,'Details local delivery'!G:G,'RECAP Delivery Plan '!A73) -> 7100 | I73: =SUMIFS('Details local delivery'!Y:Y,'Details local delivery'!B:B,A:A) -> 0 | J73: =AVERAGEIFS('Details local delivery'!W:W,'Details local delivery'!B:B,A73) -> 1 | K73: =_xlfn.MAXIFS('Details local delivery'!Z:Z,'Details local delivery'!B:B,A73) -> 0 | L73: =_xlfn.MAXIFS('Details local delivery'!AA:AA,'Details local delivery'!B:B,A73) -> 0 | M73: =IFERROR(_xlfn.MAXIFS('Details local delivery'!AB:AB,'Details local delivery'!B:B,A73),"-") -> 0 | N73: =+F73/E73 -> 0.42857143 | O73: =+H73/G73 -> 0.69607843 | P73: =K73+L73+M73 -> 0 | Q73: =P73+I73 -> 0 | R73: =Q73/P73 -> #DIV/0! | S73: =MAX(N73,O73) -> 0.69607843
A74: VOY2026COFTN73 | B74: =+IFERROR(VLOOKUP(A74,'Details local delivery'!B:C,2,0),"-") -> 46032 | C74: =B74 -> 46032 | D74: =+IFERROR(VLOOKUP(A74,'Details local delivery'!B:E,4,0),"-") -> 9524TU238 | E74: =VLOOKUP(A74,'Details local delivery'!B:L,11,0) -> 14 | F74: =SUMIFS('Details local delivery'!M:M,'Details local delivery'!G:G,'RECAP Delivery Plan '!A74) -> 8 | G74: =VLOOKUP(A74,'Details local delivery'!B:J,9,0) -> 10230 | H74: =SUMIFS('Details local delivery'!K:K,'Details local delivery'!G:G,'RECAP Delivery Plan '!A74) -> 6000 | I74: =SUMIFS('Details local delivery'!Y:Y,'Details local delivery'!B:B,A:A) -> 0 | J74: =AVERAGEIFS('Details local delivery'!W:W,'Details local delivery'!B:B,A74) -> 1 | K74: =_xlfn.MAXIFS('Details local delivery'!Z:Z,'Details local delivery'!B:B,A74) -> 0 | L74: =_xlfn.MAXIFS('Details local delivery'!AA:AA,'Details local delivery'!B:B,A74) -> 0 | M74: =_xlfn.MAXIFS('Details local delivery'!AB:AB,'Details local delivery'!B:B,A74) -> 0 | N74: =+F74/E74 -> 0.57142857 | O74: =+H74/G74 -> 0.58651026 | P74: =K74+L74+M74 -> 0 | Q74: =P74+I74 -> 0 | R74: =Q74/P74 -> #DIV/0! | S74: =MAX(N74,O74) -> 0.58651026
A75: VOY2026COFTN74 | B75: =+IFERROR(VLOOKUP(A75,'Details local delivery'!B:C,2,0),"-") -> 46032 | C75: =B75 -> 46032 | D75: =+IFERROR(VLOOKUP(A75,'Details local delivery'!B:E,4,0),"-") -> 9524TU238 | E75: =VLOOKUP(A75,'Details local delivery'!B:L,11,0) -> 14 | F75: =SUMIFS('Details local delivery'!M:M,'Details local delivery'!G:G,'RECAP Delivery Plan '!A75) -> 10 | G75: =VLOOKUP(A75,'Details local delivery'!B:J,9,0) -> 10230 | H75: =SUMIFS('Details local delivery'!K:K,'Details local delivery'!G:G,'RECAP Delivery Plan '!A75) -> 6000 | I75: =SUMIFS('Details local delivery'!Y:Y,'Details local delivery'!B:B,A:A) -> 0 | J75: =AVERAGEIFS('Details local delivery'!W:W,'Details local delivery'!B:B,A75) -> 1 | K75: =_xlfn.MAXIFS('Details local delivery'!Z:Z,'Details local delivery'!B:B,A75) -> 0 | L75: =_xlfn.MAXIFS('Details local delivery'!AA:AA,'Details local delivery'!B:B,A75) -> 0 | M75: =_xlfn.MAXIFS('Details local delivery'!AB:AB,'Details local delivery'!B:B,A75) -> 0 | N75: =+F75/E75 -> 0.71428571 | O75: =+H75/G75 -> 0.58651026 | P75: =K75+L75+M75 -> 0 | Q75: =P75+I75 -> 0 | R75: =Q75/P75 -> #DIV/0! | S75: =MAX(N75,O75) -> 0.71428571
A76: VOY2026COFTN75 | B76: =+IFERROR(VLOOKUP(A76,'Details local delivery'!B:C,2,0),"-") -> 46032 | C76: =B76 -> 46032 | D76: =+IFERROR(VLOOKUP(A76,'Details local delivery'!B:E,4,0),"-") -> REM107627 | E76: =VLOOKUP(A76,'Details local delivery'!B:L,11,0) -> 27 | F76: =SUMIFS('Details local delivery'!M:M,'Details local delivery'!G:G,'RECAP Delivery Plan '!A76) -> 14 | G76: =VLOOKUP(A76,'Details local delivery'!B:J,9,0) -> 24950 | H76: =SUMIFS('Details local delivery'!K:K,'Details local delivery'!G:G,'RECAP Delivery Plan '!A76) -> 16000 | I76: =SUMIFS('Details local delivery'!Y:Y,'Details local delivery'!B:B,A:A) -> 0 | J76: =AVERAGEIFS('Details local delivery'!W:W,'Details local delivery'!B:B,A76) -> 1 | K76: =_xlfn.MAXIFS('Details local delivery'!Z:Z,'Details local delivery'!B:B,A76) -> 0 | L76: =_xlfn.MAXIFS('Details local delivery'!AA:AA,'Details local delivery'!B:B,A76) -> 0 | M76: =IFERROR(_xlfn.MAXIFS('Details local delivery'!AB:AB,'Details local delivery'!B:B,A76),"-") -> 0 | N76: =+F76/E76 -> 0.51851852 | O76: =+H76/G76 -> 0.64128257 | P76: =K76+L76+M76 -> 0 | Q76: =P76+I76 -> 0 | R76: =Q76/P76 -> #DIV/0! | S76: =MAX(N76,O76) -> 0.64128257
A77: VOY2026COFTN76 | B77: =+IFERROR(VLOOKUP(A77,'Details local delivery'!B:C,2,0),"-") -> 46034 | C77: =B77 -> 46034 | D77: =+IFERROR(VLOOKUP(A77,'Details local delivery'!B:E,4,0),"-") -> REM107627 | E77: =VLOOKUP(A77,'Details local delivery'!B:L,11,0) -> 27 | F77: =SUMIFS('Details local delivery'!M:M,'Details local delivery'!G:G,'RECAP Delivery Plan '!A77) -> 24 | G77: =VLOOKUP(A77,'Details local delivery'!B:J,9,0) -> 24950 | H77: =SUMIFS('Details local delivery'!K:K,'Details local delivery'!G:G,'RECAP Delivery Plan '!A77) -> 23000 | I77: =SUMIFS('Details local delivery'!Y:Y,'Details local delivery'!B:B,A:A) -> 0 | J77: =AVERAGEIFS('Details local delivery'!W:W,'Details local delivery'!B:B,A77) -> 1 | K77: =_xlfn.MAXIFS('Details local delivery'!Z:Z,'Details local delivery'!B:B,A77) -> 0 | L77: =_xlfn.MAXIFS('Details local delivery'!AA:AA,'Details local delivery'!B:B,A77) -> 0 | M77: =IFERROR(_xlfn.MAXIFS('Details local delivery'!AB:AB,'Details local delivery'!B:B,A77),"-") -> 0 | N77: =+F77/E77 -> 0.88888889 | O77: =+H77/G77 -> 0.92184369 | P77: =K77+L77+M77 -> 0 | Q77: =P77+I77 -> 0 | R77: =Q77/P77 -> #DIV/0! | S77: =MAX(N77,O77) -> 0.92184369
A78: VOY2026COFTN77 | B78: =+IFERROR(VLOOKUP(A78,'Details local delivery'!B:C,2,0),"-") -> 46034 | C78: =B78 -> 46034 | D78: =+IFERROR(VLOOKUP(A78,'Details local delivery'!B:E,4,0),"-") -> 7797tu218 | E78: =VLOOKUP(A78,'Details local delivery'!B:L,11,0) -> 3 | F78: =SUMIFS('Details local delivery'!M:M,'Details local delivery'!G:G,'RECAP Delivery Plan '!A78) -> 1 | G78: =VLOOKUP(A78,'Details local delivery'!B:J,9,0) -> 927 | H78: =SUMIFS('Details local delivery'!K:K,'Details local delivery'!G:G,'RECAP Delivery Plan '!A78) -> 147 | I78: =SUMIFS('Details local delivery'!Y:Y,'Details local delivery'!B:B,A:A) -> 0 | J78: =AVERAGEIFS('Details local delivery'!W:W,'Details local delivery'!B:B,A78) -> 1 | K78: =_xlfn.MAXIFS('Details local delivery'!Z:Z,'Details local delivery'!B:B,A78) -> 0 | L78: =_xlfn.MAXIFS('Details local delivery'!AA:AA,'Details local delivery'!B:B,A78) -> 0 | M78: =IFERROR(_xlfn.MAXIFS('Details local delivery'!AB:AB,'Details local delivery'!B:B,A78),"-") -> 0 | N78: =+F78/E78 -> 0.33333333 | O78: =+H78/G78 -> 0.15857605 | P78: =K78+L78+M78 -> 0 | Q78: =P78+I78 -> 0 | R78: =Q78/P78 -> #DIV/0! | S78: =MAX(N78,O78) -> 0.33333333
A79: VOY2026COFTN78 | B79: =+IFERROR(VLOOKUP(A79,'Details local delivery'!B:C,2,0),"-") -> 46034 | C79: =B79 -> 46034 | D79: =+IFERROR(VLOOKUP(A79,'Details local delivery'!B:E,4,0),"-") -> Location | E79: =VLOOKUP(A79,'Details local delivery'!B:L,11,0) -> 0 | F79: =SUMIFS('Details local delivery'!M:M,'Details local delivery'!G:G,'RECAP Delivery Plan '!A79) -> 24 | G79: =VLOOKUP(A79,'Details local delivery'!B:J,9,0) -> 0 | H79: =SUMIFS('Details local delivery'!K:K,'Details local delivery'!G:G,'RECAP Delivery Plan '!A79) -> 15400 | I79: =SUMIFS('Details local delivery'!Y:Y,'Details local delivery'!B:B,A:A) -> 0 | J79: =AVERAGEIFS('Details local delivery'!W:W,'Details local delivery'!B:B,A79) -> 1 | K79: =_xlfn.MAXIFS('Details local delivery'!Z:Z,'Details local delivery'!B:B,A79) -> 0 | L79: =_xlfn.MAXIFS('Details local delivery'!AA:AA,'Details local delivery'!B:B,A79) -> 0 | M79: =IFERROR(_xlfn.MAXIFS('Details local delivery'!AB:AB,'Details local delivery'!B:B,A79),"-") -> 0 | N79: =+F79/E79 -> #DIV/0! | O79: =+H79/G79 -> #DIV/0! | P79: =K79+L79+M79 -> 0 | Q79: =P79+I79 -> 0 | R79: =Q79/P79 -> #DIV/0! | S79: =MAX(N79,O79) -> #DIV/0!
A80: VOY2026COFTN79 | B80: =+IFERROR(VLOOKUP(A80,'Details local delivery'!B:C,2,0),"-") -> 46034 | C80: =B80 -> 46034 | D80: =+IFERROR(VLOOKUP(A80,'Details local delivery'!B:E,4,0),"-") -> Location | E80: =VLOOKUP(A80,'Details local delivery'!B:L,11,0) -> 0 | F80: =SUMIFS('Details local delivery'!M:M,'Details local delivery'!G:G,'RECAP Delivery Plan '!A80) -> 27 | G80: =VLOOKUP(A80,'Details local delivery'!B:J,9,0) -> 0 | H80: =SUMIFS('Details local delivery'!K:K,'Details local delivery'!G:G,'RECAP Delivery Plan '!A80) -> 22303 | I80: =SUMIFS('Details local delivery'!Y:Y,'Details local delivery'!B:B,A:A) -> 0 | J80: =AVERAGEIFS('Details local delivery'!W:W,'Details local delivery'!B:B,A80) -> 1 | K80: =_xlfn.MAXIFS('Details local delivery'!Z:Z,'Details local delivery'!B:B,A80) -> 0 | L80: =_xlfn.MAXIFS('Details local delivery'!AA:AA,'Details local delivery'!B:B,A80) -> 0 | M80: =_xlfn.MAXIFS('Details local delivery'!AB:AB,'Details local delivery'!B:B,A80) -> 0 | N80: =+F80/E80 -> #DIV/0! | O80: =+H80/G80 -> #DIV/0! | P80: =K80+L80+M80 -> 0 | Q80: =P80+I80 -> 0 | R80: =Q80/P80 -> #DIV/0! | S80: =MAX(N80,O80) -> #DIV/0!
A81: VOY2026COFTN80 | B81: =+IFERROR(VLOOKUP(A81,'Details local delivery'!B:C,2,0),"-") -> 46034 | C81: =B81 -> 46034 | D81: =+IFERROR(VLOOKUP(A81,'Details local delivery'!B:E,4,0),"-") -> 4331tu175 | E81: =VLOOKUP(A81,'Details local delivery'!B:L,11,0) -> 14 | F81: =SUMIFS('Details local delivery'!M:M,'Details local delivery'!G:G,'RECAP Delivery Plan '!A81) -> 14 | G81: =VLOOKUP(A81,'Details local delivery'!B:J,9,0) -> 9200 | H81: =SUMIFS('Details local delivery'!K:K,'Details local delivery'!G:G,'RECAP Delivery Plan '!A81) -> 6500 | I81: =SUMIFS('Details local delivery'!Y:Y,'Details local delivery'!B:B,A:A) -> 0 | J81: 1 | K81: =_xlfn.MAXIFS('Details local delivery'!Z:Z,'Details local delivery'!B:B,A81) -> 0 | L81: =_xlfn.MAXIFS('Details local delivery'!AA:AA,'Details local delivery'!B:B,A81) -> 0 | M81: =_xlfn.MAXIFS('Details local delivery'!AB:AB,'Details local delivery'!B:B,A81) -> 0 | N81: =+F81/E81 -> 1 | O81: =+H81/G81 -> 0.70652174 | P81: =K81+L81+M81 -> 0 | Q81: =P81+I81 -> 0 | R81: =Q81/P81 -> #DIV/0! | S81: =MAX(N81,O81) -> 1
A82: VOY2026COFTN81 | B82: =+IFERROR(VLOOKUP(A82,'Details local delivery'!B:C,2,0),"-") -> 46034 | C82: =B82 -> 46034 | D82: =+IFERROR(VLOOKUP(A82,'Details local delivery'!B:E,4,0),"-") -> 4331tu175 | E82: =VLOOKUP(A82,'Details local delivery'!B:L,11,0) -> 14 | F82: =SUMIFS('Details local delivery'!M:M,'Details local delivery'!G:G,'RECAP Delivery Plan '!A82) -> 14 | G82: =VLOOKUP(A82,'Details local delivery'!B:J,9,0) -> 9200 | H82: =SUMIFS('Details local delivery'!K:K,'Details local delivery'!G:G,'RECAP Delivery Plan '!A82) -> 4200 | I82: =SUMIFS('Details local delivery'!Y:Y,'Details local delivery'!B:B,A:A) -> 0 | J82: =AVERAGEIFS('Details local delivery'!W:W,'Details local delivery'!B:B,A82) -> 1 | K82: =_xlfn.MAXIFS('Details local delivery'!Z:Z,'Details local delivery'!B:B,A82) -> 0 | L82: =_xlfn.MAXIFS('Details local delivery'!AA:AA,'Details local delivery'!B:B,A82) -> 0 | M82: =_xlfn.MAXIFS('Details local delivery'!AB:AB,'Details local delivery'!B:B,A82) -> 0 | N82: =+F82/E82 -> 1 | O82: =+H82/G82 -> 0.45652174 | P82: =K82+L82+M82 -> 0 | Q82: =P82+I82 -> 0 | R82: =Q82/P82 -> #DIV/0! | S82: =MAX(N82,O82) -> 1
A83: VOY2026COFTN82 | B83: =+IFERROR(VLOOKUP(A83,'Details local delivery'!B:C,2,0),"-") -> 46034 | C83: =B83 -> 46034 | D83: =+IFERROR(VLOOKUP(A83,'Details local delivery'!B:E,4,0),"-") -> 626tu203 | E83: =VLOOKUP(A83,'Details local delivery'!B:L,11,0) -> 14 | F83: =SUMIFS('Details local delivery'!M:M,'Details local delivery'!G:G,'RECAP Delivery Plan '!A83) -> 16 | G83: =VLOOKUP(A83,'Details local delivery'!B:J,9,0) -> 8500 | H83: =SUMIFS('Details local delivery'!K:K,'Details local delivery'!G:G,'RECAP Delivery Plan '!A83) -> 9013 | I83: =SUMIFS('Details local delivery'!Y:Y,'Details local delivery'!B:B,A:A) -> 0 | J83: =AVERAGEIFS('Details local delivery'!W:W,'Details local delivery'!B:B,A83) -> 1 | K83: =_xlfn.MAXIFS('Details local delivery'!Z:Z,'Details local delivery'!B:B,A83) -> 0 | L83: =_xlfn.MAXIFS('Details local delivery'!AA:AA,'Details local delivery'!B:B,A83) -> 0 | M83: =IFERROR(_xlfn.MAXIFS('Details local delivery'!AB:AB,'Details local delivery'!B:B,A83),"-") -> 0 | N83: =+F83/E83 -> 1.1428571 | O83: =+H83/G83 -> 1.0603529 | P83: =K83+L83+M83 -> 0 | Q83: =P83+I83 -> 0 | R83: =Q83/P83 -> #DIV/0! | S83: =MAX(N83,O83) -> 1.1428571
A84: VOY2026COFTN83 | B84: =+IFERROR(VLOOKUP(A84,'Details local delivery'!B:C,2,0),"-") -> 46034 | C84: =B84 -> 46034 | D84: =+IFERROR(VLOOKUP(A84,'Details local delivery'!B:E,4,0),"-") -> 5735tu217 | E84: =VLOOKUP(A84,'Details local delivery'!B:L,11,0) -> 14 | F84: =SUMIFS('Details local delivery'!M:M,'Details local delivery'!G:G,'RECAP Delivery Plan '!A84) -> 7 | G84: =VLOOKUP(A84,'Details local delivery'!B:J,9,0) -> 10200 | H84: =SUMIFS('Details local delivery'!K:K,'Details local delivery'!G:G,'RECAP Delivery Plan '!A84) -> 7100 | I84: =SUMIFS('Details local delivery'!Y:Y,'Details local delivery'!B:B,A:A) -> 0 | J84: =AVERAGEIFS('Details local delivery'!W:W,'Details local delivery'!B:B,A84) -> 1 | K84: =_xlfn.MAXIFS('Details local delivery'!Z:Z,'Details local delivery'!B:B,A84) -> 0 | L84: =_xlfn.MAXIFS('Details local delivery'!AA:AA,'Details local delivery'!B:B,A84) -> 0 | M84: =IFERROR(_xlfn.MAXIFS('Details local delivery'!AB:AB,'Details local delivery'!B:B,A84),"-") -> 0 | N84: =+F84/E84 -> 0.5 | O84: =+H84/G84 -> 0.69607843 | P84: =K84+L84+M84 -> 0 | Q84: =P84+I84 -> 0 | R84: =Q84/P84 -> #DIV/0! | S84: =MAX(N84,O84) -> 0.69607843
A85: VOY2026COFTN84 | B85: =+IFERROR(VLOOKUP(A85,'Details local delivery'!B:C,2,0),"-") -> 46034 | C85: =B85 -> 46034 | D85: =+IFERROR(VLOOKUP(A85,'Details local delivery'!B:E,4,0),"-") -> 5735tu217 | E85: =VLOOKUP(A85,'Details local delivery'!B:L,11,0) -> 14 | F85: =SUMIFS('Details local delivery'!M:M,'Details local delivery'!G:G,'RECAP Delivery Plan '!A85) -> 14 | G85: =VLOOKUP(A85,'Details local delivery'!B:J,9,0) -> 10200 | H85: =SUMIFS('Details local delivery'!K:K,'Details local delivery'!G:G,'RECAP Delivery Plan '!A85) -> 7626 | I85: =SUMIFS('Details local delivery'!Y:Y,'Details local delivery'!B:B,A:A) -> 0 | J85: =AVERAGEIFS('Details local delivery'!W:W,'Details local delivery'!B:B,A85) -> 1 | K85: =_xlfn.MAXIFS('Details local delivery'!Z:Z,'Details local delivery'!B:B,A85) -> 0 | L85: =_xlfn.MAXIFS('Details local delivery'!AA:AA,'Details local delivery'!B:B,A85) -> 0 | M85: =IFERROR(_xlfn.MAXIFS('Details local delivery'!AB:AB,'Details local delivery'!B:B,A85),"-") -> 0 | N85: =+F85/E85 -> 1 | O85: =+H85/G85 -> 0.74764706 | P85: =K85+L85+M85 -> 0 | Q85: =P85+I85 -> 0 | R85: =Q85/P85 -> #DIV/0! | S85: =MAX(N85,O85) -> 1
A86: VOY2026COFTN85 | B86: =+IFERROR(VLOOKUP(A86,'Details local delivery'!B:C,2,0),"-") -> 46034 | C86: =B86 -> 46034 | D86: =+IFERROR(VLOOKUP(A86,'Details local delivery'!B:E,4,0),"-") -> 9524TU238 | E86: =VLOOKUP(A86,'Details local delivery'!B:L,11,0) -> 14 | F86: =SUMIFS('Details local delivery'!M:M,'Details local delivery'!G:G,'RECAP Delivery Plan '!A86) -> 10 | G86: =VLOOKUP(A86,'Details local delivery'!B:J,9,0) -> 10230 | H86: =SUMIFS('Details local delivery'!K:K,'Details local delivery'!G:G,'RECAP Delivery Plan '!A86) -> 10000 | I86: =SUMIFS('Details local delivery'!Y:Y,'Details local delivery'!B:B,A:A) -> 0 | J86: =AVERAGEIFS('Details local delivery'!W:W,'Details local delivery'!B:B,A86) -> 1 | K86: =_xlfn.MAXIFS('Details local delivery'!Z:Z,'Details local delivery'!B:B,A86) -> 0 | L86: =_xlfn.MAXIFS('Details local delivery'!AA:AA,'Details local delivery'!B:B,A86) -> 0 | M86: =IFERROR(_xlfn.MAXIFS('Details local delivery'!AB:AB,'Details local delivery'!B:B,A86),"-") -> 0 | N86: =+F86/E86 -> 0.71428571 | O86: =+H86/G86 -> 0.97751711 | P86: =K86+L86+M86 -> 0 | Q86: =P86+I86 -> 0 | R86: =Q86/P86 -> #DIV/0! | S86: =MAX(N86,O86) -> 0.97751711
A87: VOY2026COFTN86 | B87: =+IFERROR(VLOOKUP(A87,'Details local delivery'!B:C,2,0),"-") -> 46034 | C87: =B87 -> 46034 | D87: =+IFERROR(VLOOKUP(A87,'Details local delivery'!B:E,4,0),"-") -> 9524TU238 | E87: =VLOOKUP(A87,'Details local delivery'!B:L,11,0) -> 14 | F87: =SUMIFS('Details local delivery'!M:M,'Details local delivery'!G:G,'RECAP Delivery Plan '!A87) -> 4 | G87: =VLOOKUP(A87,'Details local delivery'!B:J,9,0) -> 10230 | H87: =SUMIFS('Details local delivery'!K:K,'Details local delivery'!G:G,'RECAP Delivery Plan '!A87) -> 2100 | I87: =SUMIFS('Details local delivery'!Y:Y,'Details local delivery'!B:B,A:A) -> 0 | J87: =AVERAGEIFS('Details local delivery'!W:W,'Details local delivery'!B:B,A87) -> 1 | K87: =_xlfn.MAXIFS('Details local delivery'!Z:Z,'Details local delivery'!B:B,A87) -> 0 | L87: =_xlfn.MAXIFS('Details local delivery'!AA:AA,'Details local delivery'!B:B,A87) -> 0 | M87: =IFERROR(_xlfn.MAXIFS('Details local delivery'!AB:AB,'Details local delivery'!B:B,A87),"-") -> 0 | N87: =+F87/E87 -> 0.28571429 | O87: =+H87/G87 -> 0.20527859 | P87: =K87+L87+M87 -> 0 | Q87: =P87+I87 -> 0 | R87: =Q87/P87 -> #DIV/0! | S87: =MAX(N87,O87) -> 0.28571429
A88: VOY2026COFTN87 | B88: =+IFERROR(VLOOKUP(A88,'Details local delivery'!B:C,2,0),"-") -> 46034 | C88: =B88 -> 46034 | D88: =+IFERROR(VLOOKUP(A88,'Details local delivery'!B:E,4,0),"-") -> 9524TU238 | E88: =VLOOKUP(A88,'Details local delivery'!B:L,11,0) -> 14 | F88: =SUMIFS('Details local delivery'!M:M,'Details local delivery'!G:G,'RECAP Delivery Plan '!A88) -> 10 | G88: =VLOOKUP(A88,'Details local delivery'!B:J,9,0) -> 10230 | H88: =SUMIFS('Details local delivery'!K:K,'Details local delivery'!G:G,'RECAP Delivery Plan '!A88) -> 6000 | I88: =SUMIFS('Details local delivery'!Y:Y,'Details local delivery'!B:B,A:A) -> 0 | J88: =AVERAGEIFS('Details local delivery'!W:W,'Details local delivery'!B:B,A88) -> 1 | K88: =_xlfn.MAXIFS('Details local delivery'!Z:Z,'Details local delivery'!B:B,A88) -> 0 | L88: =_xlfn.MAXIFS('Details local delivery'!AA:AA,'Details local delivery'!B:B,A88) -> 0 | M88: =IFERROR(_xlfn.MAXIFS('Details local delivery'!AB:AB,'Details local delivery'!B:B,A88),"-") -> 0 | N88: =+F88/E88 -> 0.71428571 | O88: =+H88/G88 -> 0.58651026 | P88: =K88+L88+M88 -> 0 | Q88: =P88+I88 -> 0 | R88: =Q88/P88 -> #DIV/0! | S88: =MAX(N88,O88) -> 0.71428571
A89: VOY2026COFTN88 | B89: =+IFERROR(VLOOKUP(A89,'Details local delivery'!B:C,2,0),"-") -> 46035 | C89: =B89 -> 46035 | D89: =+IFERROR(VLOOKUP(A89,'Details local delivery'!B:E,4,0),"-") -> 2282tu131 | E89: =VLOOKUP(A89,'Details local delivery'!B:L,11,0) -> 14 | F89: =SUMIFS('Details local delivery'!M:M,'Details local delivery'!G:G,'RECAP Delivery Plan '!A89) -> 9 | G89: =VLOOKUP(A89,'Details local delivery'!B:J,9,0) -> 10200 | H89: =SUMIFS('Details local delivery'!K:K,'Details local delivery'!G:G,'RECAP Delivery Plan '!A89) -> 6681 | I89: =SUMIFS('Details local delivery'!Y:Y,'Details local delivery'!B:B,A:A) -> 0 | J89: =AVERAGEIFS('Details local delivery'!W:W,'Details local delivery'!B:B,A89) -> 1 | K89: =_xlfn.MAXIFS('Details local delivery'!Z:Z,'Details local delivery'!B:B,A89) -> 0 | L89: =_xlfn.MAXIFS('Details local delivery'!AA:AA,'Details local delivery'!B:B,A89) -> 0 | M89: =_xlfn.MAXIFS('Details local delivery'!AB:AB,'Details local delivery'!B:B,A89) -> 0 | N89: =+F89/E89 -> 0.64285714 | O89: =+H89/G89 -> 0.655 | P89: =K89+L89+M89 -> 0 | Q89: =P89+I89 -> 0 | R89: =Q89/P89 -> #DIV/0! | S89: =MAX(N89,O89) -> 0.655
A90: VOY2026COFTN89 | B90: =+IFERROR(VLOOKUP(A90,'Details local delivery'!B:C,2,0),"-") -> 46035 | C90: =B90 -> 46035 | D90: =+IFERROR(VLOOKUP(A90,'Details local delivery'!B:E,4,0),"-") -> 7797tu218 | E90: =VLOOKUP(A90,'Details local delivery'!B:L,11,0) -> 3 | F90: =SUMIFS('Details local delivery'!M:M,'Details local delivery'!G:G,'RECAP Delivery Plan '!A90) -> 2 | G90: =VLOOKUP(A90,'Details local delivery'!B:J,9,0) -> 927 | H90: =SUMIFS('Details local delivery'!K:K,'Details local delivery'!G:G,'RECAP Delivery Plan '!A90) -> 120 | I90: =SUMIFS('Details local delivery'!Y:Y,'Details local delivery'!B:B,A:A) -> 0 | J90: 1 | K90: =_xlfn.MAXIFS('Details local delivery'!Z:Z,'Details local delivery'!B:B,A90) -> 0 | L90: =_xlfn.MAXIFS('Details local delivery'!AA:AA,'Details local delivery'!B:B,A90) -> 0 | M90: =_xlfn.MAXIFS('Details local delivery'!AB:AB,'Details local delivery'!B:B,A90) -> 0 | N90: =+F90/E90 -> 0.66666667 | O90: =+H90/G90 -> 0.12944984 | P90: =K90+L90+M90 -> 0 | Q90: =P90+I90 -> 0 | R90: =Q90/P90 -> #DIV/0! | S90: =MAX(N90,O90) -> 0.66666667
A91: VOY2026COFTN90 | B91: =+IFERROR(VLOOKUP(A91,'Details local delivery'!B:C,2,0),"-") -> 46035 | C91: =B91 -> 46035 | D91: =+IFERROR(VLOOKUP(A91,'Details local delivery'!B:E,4,0),"-") -> 626tu203 | E91: =VLOOKUP(A91,'Details local delivery'!B:L,11,0) -> 14 | F91: =SUMIFS('Details local delivery'!M:M,'Details local delivery'!G:G,'RECAP Delivery Plan '!A91) -> 11 | G91: =VLOOKUP(A91,'Details local delivery'!B:J,9,0) -> 8500 | H91: =SUMIFS('Details local delivery'!K:K,'Details local delivery'!G:G,'RECAP Delivery Plan '!A91) -> 5410 | I91: =SUMIFS('Details local delivery'!Y:Y,'Details local delivery'!B:B,A:A) -> 0 | J91: =AVERAGEIFS('Details local delivery'!W:W,'Details local delivery'!B:B,A91) -> 1 | K91: =_xlfn.MAXIFS('Details local delivery'!Z:Z,'Details local delivery'!B:B,A91) -> 0 | L91: =_xlfn.MAXIFS('Details local delivery'!AA:AA,'Details local delivery'!B:B,A91) -> 0 | M91: =_xlfn.MAXIFS('Details local delivery'!AB:AB,'Details local delivery'!B:B,A91) -> 0 | N91: =+F91/E91 -> 0.78571429 | O91: =+H91/G91 -> 0.63647059 | P91: =K91+L91+M91 -> 0 | Q91: =P91+I91 -> 0 | R91: =Q91/P91 -> #DIV/0! | S91: =MAX(N91,O91) -> 0.78571429
A92: VOY2026COFTN91 | B92: =+IFERROR(VLOOKUP(A92,'Details local delivery'!B:C,2,0),"-") -> 46035 | C92: =B92 -> 46035 | D92: =+IFERROR(VLOOKUP(A92,'Details local delivery'!B:E,4,0),"-") -> 626tu203 | E92: =VLOOKUP(A92,'Details local delivery'!B:L,11,0) -> 14 | F92: =SUMIFS('Details local delivery'!M:M,'Details local delivery'!G:G,'RECAP Delivery Plan '!A92) -> 10 | G92: =VLOOKUP(A92,'Details local delivery'!B:J,9,0) -> 8500 | H92: =SUMIFS('Details local delivery'!K:K,'Details local delivery'!G:G,'RECAP Delivery Plan '!A92) -> 8500 | I92: =SUMIFS('Details local delivery'!Y:Y,'Details local delivery'!B:B,A:A) -> 0 | J92: =AVERAGEIFS('Details local delivery'!W:W,'Details local delivery'!B:B,A92) -> 1 | K92: =_xlfn.MAXIFS('Details local delivery'!Z:Z,'Details local delivery'!B:B,A92) -> 0 | L92: =_xlfn.MAXIFS('Details local delivery'!AA:AA,'Details local delivery'!B:B,A92) -> 0 | M92: =_xlfn.MAXIFS('Details local delivery'!AB:AB,'Details local delivery'!B:B,A92) -> 0 | N92: =+F92/E92 -> 0.71428571 | O92: =+H92/G92 -> 1 | P92: =K92+L92+M92 -> 0 | Q92: =P92+I92 -> 0 | R92: =Q92/P92 -> #DIV/0! | S92: =MAX(N92,O92) -> 1
A93: VOY2026COFTN92 | B93: =+IFERROR(VLOOKUP(A93,'Details local delivery'!B:C,2,0),"-") -> 46035 | C93: =B93 -> 46035 | D93: =+IFERROR(VLOOKUP(A93,'Details local delivery'!B:E,4,0),"-") -> 9524TU238 | E93: =VLOOKUP(A93,'Details local delivery'!B:L,11,0) -> 14 | F93: =SUMIFS('Details local delivery'!M:M,'Details local delivery'!G:G,'RECAP Delivery Plan '!A93) -> 11 | G93: =VLOOKUP(A93,'Details local delivery'!B:J,9,0) -> 10230 | H93: =SUMIFS('Details local delivery'!K:K,'Details local delivery'!G:G,'RECAP Delivery Plan '!A93) -> 3200 | I93: =SUMIFS('Details local delivery'!Y:Y,'Details local delivery'!B:B,A:A) -> 0 | J93: =AVERAGEIFS('Details local delivery'!W:W,'Details local delivery'!B:B,A93) -> 1 | K93: =_xlfn.MAXIFS('Details local delivery'!Z:Z,'Details local delivery'!B:B,A93) -> 0 | L93: =_xlfn.MAXIFS('Details local delivery'!AA:AA,'Details local delivery'!B:B,A93) -> 0 | M93: =_xlfn.MAXIFS('Details local delivery'!AB:AB,'Details local delivery'!B:B,A93) -> 0 | N93: =+F93/E93 -> 0.78571429 | O93: =+H93/G93 -> 0.31280547 | P93: =K93+L93+M93 -> 0 | Q93: =P93+I93 -> 0 | R93: =Q93/P93 -> #DIV/0! | S93: =MAX(N93,O93) -> 0.78571429
A94: VOY2026COFTN93 | B94: =+IFERROR(VLOOKUP(A94,'Details local delivery'!B:C,2,0),"-") -> 46035 | C94: =B94 -> 46035 | D94: =+IFERROR(VLOOKUP(A94,'Details local delivery'!B:E,4,0),"-") -> 9524TU238 | E94: =VLOOKUP(A94,'Details local delivery'!B:L,11,0) -> 14 | F94: =SUMIFS('Details local delivery'!M:M,'Details local delivery'!G:G,'RECAP Delivery Plan '!A94) -> 10 | G94: =VLOOKUP(A94,'Details local delivery'!B:J,9,0) -> 10230 | H94: =SUMIFS('Details local delivery'!K:K,'Details local delivery'!G:G,'RECAP Delivery Plan '!A94) -> 4500 | I94: =SUMIFS('Details local delivery'!Y:Y,'Details local delivery'!B:B,A:A) -> 0 | J94: =AVERAGEIFS('Details local delivery'!W:W,'Details local delivery'!B:B,A94) -> 0.85 | K94: =_xlfn.MAXIFS('Details local delivery'!Z:Z,'Details local delivery'!B:B,A94) -> 0 | L94: =_xlfn.MAXIFS('Details local delivery'!AA:AA,'Details local delivery'!B:B,A94) -> 0 | M94: =_xlfn.MAXIFS('Details local delivery'!AB:AB,'Details local delivery'!B:B,A94) -> 0 | N94: =+F94/E94 -> 0.71428571 | O94: =+H94/G94 -> 0.4398827 | P94: =K94+L94+M94 -> 0 | Q94: =P94+I94 -> 0 | R94: =Q94/P94 -> #DIV/0! | S94: =MAX(N94,O94) -> 0.71428571
A95: VOY2026COFTN94 | B95: =+IFERROR(VLOOKUP(A95,'Details local delivery'!B:C,2,0),"-") -> 46035 | C95: =B95 -> 46035 | D95: =+IFERROR(VLOOKUP(A95,'Details local delivery'!B:E,4,0),"-") -> Location | E95: =VLOOKUP(A95,'Details local delivery'!B:L,11,0) -> 0 | F95: =SUMIFS('Details local delivery'!M:M,'Details local delivery'!G:G,'RECAP Delivery Plan '!A95) -> 33 | G95: =VLOOKUP(A95,'Details local delivery'!B:J,9,0) -> 0 | H95: =SUMIFS('Details local delivery'!K:K,'Details local delivery'!G:G,'RECAP Delivery Plan '!A95) -> 0 | I95: =SUMIFS('Details local delivery'!Y:Y,'Details local delivery'!B:B,A:A) -> 0 | J95: =AVERAGEIFS('Details local delivery'!W:W,'Details local delivery'!B:B,A95) -> 1 | K95: =_xlfn.MAXIFS('Details local delivery'!Z:Z,'Details local delivery'!B:B,A95) -> 0 | L95: =_xlfn.MAXIFS('Details local delivery'!AA:AA,'Details local delivery'!B:B,A95) -> 0 | M95: =IFERROR(_xlfn.MAXIFS('Details local delivery'!AB:AB,'Details local delivery'!B:B,A95),"-") -> 0 | N95: =+F95/E95 -> #DIV/0! | O95: =+H95/G95 -> #DIV/0! | P95: =K95+L95+M95 -> 0 | Q95: =P95+I95 -> 0 | R95: =Q95/P95 -> #DIV/0! | S95: =MAX(N95,O95) -> #DIV/0!
A96: VOY2026COFTN95 | B96: =+IFERROR(VLOOKUP(A96,'Details local delivery'!B:C,2,0),"-") -> 46035 | C96: =B96 -> 46035 | D96: =+IFERROR(VLOOKUP(A96,'Details local delivery'!B:E,4,0),"-") -> 5735tu217 | E96: =VLOOKUP(A96,'Details local delivery'!B:L,11,0) -> 14 | F96: =SUMIFS('Details local delivery'!M:M,'Details local delivery'!G:G,'RECAP Delivery Plan '!A96) -> 10 | G96: =VLOOKUP(A96,'Details local delivery'!B:J,9,0) -> 10200 | H96: =SUMIFS('Details local delivery'!K:K,'Details local delivery'!G:G,'RECAP Delivery Plan '!A96) -> 7100 | I96: =SUMIFS('Details local delivery'!Y:Y,'Details local delivery'!B:B,A:A) -> 0 | J96: =AVERAGEIFS('Details local delivery'!W:W,'Details local delivery'!B:B,A96) -> 1 | K96: =_xlfn.MAXIFS('Details local delivery'!Z:Z,'Details local delivery'!B:B,A96) -> 0 | L96: =_xlfn.MAXIFS('Details local delivery'!AA:AA,'Details local delivery'!B:B,A96) -> 0 | M96: =IFERROR(_xlfn.MAXIFS('Details local delivery'!AB:AB,'Details local delivery'!B:B,A96),"-") -> 0 | N96: =+F96/E96 -> 0.71428571 | O96: =+H96/G96 -> 0.69607843 | P96: =K96+L96+M96 -> 0 | Q96: =P96+I96 -> 0 | R96: =Q96/P96 -> #DIV/0! | S96: =MAX(N96,O96) -> 0.71428571
A97: VOY2026COFTN96 | B97: =+IFERROR(VLOOKUP(A97,'Details local delivery'!B:C,2,0),"-") -> 46035 | C97: =B97 -> 46035 | D97: =+IFERROR(VLOOKUP(A97,'Details local delivery'!B:E,4,0),"-") -> 5735tu217 | E97: =VLOOKUP(A97,'Details local delivery'!B:L,11,0) -> 14 | F97: =SUMIFS('Details local delivery'!M:M,'Details local delivery'!G:G,'RECAP Delivery Plan '!A97) -> 17 | G97: =VLOOKUP(A97,'Details local delivery'!B:J,9,0) -> 10200 | H97: =SUMIFS('Details local delivery'!K:K,'Details local delivery'!G:G,'RECAP Delivery Plan '!A97) -> 7100 | I97: =SUMIFS('Details local delivery'!Y:Y,'Details local delivery'!B:B,A:A) -> 0 | J97: =AVERAGEIFS('Details local delivery'!W:W,'Details local delivery'!B:B,A97) -> 1 | K97: =_xlfn.MAXIFS('Details local delivery'!Z:Z,'Details local delivery'!B:B,A97) -> 0 | L97: =_xlfn.MAXIFS('Details local delivery'!AA:AA,'Details local delivery'!B:B,A97) -> 0 | M97: =IFERROR(_xlfn.MAXIFS('Details local delivery'!AB:AB,'Details local delivery'!B:B,A97),"-") -> 0 | N97: =+F97/E97 -> 1.2142857 | O97: =+H97/G97 -> 0.69607843 | P97: =K97+L97+M97 -> 0 | Q97: =P97+I97 -> 0 | R97: =Q97/P97 -> #DIV/0! | S97: =MAX(N97,O97) -> 1.2142857
A98: VOY2026COFTN97 | B98: =+IFERROR(VLOOKUP(A98,'Details local delivery'!B:C,2,0),"-") -> 46035 | C98: =B98 -> 46035 | D98: =+IFERROR(VLOOKUP(A98,'Details local delivery'!B:E,4,0),"-") -> 4331tu175 | E98: =VLOOKUP(A98,'Details local delivery'!B:L,11,0) -> 14 | F98: =SUMIFS('Details local delivery'!M:M,'Details local delivery'!G:G,'RECAP Delivery Plan '!A98) -> 9 | G98: =VLOOKUP(A98,'Details local delivery'!B:J,9,0) -> 9200 | H98: =SUMIFS('Details local delivery'!K:K,'Details local delivery'!G:G,'RECAP Delivery Plan '!A98) -> 6500 | I98: =SUMIFS('Details local delivery'!Y:Y,'Details local delivery'!B:B,A:A) -> 0 | J98: =AVERAGEIFS('Details local delivery'!W:W,'Details local delivery'!B:B,A98) -> 1 | K98: =_xlfn.MAXIFS('Details local delivery'!Z:Z,'Details local delivery'!B:B,A98) -> 0 | L98: =_xlfn.MAXIFS('Details local delivery'!AA:AA,'Details local delivery'!B:B,A98) -> 0 | M98: =_xlfn.MAXIFS('Details local delivery'!AB:AB,'Details local delivery'!B:B,A98) -> 0 | N98: =+F98/E98 -> 0.64285714 | O98: =+H98/G98 -> 0.70652174 | P98: =K98+L98+M98 -> 0 | Q98: =P98+I98 -> 0 | R98: =Q98/P98 -> #DIV/0! | S98: =MAX(N98,O98) -> 0.70652174
A99: VOY2026COFTN98 | B99: =+IFERROR(VLOOKUP(A99,'Details local delivery'!B:C,2,0),"-") -> 46035 | C99: =B99 -> 46035 | D99: =+IFERROR(VLOOKUP(A99,'Details local delivery'!B:E,4,0),"-") -> 4331tu175 | E99: =VLOOKUP(A99,'Details local delivery'!B:L,11,0) -> 14 | F99: =SUMIFS('Details local delivery'!M:M,'Details local delivery'!G:G,'RECAP Delivery Plan '!A99) -> 7 | G99: =VLOOKUP(A99,'Details local delivery'!B:J,9,0) -> 9200 | H99: =SUMIFS('Details local delivery'!K:K,'Details local delivery'!G:G,'RECAP Delivery Plan '!A99) -> 2075 | I99: =SUMIFS('Details local delivery'!Y:Y,'Details local delivery'!B:B,A:A) -> 0 | J99: =AVERAGEIFS('Details local delivery'!W:W,'Details local delivery'!B:B,A99) -> 1 | K99: =_xlfn.MAXIFS('Details local delivery'!Z:Z,'Details local delivery'!B:B,A99) -> 0 | L99: =_xlfn.MAXIFS('Details local delivery'!AA:AA,'Details local delivery'!B:B,A99) -> 0 | M99: =_xlfn.MAXIFS('Details local delivery'!AB:AB,'Details local delivery'!B:B,A99) -> 0 | N99: =+F99/E99 -> 0.5 | O99: =+H99/G99 -> 0.22554348 | P99: =K99+L99+M99 -> 0 | Q99: =P99+I99 -> 0 | R99: =Q99/P99 -> #DIV/0! | S99: =MAX(N99,O99) -> 0.5
A100: VOY2026COFTN99 | B100: =+IFERROR(VLOOKUP(A100,'Details local delivery'!B:C,2,0),"-") -> 46035 | C100: =B100 -> 46035 | D100: =+IFERROR(VLOOKUP(A100,'Details local delivery'!B:E,4,0),"-") -> 2282TU131 | E100: =VLOOKUP(A100,'Details local delivery'!B:L,11,0) -> 14 | F100: =SUMIFS('Details local delivery'!M:M,'Details local delivery'!G:G,'RECAP Delivery Plan '!A100) -> 5 | G100: =VLOOKUP(A100,'Details local delivery'!B:J,9,0) -> 10200 | H100: =SUMIFS('Details local delivery'!K:K,'Details local delivery'!G:G,'RECAP Delivery Plan '!A100) -> 4500 | I100: =SUMIFS('Details local delivery'!Y:Y,'Details local delivery'!B:B,A:A) -> 0 | J100: =AVERAGEIFS('Details local delivery'!W:W,'Details local delivery'!B:B,A100) -> 1 | K100: =_xlfn.MAXIFS('Details local delivery'!Z:Z,'Details local delivery'!B:B,A100) -> 0 | L100: =_xlfn.MAXIFS('Details local delivery'!AA:AA,'Details local delivery'!B:B,A100) -> 0 | M100: =IFERROR(_xlfn.MAXIFS('Details local delivery'!AB:AB,'Details local delivery'!B:B,A100),"-") -> 0 | N100: =+F100/E100 -> 0.35714286 | O100: =+H100/G100 -> 0.44117647 | P100: =K100+L100+M100 -> 0 | Q100: =P100+I100 -> 0 | R100: =Q100/P100 -> #DIV/0! | S100: =MAX(N100,O100) -> 0.44117647
...

Sheet Feuil9

Sheet Feuil10
A3: Étiquettes de lignes | B3: Nombre de N° Voyage | C3: Somme de Weight /Truck | D3: Moyenne de Loading Rate % | E3: Moyenne de Charging Rate %
A4: 2282tu131 | B4: 2 | C4: 16600 | D4: 0.35714286 | E4: 0.81372549
A5: 4331tu175 | B5: 39 | C5: 253009 | D5: 0.74358974 | E5: 0.70515329
A6: 626tu203 | B6: 44 | C6: 341692.14 | D6: 0.90584416 | E6: 0.91361535
A7: 6502TU247 | B7: 49 | C7: 304484 | D7: 0.67492711 | E7: 0.73105402
A8: 7797tu218 | B8: 34 | C8: 14535 | D8: 0.66666667 | E8: 0.46116505
A9: 9524TU238 | B9: 39 | C9: 313785.77 | D9: 0.85897436 | E9: 0.78648964
A10: REM107627 | B10: 31 | C10: 472775.31 | D10: 0.80585424 | E10: 0.61125517
A11: Total général | B11: 238 | C11: 1716881.2 | D11: 0.77223111 | E11: 0.7161797

Sheet Feuil7
A1: N° Voyage | B1: Date de Livraison | C1: Month | D1: matricule | E1: Capacite Truck Position | F1: Nbr Position Truck | G1: Max weigh t truck | H1: Weight /Truck | I1: Stationnement | J1: otd | K1: Trajet AllE(H) | L1: Trajet Retour (H) | M1: Trajet entre les clients(H) | N1: Loading Rate % | O1: Charging Rate % | P1: Total Heure Active
A2: VOY2026COFTN786 | B2: 46113 | C2: 46113 | D2: REM107627 | E2: 14 | F2: 21 | G2: 24950 | H2: 14756.3 | I2: 0 | J2: 0.94027778 | K2: 0 | L2: 0 | M2: 0 | N2: 1.5 | O2: 0.59143487 | P2: 0
A3: VOY2026COFTN788 | B3: 46113 | C3: 46113 | D3: 9524TU238 | E3: 14 | F3: 18 | G3: 10230 | H3: 4500 | I3: 0 | J3: 1 | K3: 0 | L3: 0 | M3: 0 | N3: 1.2857143 | O3: 0.4398827 | P3: 0
A4: VOY2026COFTN789 | B4: 46113 | C4: 46113 | D4: 9524TU238 | E4: 14 | F4: 12 | G4: 10230 | H4: 9700 | I4: 0 | J4: 1 | K4: 0 | L4: 0 | M4: 0 | N4: 0.85714286 | O4: 0.94819159 | P4: 0
A5: VOY2026COFTN790 | B5: 46113 | C5: 46113 | D5: 626tu203 | E5: 14 | F5: 9 | G5: 8500 | H5: 3404.7 | I5: 0 | J5: 1 | K5: 0 | L5: 0 | M5: 0 | N5: 0.64285714 | O5: 0.40055294 | P5: 0
A6: VOY2026COFTN791 | B6: 46113 | C6: 46113 | D6: 626tu203 | E6: 14 | F6: 3 | G6: 8500 | H6: 1187.44 | I6: 0 | J6: 1 | K6: 0 | L6: 0 | M6: 0 | N6: 0.21428571 | O6: 0.13969882 | P6: 0
A7: VOY2026COFTN793 | B7: 46113 | C7: 46113 | D7: 4331tu175 | E7: 14 | F7: 6 | G7: 9200 | H7: 7078 | I7: 0 | J7: 1 | K7: 0 | L7: 0 | M7: 0 | N7: 0.42857143 | O7: 0.76934783 | P7: 0
A8: VOY2026COFTN794 | B8: 46113 | C8: 46113 | D8: 6502TU247 | E8: 14 | F8: 4 | G8: 8500 | H8: 8900 | I8: 0 | J8: 1 | K8: 0 | L8: 0 | M8: 0 | N8: 0.28571429 | O8: 1.0470588 | P8: 0
A9: VOY2026COFTN795 | B9: 46113 | C9: 46113 | D9: 626tu203 | E9: 14 | F9: 7 | G9: 8500 | H9: 7651 | I9: 0 | J9: 1 | K9: 0 | L9: 0 | M9: 0 | N9: 0.5 | O9: 0.90011765 | P9: 0
A10: VOY2026COFTN796 | B10: 46113 | C10: 46113 | D10: 6502TU247 | E10: 14 | F10: 17 | G10: 8500 | H10: 6370 | I10: 0 | J10: 1 | K10: 0 | L10: 0 | M10: 0 | N10: 1.2142857 | O10: 0.74941176 | P10: 0
A11: VOY2026COFTN799 | B11: 46114 | C11: 46114 | D11: 4331tu175 | E11: 14 | F11: 8 | G11: 9200 | H11: 7500 | I11: 0 | J11: 1 | K11: 0 | L11: 0 | M11: 0 | N11: 0.57142857 | O11: 0.81521739 | P11: 0
A12: VOY2026COFTN800 | B12: 46114 | C12: 46114 | D12: 4331tu175 | E12: 14 | F12: 10 | G12: 9200 | H12: 5400 | I12: 0 | J12: 1 | K12: 0 | L12: 0 | M12: 0 | N12: 0.71428571 | O12: 0.58695652 | P12: 0
A13: VOY2026COFTN801 | B13: 46114 | C13: 46114 | D13: 626tu203 | E13: 14 | F13: 14 | G13: 8500 | H13: 9193.5 | I13: 0 | J13: 1 | K13: 0 | L13: 0 | M13: 0 | N13: 1 | O13: 1.0815882 | P13: 0
... A239: VOY2026COFTN1068 | B239: 46142 | C239: 46142 | D239: 2282tu131 | E239: 14 | F239: 6 | G239: 10200 | H239: 5600 | I239: 0 | J239: 1 | K239: 0 | L239: 0 | M239: 0 | N239: 0.42857143 | O239: 0.54901961 | P239: 0

Sheet Feuil6
A3: Étiquettes de lignes | B3: Moyenne de OTD
A4: A C T Assemblage Cable Tunisie | B4: 1
A5: AEC | B5: 1
A6: AMPHENOL TUNISIE | B6: 1
A7: Aptiv Services Tunisia SARL | B7: 0.98020833
A8: CABLISYS TUNISIE | B8: 1
A9: CMR | B9: 1
A10: COELEC TUNISIA | B10: 1
A11: COFAT KAIROUAN | B11: 1
A12: COFAT MATEUR | B12: 0.95494792
A13: COFAT TUNIS | B13: 1
A14: DIS Draxlmaier Indust Solution Gmbh | B14: 1
A15: ELECTROCONTACT TUNISIE | B15: 0.99972222
... A40: Total général | B40: 0.98501272

Sheet Feuil13

Sheet Feuil5
A1: N° Voyage | B1: Date PICK UP | C1: MOIS | D1: Matricule | E1: Chauffeur | F1: N° Voyage | G1: Delivery address | H1: Matricule | I1: Max weight truck | J1: weight | K1: Max Nbr of position truck | L1: POSITION | M1: Matricule | N1: Chauffeur | O1: ETD COF TN | P1: Real ETD COF TN | Q1: objectif ETA CLINET | R1: REAL ETA Customer | S1: Real ETD Customer | T1: ETA COFICAB | U1: real ETA COFICAB | V1: OTD
A2: VOY2026COFTN786 | B2: 46113 | C2: AVRIL | D2: REM107627 | E2: KARIM | F2: VOY2026COFTN786 | G2: LEONI Wiring Systems Tunisia SUD | H2: REM107627 | J2: 9382 | K2: 14 | L2: 7 | M2: REM107627 | N2: KARIM | O2: 0.41666667 | P2: 0.60416667 | Q2: 0.70833333 | R2: 0.68055556 | S2: 0.71527778 | T2: 0.86111111 | U2: 0.86111111 | V2: 1
A3: VOY2026COFTN786 | B3: 46113 | C3: AVRIL | D3: REM107627 | E3: KARIM | F3: VOY2026COFTN786 | G3: COFAT MATEUR | H3: REM107627 | J3: 4348.9 | K3: 14 | L3: 7 | M3: REM107627 | N3: KARIM | O3: 0.083333333 | P3: 0.60416667 | Q3: 0.75 | R3: 0.71875 | S3: 0.73611111 | T3: 0.86111111 | U3: 0.86111111 | V3: 1
A4: VOY2026COFTN786 | B4: 46113 | C4: AVRIL | D4: REM107627 | E4: KARIM | F4: VOY2026COFTN786 | G4: Yazaki Automotive Products Tunisia | H4: REM107627 | J4: 1025.4 | K4: 27 | L4: 7 | M4: REM107627 | N4: KARIM | O4: 0.20833333 | P4: 0.60416667 | Q4: 0.625 | R4: 0.77430556 | S4: 0.79166667 | T4: 0.86111111 | U4: 0.86111111 | V4: 0.82083333
A5: VOY2026COFTN787 | B5: 46113 | C5: AVRIL | D5: GTS | E5: GTS | F5: VOY2026COFTN787 | G5: YAZAKI TUNISIA s.a.r.l | H5: GTS | L5: 7 | M5: GTS | N5: GTS | O5: 0.54166667 | V5: 1
A6: VOY2026COFTN788 | B6: 46113 | C6: AVRIL | D6: 9524TU238 | E6: Ridha | F6: VOY2026COFTN788 | G6: SCHULTE AUTOMOTIVE TUNISIA srl | H6: 9524TU238 | J6: 4500 | L6: 18 | M6: 9524TU238 | N6: Ridha | O6: 0.54166667 | P6: 0.33333333 | Q6: 0.625 | R6: 0.41666667 | S6: 0.5 | T6: 0.58333333 | U6: 0.58333333 | V6: 1
A7: VOY2026COFTN789 | B7: 46113 | C7: AVRIL | D7: 9524TU238 | E7: Ridha | F7: VOY2026COFTN789 | G7: WeWire Hammamet Tunisia SARL | H7: 9524TU238 | J7: 8500 | K7: 14 | L7: 10 | M7: 9524TU238 | N7: Ridha | O7: 0.33333333 | P7: 0.64236111 | Q7: 0.75 | R7: 0.72569444 | S7: 0.75 | T7: 0.83333333 | U7: 0.83333333 | V7: 1
A8: VOY2026COFTN789 | B8: 46113 | C8: AVRIL | D8: 9524TU238 | E8: Ridha | F8: VOY2026COFTN789 | G8: Jetty | H8: 9524TU238 | J8: 1200 | K8: 14 | L8: 2 | M8: 9524TU238 | N8: Ridha | O8: 0.33333333 | P8: 0.64236111 | Q8: 0.75 | R8: 0.68055556 | S8: 0.70833333 | T8: 0.83333333 | U8: 0.83333333 | V8: 1
A9: VOY2026COFTN790 | B9: 46113 | C9: AVRIL | D9: 626tu203 | E9: hbib | F9: VOY2026COFTN790 | G9: SE BORDNETZE EL FEJJA S.A.R.L | H9: 626tu203 | J9: 3404.7 | K9: 14 | L9: 9 | M9: 626tu203 | N9: hbib | O9: 0.54166667 | P9: 0.625 | Q9: 0.75 | R9: 0.67013889 | S9: 0.69444444 | T9: 0.84375 | U9: 0.84375 | V9: 1
A10: VOY2026COFTN791 | B10: 46113 | C10: AVRIL | D10: 626tu203 | E10: hbib | F10: VOY2026COFTN791 | G10: Aptiv Services Tunisia SARL | H10: 626tu203 | J10: 1187.44 | K10: 14 | L10: 3 | M10: 626tu203 | N10: hbib | O10: 0.54166667 | P10: 0.625 | Q10: 0.75 | R10: 0.72916667 | S10: 0.75 | T10: 0.84375 | U10: 0.84375 | V10: 1
A11: VOY2026COFTN792 | B11: 46113 | C11: AVRIL | D11: location | E11: location | F11: VOY2026COFTN792 | G11: Kromberg & Schubert Tunisie SARL | H11: location | L11: 9 | M11: location | N11: location | O11: 0.25 | V11: 1
A12: VOY2026COFTN792 | B12: 46113 | C12: AVRIL | D12: location | E12: location | F12: VOY2026COFTN792 | G12: SEBN (SUMITOMO) | H12: location | L12: 12 | M12: location | N12: location | O12: 0.25 | V12: 1
A13: VOY2026COFTN793 | B13: 46113 | C13: AVRIL | D13: 4331tu175 | E13: mehrez | F13: VOY2026COFTN793 | G13: DIS Draxlmaier Indust Solution Gmbh | H13: 4331tu175 | J13: 4878 | L13: 4 | M13: 4331tu175 | N13: mehrez | O13: 0.625 | P13: 0.41666667 | Q13: 0.625 | R13: 0.54166667 | S13: 0.625 | T13: 0.83333333 | U13: 0.83333333 | V13: 1
A14: VOY2026COFTN793 | B14: 46113 | C14: AVRIL | D14: 4331tu175 | E14: mehrez | F14: VOY2026COFTN793 | G14: CMR | H14: 4331tu175 | J14: 2200 | L14: 2 | M14: 4331tu175 | N14: mehrez | O14: 0.29166667 | P14: 0.41666667 | Q14: 0.625 | R14: 0.45833333 | S14: 0.48263889 | T14: 0.83333333 | U14: 0.83333333 | V14: 1
A15: VOY2026COFTN794 | B15: 46113 | C15: AVRIL | D15: 6502TU247 | E15: ala | F15: VOY2026COFTN794 | G15: perplastic | H15: 6502TU247 | L15: 4 | M15: 6502TU247 | N15: ala | O15: 0.35416667 | P15: 0.35416667 | Q15: 0.70833333 | R15: 0.39583333 | S15: 0.41666667 | T15: 0.45833333 | U15: 0.45833333 | V15: 1
A16: VOY2026COFTN795 | B16: 46113 | C16: AVRIL | D16: 626tu203 | E16: hbib | F16: VOY2026COFTN795 | G16: COFAT TUNIS | H16: 626tu203 | J16: 7651 | L16: 7 | M16: 626tu203 | N16: hbib | O16: 0.35416667 | P16: 0.51736111 | Q16: 0.625 | R16: 0.54166667 | S16: 0.54513889 | T16: 0.54861111 | U16: 0.54861111 | V16: 1
A17: VOY2026COFTN796 | B17: 46113 | C17: AVRIL | D17: 6502TU247 | E17: ala | F17: VOY2026COFTN796 | G17: leoni sousse | H17: 626tu203 | J17: 5000 | L17: 10 | M17: 626tu203 | N17: hbib | O17: 0.29166667 | P17: 0.5625 | Q17: 0.75 | R17: 0.66666667 | S17: 0.68402778 | T17: 0.90625 | U17: 0.90625 | V17: 1
A18: VOY2026COFTN796 | B18: 46113 | C18: AVRIL | D18: 6502TU247 | E18: ala | F18: VOY2026COFTN796 | G18: METS MANUFAC ELECTRO.DE SOUSSE | H18: 626tu203 | J18: 1370 | L18: 7 | M18: 626tu203 | N18: hbib | O18: 0.29166667 | P18: 0.5625 | Q18: 0.70833333 | R18: 0.70833333 | S18: 0.76736111 | T18: 0.90625 | U18: 0.90625 | V18: 1
A19: VOY2026COFTN797 | B19: 46113 | C19: AVRIL | D19: location | E19: location | F19: VOY2026COFTN797 | G19: ELECTROCONTACT TUNISIE | H19: location | L19: 14 | M19: location | N19: location | O19: 0.29166667 | V19: 1
A20: VOY2026COFTN797 | B20: 46113 | C20: AVRIL | D20: location | E20: location | F20: VOY2026COFTN797 | G20: CABLISYS TUNISIE | H20: location | L20: 1 | M20: location | N20: location | V20: 1
A21: VOY2026COFTN797 | B21: 46113 | C21: AVRIL | D21: location | E21: location | F21: VOY2026COFTN797 | G21: SEWS TN SARL | H21: location | L21: 12 | M21: location | N21: location | V21: 1
A22: VOY2026COFTN798 | B22: 46114 | C22: AVRIL | D22: GTS | E22: GTS | F22: VOY2026COFTN798 | G22: A C T Assemblage Cable Tunisie | H22: GTS | L22: 2 | M22: GTS | N22: GTS | O22: 0.29166667 | V22: 1
A23: VOY2026COFTN799 | B23: 46114 | C23: AVRIL | D23: 4331tu175 | E23: mehrez | F23: VOY2026COFTN799 | G23: I.C.eM | H23: 4331tu175 | J23: 7500 | L23: 8 | M23: 4331tu175 | N23: mehrez | O23: 0.45833333 | P23: 0.54166667 | Q23: 0.625 | R23: 0.56944444 | S23: 0.625 | T23: 0.68055556 | U23: 0.68055556 | V23: 1
A24: VOY2026COFTN800 | B24: 46114 | C24: AVRIL | D24: 4331tu175 | E24: mehrez | F24: VOY2026COFTN800 | G24: TTE International | H24: 4331tu175 | J24: 900 | L24: 3 | M24: 4331tu175 | N24: mehrez | O24: 0.625 | P24: 0.70833333 | Q24: 0.83333333 | R24: 0.79166667 | S24: 0.80555556 | T24: 0.90625 | U24: 0.90625 | V24: 1
A25: VOY2026COFTN800 | B25: 46114 | C25: AVRIL | D25: 4331tu175 | E25: mehrez | F25: VOY2026COFTN800 | G25: Yazaki Automotive Products Tunisia | H25: 4331tu175 | J25: 4500 | L25: 7 | M25: 4331tu175 | N25: mehrez | O25: 0.625 | P25: 0.70833333 | Q25: 0.83333333 | R25: 0.79375 | S25: 0.83333333 | T25: 0.90625 | U25: 0.90625 | V25: 1
A26: VOY2026COFTN801 | B26: 46114 | C26: AVRIL | D26: 626tu203 | E26: Hbib | F26: VOY2026COFTN801 | G26: leoni sousse | H26: 626tu203 | J26: 9193.5 | L26: 14 | M26: 626tu203 | N26: Hbib | O26: 0.45833333 | P26: 0.57638889 | Q26: 0.75 | R26: 0.70138889 | S26: 0.72916667 | T26: 0.875 | U26: 0.875 | V26: 1
A27: VOY2026COFTN802 | B27: 46114 | C27: AVRIL | D27: 7797tu218 | E27: Houssem | F27: VOY2026COFTN802 | G27: KAB-LEM Tunisia SARL | H27: 7797tu218 | J27: 1049 | L27: 2 | M27: 7797tu218 | N27: Houssem | O27: 0.41666667 | P27: 0.54861111 | Q27: 0.625 | R27: 0.59375 | S27: 0.64930556 | T27: 0.69791667 | U27: 0.69791667 | V27: 1
A28: VOY2026COFTN803 | B28: 46114 | C28: AVRIL | D28: REM107627 | E28: KARIM | F28: VOY2026COFTN803 | G28: YURA CORPORATION TUNISIA | H28: REM107627 | J28: 12300 | L28: 24 | M28: REM107627 | N28: KARIM | O28: 0.41666667 | P28: 0.50694444 | Q28: 0.625 | R28: 0.625 | S28: 0.68055556 | T28: 0.83333333 | U28: 0.83333333 | V28: 1
A29: VOY2026COFTN804 | B29: 46114 | C29: AVRIL | D29: location | E29: location | F29: VOY2026COFTN804 | G29: SCHULTE AUTOMOTIVE TUNISIA srl | H29: location | J29: 11000 | L29: 19 | M29: location | N29: location | O29: 0.41666667 | V29: 1
A30: VOY2026COFTN805 | B30: 46114 | C30: AVRIL | D30: 9524TU238 | E30: RIDHA | F30: VOY2026COFTN805 | G30: AMPHENOL TUNISIE | H30: 9524TU238 | J30: 4600 | L30: 17 | M30: 9524TU238 | N30: RIDHA | O30: 0.41666667 | P30: 0.5 | Q30: 0.625 | R30: 0.54166667 | S30: 0.58333333 | T30: 0.64583333 | U30: 0.64583333 | V30: 1
A31: VOY2026COFTN806 | B31: 46114 | C31: AVRIL | D31: 9524TU238 | E31: RIDHA | F31: VOY2026COFTN806 | G31: perplastic | H31: 9524TU238 | J31: 8000 | L31: 10 | M31: 9524TU238 | N31: RIDHA | O31: 0.66666667 | P31: 0.66666667 | Q31: 0.70833333 | R31: 0.6875 | S31: 0.70833333 | T31: 0.72916667 | U31: 0.72916667 | V31: 1
A32: VOY2026COFTN807 | B32: 46114 | C32: AVRIL | D32: location | E32: location | F32: VOY2026COFTN807 | G32: COFAT MATEUR | H32: location | J32: 5000 | L32: 9 | M32: location | N32: location | O32: 0.29166667 | V32: 1
A33: VOY2026COFTN807 | B33: 46114 | C33: AVRIL | D33: location | E33: location | F33: VOY2026COFTN807 | G33: LEONI Wiring Systems Tunisia NORD | H33: location | J33: 7000 | L33: 11 | M33: location | N33: location | O33: 0.29166667 | V33: 1
A34: VOY2026COFTN807 | B34: 46114 | C34: AVRIL | D34: location | E34: location | F34: VOY2026COFTN807 | G34: LEONI Wiring Systems Tunisia SUD | H34: location | J34: 177 | L34: 13 | M34: location | N34: location | O34: 0.29166667 | V34: 1
A35: VOY2026COFTN808 | B35: 46114 | C35: AVRIL | D35: 6502TU247 | E35: ala | F35: VOY2026COFTN808 | G35: COFAT TUNIS | H35: 6502TU247 | J35: 2400 | L35: 7 | M35: 6502TU247 | N35: ala | O35: 0.41666667 | P35: 0.5 | Q35: 0.625 | R35: 0.50347222 | S35: 0.54166667 | T35: 0.5625 | U35: 0.5625 | V35: 1
A36: VOY2026COFTN809 | B36: 46114 | C36: AVRIL | D36: 6502TU247 | E36: ala | F36: VOY2026COFTN809 | G36: Aptiv Services Tunisia SARL | H36: 6502TU247 | J36: 10000 | L36: 12 | M36: 6502TU247 | N36: ala | O36: 0.45833333 | P36: 0.84722222 | Q36: 0.91666667 | R36: 0.88888889 | S36: 0.90625 | T36: 0.94444444 | U36: 0.94444444 | V36: 1
A37: VOY2026COFTN810 | B37: 46114 | C37: AVRIL | D37: 6502TU247 | E37: ala | F37: VOY2026COFTN810 | G37: perplastic | H37: 6502TU247 | J37: 12000 | L37: 10 | M37: 6502TU247 | N37: ala | O37: 0.63194444 | P37: 0.63194444 | Q37: 0.70833333 | R37: 0.64583333 | S37: 0.79166667 | T37: 0.80555556 | U37: 0.80555556 | V37: 1
A38: VOY2026COFTN811 | B38: 46114 | C38: AVRIL | D38: 7797tu218 | E38: Houssem | F38: VOY2026COFTN811 | G38: COFAT MATEUR | H38: 7797tu218 | J38: 200 | L38: 1 | M38: 7797tu218 | N38: Houssem | O38: 0.72916667 | P38: 0.72916667 | Q38: 0.5 | R38: 0.78819444 | S38: 0.8125 | T38: 0.85416667 | U38: 0.85416667 | V38: 0.65416667
A39: VOY2026COFTN812 | B39: 46114 | C39: AVRIL | D39: 7797tu218 | E39: RIDHA | F39: VOY2026COFTN812 | G39: Aptiv Services Tunisia SARL | H39: 7797tu218 | J39: 120 | L39: 1 | M39: 7797tu218 | N39: Houssem | O39: 0.75 | P39: 0.75 | Q39: 0.83333333 | R39: 0.79861111 | S39: 0.83333333 | T39: 0.89583333 | U39: 0.89583333 | V39: 1
A40: VOY2026COFTN813 | B40: 46115 | C40: AVRIL | D40: 9524TU238 | E40: RIDHA | F40: VOY2026COFTN813 | G40: COFAT TUNIS | H40: 9524TU238 | J40: 8500 | L40: 4 | M40: 9524TU238 | N40: RIDHA | O40: 0.29166667 | P40: 0.29166667 | Q40: 0.5 | R40: 0.29513889 | S40: 0.33333333 | T40: 0.33680556 | U40: 0.33680556 | V40: 1
A41: VOY2026COFTN814 | B41: 46115 | C41: AVRIL | D41: 9524TU238 | E41: RIDHA | F41: VOY2026COFTN814 | G41: LEONI Wiring Systems Tunisia SUD | H41: 9524TU238 | J41: 5320 | L41: 14 | M41: 9524TU238 | N41: RIDHA | O41: 0.35416667 | P41: 0.38888889 | Q41: 0.625 | R41: 0.45138889 | S41: 0.47916667 | T41: 0.625 | U41: 0.625 | V41: 1
A42: VOY2026COFTN815 | B42: 46115 | C42: AVRIL | D42: 6502TU247 | E42: ala | F42: VOY2026COFTN815 | G42: ERA CONTACTS TUNISIA | H42: 6502TU247 | J42: 320 | L42: 1 | M42: 6502TU247 | N42: ala | O42: 0.29166667 | P42: 0.38888889 | Q42: 0.625 | R42: 0.5 | S42: 0.52083333 | T42: 0.625 | U42: 0.625 | V42: 1
A43: VOY2026COFTN815 | B43: 46115 | C43: AVRIL | D43: 6502TU247 | E43: ala | F43: VOY2026COFTN815 | G43: COFAT MATEUR | H43: 6502TU247 | J43: 7300 | L43: 9 | M43: 6502TU247 | N43: ala | O43: 0.29166667 | P43: 0.41666667 | Q43: 0.625 | R43: 0.48958333 | S43: 0.53472222 | T43: 0.64236111 | U43: 0.64236111 | V43: 1
A44: VOY2026COFTN816 | B44: 46115 | C44: AVRIL | D44: 6502TU247 | E44: ala | F44: VOY2026COFTN816 | G44: WeWire Hammamet Tunisia SARL | H44: 6502TU247 | J44: 4550 | L44: 6 | M44: 6502TU247 | N44: ala | O44: 0.58333333 | P44: 0.66666667 | Q44: 0.75 | R44: 0.72222222 | S44: 0.75 | T44: 0.79861111 | U44: 0.79861111 | V44: 1
A45: VOY2026COFTN817 | B45: 46115 | C45: AVRIL | D45: REM107627 | E45: KARIM | F45: VOY2026COFTN817 | G45: leoni sousse | H45: REM107627 | J45: 8500 | L45: 10 | M45: REM107627 | N45: KARIM | O45: 0.25 | P45: 0.39583333 | Q45: 0.75 | R45: 0.58333333 | S45: 0.625 | T45: 0.94097222 | U45: 0.94097222 | V45: 1
A46: VOY2026COFTN817 | B46: 46115 | C46: AVRIL | D46: REM107627 | E46: KARIM | F46: VOY2026COFTN817 | G46: ELECTROCONTACT TUNISIE | H46: REM107627 | J46: 13822 | L46: 18 | M46: REM107627 | N46: KARIM | O46: 0.25 | P46: 0.39583333 | Q46: 0.75 | R46: 0.66666667 | S46: 0.75 | T46: 0.94097222 | U46: 0.94097222 | V46: 1
A47: VOY2026COFTN818 | B47: 46115 | C47: AVRIL | D47: GTS | E47: GTS | F47: VOY2026COFTN818 | G47: YAZAKI TUNISIA s.a.r.l | H47: GTS | L47: 1 | M47: GTS | N47: GTS | O47: 0.41666667 | V47: 1
A48: VOY2026COFTN819 | B48: 46115 | C48: AVRIL | D48: 626tu203 | E48: Hbib | F48: VOY2026COFTN819 | G48: YURA CORPORATION TUNISIA | H48: 626tu203 | J48: 1000 | L48: 1 | M48: 626tu203 | N48: Hbib | O48: 0.33333333 | P48: 0.43402778 | Q48: 0.75 | R48: 0.65277778 | S48: 0.65277778 | T48: 0.94791667 | U48: 0.94791667 | V48: 1
A49: VOY2026COFTN819 | B49: 46115 | C49: AVRIL | D49: 626tu203 | E49: Hbib | F49: VOY2026COFTN819 | G49: COFAT KAIROUAN | H49: 626tu203 | J49: 287.8 | L49: 1 | M49: 626tu203 | N49: Hbib | O49: 0.33333333 | P49: 0.43402778 | Q49: 0.75 | R49: 0.65277778 | S49: 0.65277778 | T49: 0.94791667 | U49: 0.94791667 | V49: 1
A50: VOY2026COFTN819 | B50: 46115 | C50: AVRIL | D50: 626tu203 | E50: Hbib | F50: VOY2026COFTN819 | G50: MEDITERRANEAN ELECTRIC WIRING | H50: 626tu203 | J50: 173.7 | L50: 1 | M50: 626tu203 | N50: Hbib | O50: 0.33333333 | P50: 0.43402778 | Q50: 0.625 | R50: 0.59375 | S50: 0.61458333 | T50: 0.94791667 | U50: 0.94791667 | V50: 1
A51: VOY2026COFTN819 | B51: 46115 | C51: AVRIL | D51: 626tu203 | E51: Hbib | F51: VOY2026COFTN819 | G51: SCHULTE AUTOMOTIVE TUNISIA srl | H51: 626tu203 | J51: 2494 | L51: 14 | M51: 626tu203 | N51: Hbib | O51: 0.33333333 | P51: 0.43402778 | Q51: 0.625 | R51: 0.52083333 | S51: 0.54861111 | T51: 0.94791667 | U51: 0.94791667 | V51: 1
A52: VOY2026COFTN820 | B52: 46115 | C52: AVRIL | D52: 4331tu175 | E52: mehrez | F52: VOY2026COFTN820 | G52: Aptiv Services Tunisia SARL | H52: 4331tu175 | J52: 200 | L52: 2 | M52: 4331tu175 | N52: mehrez | O52: 0.33333333 | P52: 0.41666667 | Q52: 0.625 | R52: 0.46527778 | S52: 0.47916667 | T52: 0.70833333 | U52: 0.70833333 | V52: 1
A53: VOY2026COFTN821 | B53: 46115 | C53: AVRIL | D53: 4331tu175 | E53: mehrez | F53: VOY2026COFTN821 | G53: SEBN (SUMITOMO) | H53: 4331tu175 | J53: 1000 | L53: 4 | M53: 4331tu175 | N53: mehrez | O53: 0.33333333 | P53: 0.41666667 | Q53: 0.625 | R53: 0.54166667 | S53: 0.58333333 | T53: 0.70833333 | U53: 0.70833333 | V53: 1
A54: VOY2026COFTN822 | B54: 46116 | C54: AVRIL | D54: REM107627 | E54: ala | F54: VOY2026COFTN822 | G54: LEONI Wiring Systems Tunisia SUD | H54: REM107627 | J54: 7123 | L54: 10 | M54: REM107627 | N54: ala | O54: 0.41666667 | P54: 0.54166667 | Q54: 0.75 | R54: 0.67361111 | S54: 0.72222222 | T54: 0.81944444 | U54: 0.81944444 | V54: 1
A55: VOY2026COFTN822 | B55: 46116 | C55: AVRIL | D55: REM107627 | E55: ala | F55: VOY2026COFTN822 | G55: COFAT MATEUR | H55: REM107627 | J55: 9100 | L55: 10 | M55: REM107627 | N55: ala | O55: 0.41666667 | P55: 0.54166667 | Q55: 0.75 | R55: 0.63888889 | S55: 0.66666667 | T55: 0.81944444 | U55: 0.81944444 | V55: 1
A56: VOY2026COFTN823 | B56: 46116 | C56: AVRIL | D56: 6502TU247 | E56: Hbib | F56: VOY2026COFTN823 | G56: COFAT TUNIS | H56: 6502TU247 | J56: 12123 | L56: 14 | M56: 6502TU247 | N56: KARIM | O56: 0.29166667 | P56: 0.51041667 | Q56: 0.75 | R56: 0.50694444 | S56: 0.5625 | T56: 0.58333333 | U56: 0.58333333 | V56: 1
A57: VOY2026COFTN824 | B57: 46116 | C57: AVRIL | D57: 6502TU247 | E57: KARIM | F57: VOY2026COFTN824 | G57: leoni sousse | H57: 6502TU247 | L57: 10 | M57: 6502TU247 | N57: KARIM | O57: 0.375 | V57: 1
A58: VOY2026COFTN825 | B58: 46116 | C58: AVRIL | D58: 626tu203 | E58: hbib | F58: VOY2026COFTN825 | G58: perplastic | H58: 626tu203 | J58: 11820 | L58: 10 | M58: 626tu203 | N58: hbib | O58: 0.33333333 | P58: 0.38541667 | Q58: 0.70833333 | R58: 0.39930556 | S58: 0.4375 | T58: 0.45138889 | U58: 0.45138889 | V58: 1
A59: VOY2026COFTN826 | B59: 46116 | C59: AVRIL | D59: 626tu203 | E59: hbib | F59: VOY2026COFTN826 | G59: perplastic | H59: 626tu203 | J59: 11890 | L59: 10 | M59: 626tu203 | N59: hbib | O59: 0.41666667 | P59: 0.51041667 | Q59: 0.70833333 | R59: 0.54166667 | S59: 0.54444444 | T59: 0.58333333 | U59: 0.58333333 | V59: 1
A60: VOY2026COFTN827 | B60: 46116 | C60: AVRIL | D60: 4331tu175 | E60: mehrez | F60: VOY2026COFTN827 | G60: Aptiv Services Tunisia SARL | H60: 4331tu175 | J60: 230 | L60: 4 | M60: 4331tu175 | N60: mehrez | O60: 0.41666667 | P60: 0.50694444 | Q60: 0.625 | R60: 0.5625 | S60: 0.58333333 | T60: 0.64583333 | U60: 0.64583333 | V60: 1
A61: VOY2026COFTN828 | B61: 46118 | C61: AVRIL | D61: 9524TU238 | E61: Ridha | F61: VOY2026COFTN828 | G61: Yazaki Automotive Products Tunisia | H61: 9524TU238 | J61: 4200 | L61: 10 | M61: 9524TU238 | N61: Ridha | O61: 0.29166667 | V61: 1
A62: VOY2026COFTN828 | B62: 46118 | C62: AVRIL | D62: 9524TU238 | E62: Ridha | F62: VOY2026COFTN828 | G62: TTE International | H62: 9524TU238 | J62: 6690 | L62: 8 | M62: 9524TU238 | N62: Ridha | O62: 0.29166667 | P62: 0.375 | Q62: 0.625 | R62: 0.44791667 | S62: 0.45833333 | T62: 0.58333333 | U62: 0.58333333 | V62: 1
A63: VOY2026COFTN828 | B63: 46118 | C63: AVRIL | D63: 9524TU238 | E63: Ridha | F63: VOY2026COFTN828 | G63: KAB-LEM Tunisia SARL | H63: 9524TU238 | J63: 936 | L63: 6 | M63: 9524TU238 | N63: Ridha | O63: 0.29166667 | P63: 0.375 | Q63: 0.625 | R63: 0.43055556 | S63: 0.45833333 | T63: 0.58333333 | U63: 0.58333333 | V63: 1
A64: VOY2026COFTN829 | B64: 46118 | C64: AVRIL | D64: 626tu203 | E64: hbib | F64: VOY2026COFTN829 | G64: COFAT TUNIS | H64: 626tu203 | J64: 4200 | L64: 8 | M64: 626tu203 | N64: hbib | O64: 0.33333333 | P64: 0.33333333 | Q64: 0.5 | R64: 0.33680556 | S64: 0.375 | T64: 0.37847222 | U64: 0.37847222 | V64: 1
A65: VOY2026COFTN830 | B65: 46118 | C65: AVRIL | D65: 626tu203 | E65: hbib | F65: VOY2026COFTN830 | G65: A C T Assemblage Cable Tunisie | H65: 626tu203 | J65: 2128 | L65: 4 | M65: 626tu203 | N65: hbib | O65: 0.41666667 | P65: 0.42361111 | Q65: 0.625 | R65: 0.46527778 | S65: 0.48263889 | T65: 0.71180556 | U65: 0.71180556 | V65: 1
A66: VOY2026COFTN830 | B66: 46118 | C66: AVRIL | D66: 626tu203 | E66: hbib | F66: VOY2026COFTN830 | G66: WeWire Hammamet Tunisia SARL | H66: 626tu203 | J66: 12000 | L66: 12 | M66: 626tu203 | N66: hbib | O66: 0.41666667 | P66: 0.5625 | Q66: 0.625 | R66: 0.60763889 | S66: 0.76041667 | T66: 0.83333333 | U66: 0.83333333 | V66: 1
A67: VOY2026COFTN831 | B67: 46118 | C67: AVRIL | D67: 6502TU247 | E67: Houssem | F67: VOY2026COFTN831 | G67: WeWire Hammamet Tunisia SARL | H67: 6502TU247 | J67: 23000 | L67: 12 | M67: 6502TU247 | N67: Houssem | O67: 0.41666667 | P67: 0.45833333 | Q67: 0.625 | R67: 0.54166667 | S67: 0.625 | T67: 0.70833333 | U67: 0.70833333 | V67: 1
A68: VOY2026COFTN832 | B68: 46118 | C68: AVRIL | D68: REM107627 | E68: ala | F68: VOY2026COFTN832 | G68: LEONI Wiring Systems Tunisia SUD | H68: REM107627 | J68: 1027 | L68: 6 | M68: REM107627 | N68: ala | O68: 0.29166667 | P68: 0.375 | Q68: 0.5 | R68: 0.47916667 | S68: 0.50694444 | T68: 0.75 | U68: 0.75 | V68: 1
A69: VOY2026COFTN832 | B69: 46118 | C69: AVRIL | D69: REM107627 | E69: ala | F69: VOY2026COFTN832 | G69: LEONI Wiring Systems Tunisia NORD | H69: REM107627 | J69: 6200 | L69: 12 | M69: REM107627 | N69: ala | O69: 0.33333333 | P69: 0.375 | Q69: 0.5 | R69: 0.4375 | S69: 0.66666667 | T69: 0.75 | U69: 0.75 | V69: 1
A70: VOY2026COFTN832 | B70: 46118 | C70: AVRIL | D70: REM107627 | E70: ala | F70: VOY2026COFTN832 | G70: COFAT MATEUR | H70: REM107627 | J70: 4300 | L70: 7 | M70: REM107627 | N70: ala | O70: 0.375 | P70: 0.375 | Q70: 0.5 | R70: 0.5 | S70: 0.54861111 | T70: 0.75 | U70: 0.75 | V70: 1
A71: VOY2026COFTN833 | B71: 46118 | C71: AVRIL | D71: 6502TU247 | E71: Houssem | F71: VOY2026COFTN833 | G71: perplastic | H71: 6502TU247 | J71: 1000 | L71: 5 | M71: 6502TU247 | N71: Houssem | O71: 0.33333333 | P71: 0.375 | Q71: 0.70833333 | R71: 0.39583333 | S71: 0.47916667 | T71: 0.50347222 | U71: 0.50347222 | V71: 1
A72: VOY2026COFTN834 | B72: 46118 | C72: AVRIL | D72: location | E72: location | F72: VOY2026COFTN834 | G72: ELECTROCONTACT TUNISIE | H72: location | J72: 22303 | L72: 27 | M72: location | N72: location | O72: 0.29166667 | V72: 1
A73: VOY2026COFTN834 | B73: 46118 | C73: AVRIL | D73: location | E73: location | F73: VOY2026COFTN834 | G73: leoni sousse | H73: location | J73: 2330 | L73: 6 | M73: location | N73: location | O73: 0.29166667 | V73: 1
A74: VOY2026COFTN835 | B74: 46118 | C74: AVRIL | D74: 4331tu175 | E74: mehrez | F74: VOY2026COFTN835 | G74: SCHULTE AUTOMOTIVE TUNISIA srl | H74: 4331tu175 | J74: 4500 | L74: 5 | M74: 4331tu175 | N74: mehrez | O74: 0.29166667 | P74: 0.29166667 | Q74: 0.625 | R74: 0.375 | S74: 0.41666667 | T74: 0.5 | U74: 0.5 | V74: 1
A75: VOY2026COFTN836 | B75: 46118 | C75: AVRIL | D75: 4331TU175 | E75: mehrez | F75: VOY2026COFTN836 | G75: Aptiv Services Tunisia SARL | H75: 4331TU175 | J75: 8300 | L75: 14 | M75: 4331TU175 | N75: mehrez | O75: 0.58333333 | P75: 0.63888889 | Q75: 0.70833333 | R75: 0.68402778 | S75: 0.75 | T75: 0.80902778 | U75: 0.9375 | V75: 1
A76: VOY2026COFTN837 | B76: 46118 | C76: AVRIL | D76: 7797tu218 | E76: Ridha | F76: VOY2026COFTN837 | G76: LEONI Wiring Systems Tunisia SUD | H76: 7797tu218 | J76: 900 | L76: 2 | M76: 7797tu218 | N76: Ridha | O76: 0.75 | P76: 0.79166667 | Q76: 0.5 | R76: 0.85416667 | S76: 0.875 | T76: 0.9375 | U76: 0.9375 | V76: 0.575
A77: VOY2026COFTN838 | B77: 46118 | C77: AVRIL | D77: GTS | E77: GTS | F77: VOY2026COFTN838 | G77: COFAT MATEUR | H77: GTS | J77: 200 | L77: 1 | M77: GTS | N77: GTS | O77: 0.875 | P77: 0.91666667 | Q77: 0.5 | R77: 0.97916667 | V77: 0.425
A78: VOY2026COFTN839 | B78: 46119 | C78: AVRIL | D78: REM107627 | E78: KARIM | F78: VOY2026COFTN839 | G78: perplastic | H78: REM107627 | J78: 12657.77 | L78: 12 | M78: REM107627 | N78: KARIM | O78: 0.29166667 | P78: 0.29166667 | Q78: 0.70833333 | R78: 0.33333333 | S78: 0.375 | T78: 0.41666667 | U78: 0.41666667 | V78: 1
A79: VOY2026COFTN840 | B79: 46119 | C79: AVRIL | D79: REM107627 | E79: KARIM | F79: VOY2026COFTN840 | G79: LEONI Wiring Systems Tunisia SUD | H79: REM107627 | J79: 12657.77 | L79: 12 | M79: REM107627 | N79: KARIM | O79: 0.41666667 | P79: 0.50347222 | Q79: 0.625 | R79: 0.57638889 | S79: 0.58333333 | T79: 0.83333333 | U79: 0.83333333 | V79: 1
A80: VOY2026COFTN840 | B80: 46119 | C80: AVRIL | D80: REM107627 | E80: KARIM | F80: VOY2026COFTN840 | G80: LEONI Wiring Systems Tunisia NORD | H80: REM107627 | J80: 10561 | L80: 12 | M80: REM107627 | N80: KARIM | O80: 0.41666667 | P80: 0.50347222 | Q80: 0.625 | R80: 0.56944444 | S80: 0.64583333 | T80: 0.83333333 | U80: 0.83333333 | V80: 1
A81: VOY2026COFTN840 | B81: 46119 | C81: AVRIL | D81: REM107627 | E81: KARIM | F81: VOY2026COFTN840 | G81: COFAT MATEUR | H81: REM107627 | J81: 10000 | L81: 15 | M81: REM107627 | N81: KARIM | O81: 0.41666667 | P81: 0.50347222 | Q81: 0.625 | R81: 0.625 | S81: 0.76041667 | T81: 0.83333333 | U81: 0.83333333 | V81: 1
A82: VOY2026COFTN841 | B82: 46119 | C82: AVRIL | D82: 4331tu175 | E82: mehrez | F82: VOY2026COFTN841 | G82: DIS Draxlmaier Indust Solution Gmbh | H82: 4331tu175 | J82: 3240 | L82: 4 | M82: 4331tu175 | N82: mehrez | O82: 0.25 | P82: 0.27083333 | Q82: 0.625 | R82: 0.375 | S82: 0.45833333 | T82: 0.58333333 | U82: 0.58333333 | V82: 1
A83: VOY2026COFTN841 | B83: 46119 | C83: AVRIL | D83: 4331tu175 | E83: mehrez | F83: VOY2026COFTN841 | G83: Aptiv Services Tunisia SARL | H83: 4331tu175 | J83: 5750 | L83: 14 | M83: 4331tu175 | N83: mehrez | O83: 0.58333333 | P83: 0.65277778 | Q83: 0.75 | R83: 0.70833333 | S83: 0.76388889 | T83: 0.83333333 | U83: 0.83333333 | V83: 1
A84: VOY2026COFTN842 | B84: 46119 | C84: AVRIL | D84: 6502TU247 | E84: ala | F84: VOY2026COFTN842 | G84: LECTRIC | H84: 6502TU247 | J84: 600 | L84: 1 | M84: 6502TU247 | N84: ala | O84: 0.25 | P84: 3.3472222 | Q84: 0.625 | R84: 0.47916667 | S84: 0.54166667 | T84: 0.58333333 | U84: 0.58333333 | V84: 1
A85: VOY2026COFTN842 | B85: 46119 | C85: AVRIL | D85: 6502TU247 | E85: ala | F85: VOY2026COFTN842 | G85: SCHULTE Zaghouane | H85: 6502TU247 | J85: 6770 | L85: 10 | M85: 6502TU247 | N85: ala | O85: 0.25 | P85: 0.34722222 | Q85: 0.625 | R85: 0.39583333 | S85: 0.44791667 | T85: 0.58333333 | U85: 0.58333333 | V85: 1
A86: VOY2026COFTN843 | B86: 46119 | C86: AVRIL | D86: 6502TU247 | E86: ala | F86: VOY2026COFTN843 | G86: PERPLastic SILICONE | H86: 6502TU247 | J86: 640 | L86: 4 | M86: 6502TU247 | N86: ala | O86: 0.41666667 | P86: 0.54166667 | Q86: 0.75 | R86: 0.55555556 | S86: 0.59722222 | T86: 0.61111111 | U86: 0.61111111 | V86: 1
A87: VOY2026COFTN844 | B87: 46119 | C87: AVRIL | D87: 6502TU247 | E87: ala | F87: VOY2026COFTN844 | G87: WeWire Hammamet Tunisia SARL | H87: 6502TU247 | J87: 11000 | L87: 14 | M87: 6502TU247 | N87: ala | O87: 0.58333333 | P87: 0.74305556 | Q87: 0.83333333 | R87: 0.80208333 | S87: 0.83333333 | T87: 0.87847222 | U87: 0.87847222 | V87: 1
A88: VOY2026COFTN845 | B88: 46119 | C88: AVRIL | D88: location | E88: location | F88: VOY2026COFTN845 | G88: Kromberg & Schubert Tunisie SARL | H88: location | J88: 13.222 | L88: 31 | M88: location | N88: location | O88: 0.29166667 | V88: 1
A89: VOY2026COFTN845 | B89: 46119 | C89: AVRIL | D89: location | E89: location | F89: VOY2026COFTN845 | G89: SE BORDNETZE EL FEJJA S.A.R.L | H89: location | L89: 6 | M89: location | N89: location | O89: 0.29166667 | V89: 1
A90: VOY2026COFTN846 | B90: 46119 | C90: AVRIL | D90: 7797tu218 | E90: Houssem | F90: VOY2026COFTN846 | G90: MEDITERRANEAN ELECTRIC WIRING | H90: 7797tu218 | J90: 3000 | L90: 4 | M90: 7797tu218 | N90: Houssem | O90: 0.29166667 | P90: 0.33680556 | Q90: 0.625 | R90: 0.40625 | S90: 0.44097222 | T90: 0.51041667 | U90: 0.51041667 | V90: 1
A91: VOY2026COFTN846 | B91: 46119 | C91: AVRIL | D91: 7797tu218 | E91: Houssem | F91: VOY2026COFTN846 | G91: COELEC TUNISIA | H91: 7797tu218 | J91: 900 | L91: 4 | M91: 7797tu218 | N91: Houssem | O91: 0.5 | P91: 0.5625 | Q91: 0.625 | R91: 0.59027778 | S91: 0.60416667 | T91: 0.65625 | U91: 0.65625 | V91: 1
A92: VOY2026COFTN847 | B92: 46119 | C92: AVRIL | D92: 9524TU238 | E92: Ridha | F92: VOY2026COFTN847 | G92: COFAT TUNIS | H92: 9524TU238 | J92: 12000 | L92: 13 | M92: 9524TU238 | N92: Ridha | O92: 0.33333333 | P92: 0.33333333 | Q92: 0.5 | R92: 0.33680556 | S92: 0.34027778 | T92: 0.34375 | U92: 0.34375 | V92: 1
A93: VOY2026COFTN848 | B93: 46119 | C93: AVRIL | D93: 9524TU238 | E93: Ridha | F93: VOY2026COFTN848 | G93: leoni sousse | H93: 9524TU238 | J93: 4000 | L93: 10 | M93: 9524TU238 | N93: Ridha | O93: 0.41666667 | P93: 0.45833333 | Q93: 0.625 | R93: 0.55555556 | S93: 0.625 | T93: 0.83333333 | U93: 0.83333333 | V93: 1
A94: VOY2026COFTN848 | B94: 46119 | C94: AVRIL | D94: 9524TU238 | E94: Ridha | F94: VOY2026COFTN848 | G94: COFAT KAIROUAN | H94: 9524TU238 | J94: 2300 | L94: 3 | M94: 9524TU238 | N94: Ridha | O94: 0.41666667 | P94: 0.45833333 | Q94: 0.625 | R94: 0.625 | S94: 0.66666667 | T94: 0.83333333 | U94: 0.83333333 | V94: 1
A95: VOY2026COFTN849 | B95: 46119 | C95: AVRIL | D95: 626tu203 | E95: hbib | F95: VOY2026COFTN849 | G95: SCHULTE AUTOMOTIVE TUNISIA srl | H95: 626tu203 | J95: 11200 | L95: 19 | M95: 626tu203 | N95: hbib | O95: 0.20833333 | P95: 0.20833333 | Q95: 0.625 | R95: 0.33333333 | S95: 0.41666667 | T95: 0.5 | U95: 0.5 | V95: 1
A96: VOY2026COFTN850 | B96: 46119 | C96: AVRIL | D96: 626tu203 | E96: hbib | F96: VOY2026COFTN850 | G96: SEBN (SUMITOMO) | H96: 626tu203 | J96: 1557 | L96: 14 | M96: 626tu203 | N96: hbib | O96: 0.54166667 | P96: 0.69097222 | Q96: 0.91666667 | R96: 0.90625 | S96: 0.9375 | T96: 0.024305556 | U96: 0.024305556 | V96: 1
